Workbook

Sheet Base de datos
A5: BASE DE DATOS DE CLIENTES
A7: No. | B7: PKA | C7: Apellidos | D7: Nombres | E7: Nombre Legal | F7: Grupo | G7: Fecha de Nacimiento | H7: Tipo de Servicio que le Brindamos | I7: Correo Electrónico | J7: Teléfono | K7: Artista | L7: Escritor | M7: Productor
A8: 1 | B8: Dayan | C8: Giler | D8: Dayan | E8: Dayan Giler | F8: X | I8: dayanmvpx@gmail.com | K8: X
A9: 2 | B9: Marval | C9: Marval Camero | D9: Luis Guillermo | E9: Luis Guillermo Marval Camero | F9: x | I9: Energymusicvzla@gmail.com | K9: X | L9: X
A10: =+A9+1 -> 3 | B10: Pantera | C10: Arteaga | D10: William | E10: William Arteaga | I10: williamjarteaga@gmail.com | L10: X
A11: =+A10+1 -> 4 | B11: Divino | C11: Velazquez | D11: Daniel | E11: Daniel Velazquez | K11: x
A12: =+A11+1 -> 5 | B12: Dimelo Super | C12: Perea Añez | D12: Jesus Alberto | E12: Jesus Alberto Perea Añez | F12: No | I12: dimelosuper@gmail.com | K12: ? | L12: ? | M12: ?
A13: =+A12+1 -> 6 | B13: SAINT LL | K13: x
A14: 7 | B14: Jordy Jill | C14: Valdivieso Duarte | D14: Jordy Camilo | E14: Jordy Camilo Valdivieso Duarte | I14: maribell.duarte@jordyjill.com | K14: x | L14: x
A15: =+A14+1 -> 8 | B15: Borngud | D15: Jhon Emanuel | E15: Jhon Emanuel | I15: borngud22@gmail.com | K15: x
A16: =+A15+1 -> 9 | B16: MaikyMove | C16: Sanchez | D16: Miguel Alejandro | E16: Miguel Alejandro Sanchez | I16: onlymaiky@gmail.com | K16: x
A17: =+A16+1 -> 10 | B17: Lanalizer | C17: Guzmán Velásquez | D17: Yan Carlo Francisco | E17: Yan Carlo Francisco Guzmán Velásquez | I17: lanalizerrecords@gmail.com | M17: x
A18: =+A17+1 -> 11 | B18: MozartMuzik | C18: Nizco Chaparro | D18: Jose Luis | E18: Jose Luis Nizco Chaparro | F18: x | I18: mozartmuzik2@gmail.com | M18: x
A19: =+A18+1 -> 12 | B19: Hache | C19: Taveras | D19: Bryan Argenis | E19: Bryan Argenis Taveras | I19: achebookings@gmail.com | K19: x | L19: x
A20: =+A19+1 -> 13 | B20: ErickAnt | C20: Celis Marin | D20: Erick Andres | E20: Erick Andres Celis Marin | F20: x | I20: Erickandrescm@gmail.com | M20: x
A21: 14 | B21: ECBY | C21: Campoverde | D21: Erick | E21: Erick Campoverde | F21: x | I21: contactoecby@gmail.com | M21: x
A22: 15 | B22: Jay Rozz | C22: Arias | D22: Juan | E22: Juan Arias | F22: x | I22: Jayrozzbooking@gmail.com | K22: x | L22: x
A23: =+A22+1 -> 16 | B23: Cubo | C23: Cuadrado | D23: Franklin | E23: Franklin Cuadrado | F23: x | I23: prodbycubo@gmail.com | M23: x
A24: =+A23+1 -> 17 | B24: Lennis Rodriguez | C24: Rodriguez | D24: Jorlennis | E24: Jorlennis Rodriguez | I24: info.lennis@gmail.com | K24: x

Sheet MODELO
B2: Artista:
B3: Nombre legal:
B4: Fecha de inicio: | E4: =MIN(Table1347[Fecha]) -> 0
B5: Fecha fin: | E5: =MAX(Table1347[Fecha]) -> 0
B7: ESTADO DE CUENTA
B8: Fecha | C8: Número | D8: Tipo | E8: Método de pago | F8: Nombre | G8: Concepto | H8: Valor de la Factura del Cliente | I8: Cargos Bancarios | J8: 50% Fee | K8: 20% Comisión | L8: 5% Legal | M8: Retención de Impuestos | N8: Pagado por MVPX | O8: Avance | P8: Balance
P9: =SUM(Table1347[[#This Row],[Valor de la Factura del Cliente]:[Avance]]) -> 0
P10: =SUM(Table1347[[#This Row],[Valor de la Factura del Cliente]:[Avance]])+P9 -> 0
P11: =SUM(Table1347[[#This Row],[Valor de la Factura del Cliente]:[Avance]])+P10 -> 0
P12: =SUM(Table1347[[#This Row],[Valor de la Factura del Cliente]:[Avance]])+P11 -> 0
P13: =SUM(Table1347[[#This Row],[Valor de la Factura del Cliente]:[Avance]])+P12 -> 0
P14: =SUM(Table1347[[#This Row],[Valor de la Factura del Cliente]:[Avance]])+P13 -> 0
P15: =SUM(Table1347[[#This Row],[Valor de la Factura del Cliente]:[Avance]])+P14 -> 0
P16: =SUM(Table1347[[#This Row],[Valor de la Factura del Cliente]:[Avance]])+P15 -> 0
P17: =SUM(Table1347[[#This Row],[Valor de la Factura del Cliente]:[Avance]])+P16 -> 0
P18: =SUM(Table1347[[#This Row],[Valor de la Factura del Cliente]:[Avance]])+P17 -> 0
P19: =SUM(Table1347[[#This Row],[Valor de la Factura del Cliente]:[Avance]])+P18 -> 0
P20: =SUM(Table1347[[#This Row],[Valor de la Factura del Cliente]:[Avance]])+P19 -> 0
P21: =SUM(Table1347[[#This Row],[Valor de la Factura del Cliente]:[Avance]])+P20 -> 0
... P38: =SUM(Table1347[[#This Row],[Valor de la Factura del Cliente]:[Avance]])+P37 -> 0
G39: TOTAL | H39: =SUBTOTAL(109,Table1347[Valor de la Factura del Cliente]) -> 0 | I39: =SUBTOTAL(109,Table1347[Cargos Bancarios]) -> 0 | K39: =SUBTOTAL(109,Table1347[20% Comisión]) -> 0 | L39: =SUBTOTAL(109,Table1347[5% Legal]) -> 0 | M39: =SUBTOTAL(109,Table1347[Retención de Impuestos]) -> 0 | N39: =SUBTOTAL(109,Table1347[Pagado por MVPX]) -> 0 | O39: =SUBTOTAL(109,Table1347[Avance]) -> 0 | P39: =+P38 -> 0

Sheet Jeidi
B2: Artista: | E2: Jeidi
B3: Nombre legal:
B4: Fecha de inicio: | E4: =MIN(Table134732[Fecha]) -> 45064
B5: Fecha fin: | E5: =MAX(Table134732[Fecha]) -> 45847
B7: ESTADO DE CUENTA
B8: Fecha | C8: Número | D8: Tipo | E8: Método de pago | F8: Nombre | G8: Concepto | H8: Valor de la Factura del Cliente | I8: Cargos Bancarios | J8: 50% Fee | K8: 20% Comisión | L8: 5% Legal | M8: Retención de Impuestos | N8: Pagado por MVPX | O8: Avance | P8: Balance
B9: Hasta el Q2 2024 BMI | G9: Ingresos de Bellakeo | H9: 23182 | N9: 0 | P9: =SUM(Table134732[[#This Row],[Valor de la Factura del Cliente]:[Avance]]) -> 23182
B10: 45064 | G10: Tema Loco si | N10: -333 | P10: =SUM(Table134732[[#This Row],[Valor de la Factura del Cliente]:[Avance]])+P9 -> 22849
B11: 45127 | G11: Avance | N11: -262.5 | P11: =SUM(Table134732[[#This Row],[Valor de la Factura del Cliente]:[Avance]])+P10 -> 22586.5
B12: 45128 | G12: Avance | N12: -700 | P12: =SUM(Table134732[[#This Row],[Valor de la Factura del Cliente]:[Avance]])+P11 -> 21886.5
B13: 45166 | G13: Avance | N13: -212.5 | P13: =SUM(Table134732[[#This Row],[Valor de la Factura del Cliente]:[Avance]])+P12 -> 21674
B14: 45170 | G14: Avance | N14: -230 | P14: =SUM(Table134732[[#This Row],[Valor de la Factura del Cliente]:[Avance]])+P13 -> 21444
B15: 45180 | G15: Avance | N15: -200 | P15: =SUM(Table134732[[#This Row],[Valor de la Factura del Cliente]:[Avance]])+P14 -> 21244
B16: 45187 | G16: Avance | N16: -100 | P16: =SUM(Table134732[[#This Row],[Valor de la Factura del Cliente]:[Avance]])+P15 -> 21144
B17: 45209 | G17: Avance | N17: -200 | P17: =SUM(Table134732[[#This Row],[Valor de la Factura del Cliente]:[Avance]])+P16 -> 20944
B18: 45209 | G18: Avance | N18: -100 | P18: =SUM(Table134732[[#This Row],[Valor de la Factura del Cliente]:[Avance]])+P17 -> 20844
B19: 45209 | G19: HECTOR NADIEL HURTADO | N19: -2000 | P19: =SUM(Table134732[[#This Row],[Valor de la Factura del Cliente]:[Avance]])+P18 -> 18844
B20: 45210 | G20: ELIAS AS YOUSEF | N20: -2000 | P20: =SUM(Table134732[[#This Row],[Valor de la Factura del Cliente]:[Avance]])+P19 -> 16844
B21: 45224 | G21: Avance (firma de jeidi) | N21: -3500 | P21: =SUM(Table134732[[#This Row],[Valor de la Factura del Cliente]:[Avance]])+P20 -> 13344
... B70: 45729 | G70: Elias Assy | N70: -100 | P70: =SUM(Table134732[[#This Row],[Valor de la Factura del Cliente]:[Avance]])+P69 -> -13716.36
B71: 45736 | G71: Pago de Contenido Autentico | H71: 400 | N71: 0 | P71: =SUM(Table134732[[#This Row],[Valor de la Factura del Cliente]:[Avance]])+P70 -> -13316.36
B72: 45740 | G72: Elias Assy | N72: -140 | P72: =SUM(Table134732[[#This Row],[Valor de la Factura del Cliente]:[Avance]])+P71 -> -13456.36
B73: 45740 | G73: Zenaida Duarte | N73: -260 | P73: =SUM(Table134732[[#This Row],[Valor de la Factura del Cliente]:[Avance]])+P72 -> -13716.36
B74: 45690 | G74: Airbnb on the Visa Expense | N74: -44.77 | P74: =SUM(Table134732[[#This Row],[Valor de la Factura del Cliente]:[Avance]])+P73 -> -13761.13
B75: 45804 | G75: Elias assy | N75: -450 | P75: =SUM(Table134732[[#This Row],[Valor de la Factura del Cliente]:[Avance]])+P74 -> -14211.13
B76: 45804 | G76: Pago en el Bofa | H76: 400 | N76: 0 | P76: =SUM(Table134732[[#This Row],[Valor de la Factura del Cliente]:[Avance]])+P75 -> -13811.13
B77: 45828 | G77: Wilman Henao | N77: -250 | P77: =SUM(Table134732[[#This Row],[Valor de la Factura del Cliente]:[Avance]])+P76 -> -14061.13
B78: 45831 | G78: Elias assy | N78: -250 | P78: =SUM(Table134732[[#This Row],[Valor de la Factura del Cliente]:[Avance]])+P77 -> -14311.13
B79: 45847 | G79: Michelle Flores | N79: -250 | P79: =SUM(Table134732[[#This Row],[Valor de la Factura del Cliente]:[Avance]])+P78 -> -14561.13
G80: TOTAL | H80: =SUBTOTAL(109,Table134732[Valor de la Factura del Cliente]) -> 23982 | I80: =SUBTOTAL(109,Table134732[Cargos Bancarios]) -> 0 | K80: =SUBTOTAL(109,Table134732[20% Comisión]) -> 0 | L80: =SUBTOTAL(109,Table134732[5% Legal]) -> 0 | M80: =SUBTOTAL(109,Table134732[Retención de Impuestos]) -> 0 | N80: =SUBTOTAL(109,Table134732[Pagado por MVPX]) -> -38543.13 | O80: =SUBTOTAL(109,Table134732[Avance]) -> 0 | P80: =+P79 -> -14561.13

Sheet Cesa Dajoy
B2: Artista: | E2: Cesar Dajoy
B3: Nombre legal:
B4: Fecha de inicio: | E4: =MIN(Table134731[Fecha]) -> 45657
B5: Fecha fin: | E5: =MAX(Table134731[Fecha]) -> 45771
B7: ESTADO DE CUENTA
B8: Fecha | C8: Número | D8: Tipo | E8: Método de pago | F8: Nombre | G8: Concepto | H8: Valor de la Factura del Cliente | I8: Cargos Bancarios | J8: 50% Fee | K8: 20% Comisión | L8: 5% Legal | M8: Retención de Impuestos | N8: Pagado por MVPX | O8: Avance | P8: Balance
B9: 45657 | F9: Ingrid Katherine | G9: Pagado a Ingrid Katherin Virviescas Valbuena por la Visa | N9: -345 | P9: =SUM(Table134731[[#This Row],[Valor de la Factura del Cliente]:[Avance]]) -> -345
B10: 45660 | F10: Wingo | G10: WINGO Gastos de Viaje | N10: -176.3 | P10: =SUM(Table134731[[#This Row],[Valor de la Factura del Cliente]:[Avance]])+P9 -> -521.3
B11: 45676 | F11: Avianca | G11: Vuelo MDE BOG | N11: -143.4 | P11: =SUM(Table134731[[#This Row],[Valor de la Factura del Cliente]:[Avance]])+P10 -> -664.7
B12: 45676 | F12: Expedia | G12: Travel Expense Hyaat Hotel Visa-CesarDajoy | N12: -63 | P12: =SUM(Table134731[[#This Row],[Valor de la Factura del Cliente]:[Avance]])+P11 -> -727.7
B13: 45686 | F13: Airbnb | G13: Pago de Airbnb Rozz, Jeidi, Dajoy | N13: -57.09 | P13: =SUM(Table134731[[#This Row],[Valor de la Factura del Cliente]:[Avance]])+P12 -> -784.79
B14: 45679 | F14: Airbnb | G14: Pago de Airbnb Rozz, Jeidi, Dajoy | N14: -100.80333 | P14: =SUM(Table134731[[#This Row],[Valor de la Factura del Cliente]:[Avance]])+P13 -> -885.59333
B15: 45690 | F15: Costco | G15: Pago de Comida Campamento PR | N15: -82.25 | P15: =SUM(Table134731[[#This Row],[Valor de la Factura del Cliente]:[Avance]])+P14 -> -967.84333
B16: 45690 | F16: Costco | G16: Pago de Comida Campamento PR | N16: -113.09 | P16: =SUM(Table134731[[#This Row],[Valor de la Factura del Cliente]:[Avance]])+P15 -> -1080.9333
B17: 45691 | F17: NewTasteChinese | G17: Pago de Comida Campamento PR | N17: -31.02 | P17: =SUM(Table134731[[#This Row],[Valor de la Factura del Cliente]:[Avance]])+P16 -> -1111.9533
B18: 45692 | F18: Costco | G18: Pago de Comida Campamento PR | N18: -62.66 | P18: =SUM(Table134731[[#This Row],[Valor de la Factura del Cliente]:[Avance]])+P17 -> -1174.6133
B19: 45690 | F19: Jetblue | G19: Boletos de Jet Blue | N19: -232.41 | P19: =SUM(Table134731[[#This Row],[Valor de la Factura del Cliente]:[Avance]])+P18 -> -1407.0233
B20: 45691 | F20: Jetblue | G20: Maletas de Jet Blue | N20: -70 | P20: =SUM(Table134731[[#This Row],[Valor de la Factura del Cliente]:[Avance]])+P19 -> -1477.0233
B21: 45692 | F21: Jetblue | G21: Boletos de Jet Blue | N21: -138.1 | P21: =SUM(Table134731[[#This Row],[Valor de la Factura del Cliente]:[Avance]])+P20 -> -1615.1233
... B27: 45690 | F27: Airbnb | G27: Airbnb Visa Appointment | N27: -44.77 | P27: =SUM(Table134731[[#This Row],[Valor de la Factura del Cliente]:[Avance]])+P26 -> -4788.3533
G28: TOTAL | H28: =SUBTOTAL(109,Table134731[Valor de la Factura del Cliente]) -> 0 | I28: =SUBTOTAL(109,Table134731[Cargos Bancarios]) -> 0 | K28: =SUBTOTAL(109,Table134731[20% Comisión]) -> 0 | L28: =SUBTOTAL(109,Table134731[5% Legal]) -> 0 | M28: =SUBTOTAL(109,Table134731[Retención de Impuestos]) -> 0 | N28: =SUBTOTAL(109,Table134731[Pagado por MVPX]) -> -4788.3533 | O28: =SUBTOTAL(109,Table134731[Avance]) -> 0 | P28: =+#REF! -> #REF!

Sheet ReneDaSilva
B2: Artista: | E2: Rene Da Silva
B3: Nombre legal:
B4: Fecha de inicio: | E4: =MIN(Table134730[Fecha]) -> 45676
B5: Fecha fin: | E5: =MAX(Table134730[Fecha]) -> 45819
B7: ESTADO DE CUENTA
B8: Fecha | C8: Número | D8: Tipo | E8: Método de pago | F8: Nombre | G8: Concepto | H8: Valor de la Factura del Cliente | I8: Cargos Bancarios | J8: 50% Fee | K8: 20% Comisión | L8: 5% Legal | M8: Retención de Impuestos | N8: Pagado por MVPX | O8: Avance | P8: Balance
B9: 45676 | F9: Avianca | G9: Vuelo Ida Y vuelta Colimbia Avianca | N9: 173.4 | P9: =SUM(Table134730[[#This Row],[Valor de la Factura del Cliente]:[Avance]]) -> 173.4
B10: 45677 | F10: Expedia | G10: Travel Expense Hyaat Hotel Visa- Rene Da Silva | N10: 89.76 | P10: =SUM(Table134730[[#This Row],[Valor de la Factura del Cliente]:[Avance]])+P9 -> 263.16
B11: 45697 | F11: COSTCO | G11: Gastos de Comida en Campamento PR | H11: 0 | N11: 82.25 | P11: =SUM(Table134730[[#This Row],[Valor de la Factura del Cliente]:[Avance]])+P10 -> 345.41
B12: 45703 | F12: COSTCO | G12: Gastos de Comida en Campamento PR | H12: 0 | N12: 113.09 | P12: =SUM(Table134730[[#This Row],[Valor de la Factura del Cliente]:[Avance]])+P11 -> 458.5
B13: 45690 | F13: JETBLUE | G13: Gastos de Transprte por Campamento | H13: 0 | N13: 232.41 | P13: =SUM(Table134730[[#This Row],[Valor de la Factura del Cliente]:[Avance]])+P12 -> 690.91
B14: 45690 | F14: JETBLUE | G14: Gastos de Transprte por Campamento | H14: 0 | N14: 138.1 | P14: =SUM(Table134730[[#This Row],[Valor de la Factura del Cliente]:[Avance]])+P13 -> 829.01
B15: 45691 | F15: NewTasteChinese | G15: Gastos de Comida en Campamento PR | H15: 0 | N15: 31.02 | P15: =SUM(Table134730[[#This Row],[Valor de la Factura del Cliente]:[Avance]])+P14 -> 860.03
B16: 45692 | F16: COSTCO | G16: Gastos de Comida en Campamento PR | H16: 0 | N16: 62.66 | P16: =SUM(Table134730[[#This Row],[Valor de la Factura del Cliente]:[Avance]])+P15 -> 922.69
B17: 45708 | F17: Spirit | G17: Vuelo SJU - FLL | N17: 150.99 | P17: =SUM(Table134730[[#This Row],[Valor de la Factura del Cliente]:[Avance]])+P16 -> 1073.68
B18: 45723 | F18: Tuyo | G18: Servicios de Producción de Tuyo - Marval | H18: -250 | N18: 0 | P18: =SUM(Table134730[[#This Row],[Valor de la Factura del Cliente]:[Avance]])+P17 -> 823.68
B19: 45733 | F19: Dynamic Records | G19: Ingreso Dynamic Records por la produccion del tema Mejor Que Tu | H19: -828.33333 | N19: 0 | P19: =SUM(Table134730[[#This Row],[Valor de la Factura del Cliente]:[Avance]])+P18 -> -4.6533333
B20: 45751 | F20: Iberia0151 | G20: Vuelo a Madrid-Medellin | H20: 0 | N20: 474.1 | P20: =SUM(Table134730[[#This Row],[Valor de la Factura del Cliente]:[Avance]])+P19 -> 469.44667
B21: 45760 | F21: Ryanair | G21: Vuelo Ibiza VLC | N21: 132.015 | P21: =SUM(Table134730[[#This Row],[Valor de la Factura del Cliente]:[Avance]])+P20 -> 601.46167
B22: 45819 | F22: DE TO | G22: Servicios de Producción de DE TO - Saint LL | H22: -300 | N22: 0 | P22: =SUM(Table134730[[#This Row],[Valor de la Factura del Cliente]:[Avance]])+P21 -> 301.46167
G23: TOTAL | H23: =SUBTOTAL(109,Table134730[Valor de la Factura del Cliente]) -> -1378.3333 | I23: =SUBTOTAL(109,Table134730[Cargos Bancarios]) -> 0 | K23: =SUBTOTAL(109,Table134730[20% Comisión]) -> 0 | L23: =SUBTOTAL(109,Table134730[5% Legal]) -> 0 | M23: =SUBTOTAL(109,Table134730[Retención de Impuestos]) -> 0 | N23: =SUBTOTAL(109,Table134730[Pagado por MVPX]) -> 1679.795 | O23: =SUBTOTAL(109,Table134730[Avance]) -> 0 | P23: =+#REF! -> #REF!

Sheet Jaime Hospedales
B2: Artista: | E2: Jaime Hospedales
B3: Nombre legal:
B4: Fecha de inicio: | E4: =MIN(Table134729[Fecha]) -> 45692
B5: Fecha fin: | E5: =MAX(Table134729[Fecha]) -> 45708
B7: ESTADO DE CUENTA
B8: Fecha | C8: Número | D8: Tipo | E8: Método de pago | F8: Nombre | G8: Concepto | H8: Valor de la Factura del Cliente | I8: Cargos Bancarios | J8: 50% Fee | K8: 20% Comisión | L8: 5% Legal | M8: Retención de Impuestos | N8: Pagado por MVPX | O8: Avance | P8: Balance
B9: 45697 | F9: COSTCO | G9: Gastos de Comida en Campamento PR | N9: -82.25 | P9: =SUM(Table134729[[#This Row],[Valor de la Factura del Cliente]:[Avance]]) -> -82.25
B10: 45703 | F10: COSTCO | G10: Gastos de Comida en Campamento PR | N10: -113.09 | P10: =SUM(Table134729[[#This Row],[Valor de la Factura del Cliente]:[Avance]])+P9 -> -195.34
B11: 45692 | F11: COSTCO | G11: Gastos de Comida en Campamento PR | N11: -62.66 | P11: =SUM(Table134729[[#This Row],[Valor de la Factura del Cliente]:[Avance]])+P10 -> -258
B12: 45704 | F12: COSTCO | G12: Gastos de Comida en Campamento PR | N12: -127.762 | P12: =SUM(Table134729[[#This Row],[Valor de la Factura del Cliente]:[Avance]])+P11 -> -385.762
B13: 45708 | F13: Spirit | G13: Vuelo San Juan - FLL | N13: -150.99 | P13: =SUM(Table134729[[#This Row],[Valor de la Factura del Cliente]:[Avance]])+P12 -> -536.752
G14: TOTAL | H14: =SUBTOTAL(109,Table134729[Valor de la Factura del Cliente]) -> 0 | I14: =SUBTOTAL(109,Table134729[Cargos Bancarios]) -> 0 | K14: =SUBTOTAL(109,Table134729[20% Comisión]) -> 0 | L14: =SUBTOTAL(109,Table134729[5% Legal]) -> 0 | M14: =SUBTOTAL(109,Table134729[Retención de Impuestos]) -> 0 | N14: =SUBTOTAL(109,Table134729[Pagado por MVPX]) -> -536.752 | O14: =SUBTOTAL(109,Table134729[Avance]) -> 0 | P14: =+#REF! -> #REF!

Sheet William Arteaga
B2: Artista:
B3: Nombre legal: | E3: William Arteaga
B4: Fecha de inicio: | E4: =MIN(Table134727[Fecha]) -> 45462
B5: Fecha fin: | E5: =MAX(Table134727[Fecha]) -> 45749
B7: ESTADO DE CUENTA
B8: Fecha | C8: Número | D8: Tipo | E8: Método de pago | F8: Nombre | G8: Concepto | H8: Valor de la Factura del Cliente | I8: Cargos Bancarios | J8: 50% Fee | K8: 20% Comisión | L8: 5% Legal | M8: Retención de Impuestos | N8: Pagado por MVPX | O8: Avance | P8: Balance
B9: 45462 | G9: Reseteo del Site Visa | O9: -20 | P9: =SUM(Table134727[[#This Row],[Valor de la Factura del Cliente]:[Avance]]) -> -20
B10: 45676 | F10: Taca Air | G10: Vuelo Colombia | O10: -143.4 | P10: =SUM(Table134727[[#This Row],[Valor de la Factura del Cliente]:[Avance]])+P9 -> -163.4
B11: 45690 | F11: Jet Blue | G11: Gastos de viaje | O11: -138.1 | P11: =SUM(Table134727[[#This Row],[Valor de la Factura del Cliente]:[Avance]])+P10 -> -301.5
B12: 45690 | F12: Jet Blue | G12: Gastos de viaje | O12: -232.41 | P12: =SUM(Table134727[[#This Row],[Valor de la Factura del Cliente]:[Avance]])+P11 -> -533.91
B13: 45690 | F13: Jet Blue | G13: Gastos de viaje | O13: -35 | P13: =SUM(Table134727[[#This Row],[Valor de la Factura del Cliente]:[Avance]])+P12 -> -568.91
B14: 45691 | F14: Costco | G14: Gastos de Comida Costco Camp PR | O14: -62.66 | P14: =SUM(Table134727[[#This Row],[Valor de la Factura del Cliente]:[Avance]])+P13 -> -631.57
B15: 45692 | F15: NewTasteChinese | G15: Gastos de Comida Costco Camp PR | O15: -31.02 | P15: =SUM(Table134727[[#This Row],[Valor de la Factura del Cliente]:[Avance]])+P14 -> -662.59
B16: 45697 | F16: Costco | G16: Gastos de Comida Costco Camp PR | O16: -82.25 | P16: =SUM(Table134727[[#This Row],[Valor de la Factura del Cliente]:[Avance]])+P15 -> -744.84
B17: 45703 | F17: Costco | G17: Gastos de Comida Costco Camp PR | O17: -113.09 | P17: =SUM(Table134727[[#This Row],[Valor de la Factura del Cliente]:[Avance]])+P16 -> -857.93
B18: 45749 | O18: -400 | P18: =SUM(Table134727[[#This Row],[Valor de la Factura del Cliente]:[Avance]])+P17 -> -1257.93
G19: TOTAL | H19: =SUBTOTAL(109,Table134727[Valor de la Factura del Cliente]) -> 0 | I19: =SUBTOTAL(109,Table134727[Cargos Bancarios]) -> 0 | K19: =SUBTOTAL(109,Table134727[20% Comisión]) -> 0 | L19: =SUBTOTAL(109,Table134727[5% Legal]) -> 0 | M19: =SUBTOTAL(109,Table134727[Retención de Impuestos]) -> 0 | N19: =SUBTOTAL(109,Table134727[Pagado por MVPX]) -> 0 | O19: =SUBTOTAL(109,Table134727[Avance]) -> -1257.93 | P19: =+#REF! -> #REF!

Sheet JayRozz
B2: Artista: | E2: JayRozz
B3: Nombre legal:
B4: Fecha de inicio: | E4: =MIN(Table134726[Fecha]) -> 45237
B5: Fecha fin: | E5: =MAX(Table134726[Fecha]) -> 45862
B7: ESTADO DE CUENTA
B8: Fecha | C8: Número | D8: Tipo | E8: Método de pago | F8: Nombre | G8: Concepto | H8: Valor de la Factura del Cliente | I8: Cargos Bancarios | J8: 50% Fee | K8: 20% Comisión | L8: 5% Legal | M8: Retención de Impuestos | N8: Pagado por MVPX | O8: Avance | P8: Balance
B9: 45856 | F9: Jaime Hospedales | G9: Adelantos a Jaime Hospedales | H9: 0 | I9: 0 | K9: 0 | L9: 0 | N9: 0 | O9: -536.752 | P9: =SUM(Table134726[[#This Row],[Cargos Bancarios]:[Avance]]) -> -536.752
B10: 45237 | F10: Nombre | G10: Adelanto Solicitado | H10: 0 | I10: 0 | K10: 0 | L10: 0 | N10: 0 | O10: -1000 | P10: =SUM(Table134726[[#This Row],[Cargos Bancarios]:[Avance]])+P9 -> -1536.752
B11: 45243 | F11: Jay Rozz | G11: Adelanto Solicitado | H11: 0 | I11: 0 | K11: 0 | L11: 0 | N11: 0 | O11: -4000 | P11: =SUM(Table134726[[#This Row],[Cargos Bancarios]:[Avance]])+P10 -> -5536.752
B12: 45287 | F12: Jay Rozz | G12: Adelanto Solicitado | H12: 0 | I12: 0 | K12: 0 | L12: 0 | N12: 0 | O12: -2000 | P12: =SUM(Table134726[[#This Row],[Cargos Bancarios]:[Avance]])+P11 -> -7536.752
B13: 45350 | F13: Jay Rozz | G13: Adelanto Solicitado | H13: 0 | I13: 0 | K13: 0 | L13: 0 | N13: 0 | O13: -11500 | P13: =SUM(Table134726[[#This Row],[Cargos Bancarios]:[Avance]])+P12 -> -19036.752
B14: 45369 | F14: Jay Rozz | G14: Adelanto Solicitado | H14: 0 | I14: 0 | K14: 0 | L14: 0 | N14: 0 | O14: -1000 | P14: =SUM(Table134726[[#This Row],[Cargos Bancarios]:[Avance]])+P13 -> -20036.752
B15: 45391 | F15: Jay Rozz | G15: Adelanto Solicitado | H15: 0 | I15: 0 | K15: 0 | L15: 0 | N15: 0 | O15: -300 | P15: =SUM(Table134726[[#This Row],[Cargos Bancarios]:[Avance]])+P14 -> -20336.752
B16: 45401 | F16: Jay Rozz | G16: Adelanto Solicitado | H16: 0 | I16: 0 | K16: 0 | L16: 0 | N16: 0 | O16: -200 | P16: =SUM(Table134726[[#This Row],[Cargos Bancarios]:[Avance]])+P15 -> -20536.752
B17: 45411 | F17: Jay Rozz | G17: Adelanto Solicitado | H17: 0 | I17: 0 | K17: 0 | L17: 0 | N17: 0 | O17: -500 | P17: =SUM(Table134726[[#This Row],[Cargos Bancarios]:[Avance]])+P16 -> -21036.752
B18: 45414 | F18: Pull&Bear | G18: Compra de Ropa | H18: 0 | I18: 0 | K18: 0 | L18: 0 | N18: 0 | O18: -115.48 | P18: =SUM(Table134726[[#This Row],[Cargos Bancarios]:[Avance]])+P17 -> -21152.232
B19: 45414 | F19: Rito y Monte MDE | G19: Comida en Colombia | H19: 0 | I19: 0 | K19: 0 | L19: 0 | N19: 0 | O19: -12.7 | P19: =SUM(Table134726[[#This Row],[Cargos Bancarios]:[Avance]])+P18 -> -21164.932
B20: 45414 | F20: Causa Poblado | G20: Comida en Colombia | H20: 0 | I20: 0 | K20: 0 | L20: 0 | N20: 0 | O20: -42.07 | P20: =SUM(Table134726[[#This Row],[Cargos Bancarios]:[Avance]])+P19 -> -21207.002
B21: 45424 | F21: AirBnB | G21: Pago de AirBnB Colombia | H21: 0 | I21: 0 | K21: 0 | L21: 0 | N21: 0 | O21: -216.565 | P21: =SUM(Table134726[[#This Row],[Cargos Bancarios]:[Avance]])+P20 -> -21423.567
... B45: 45509 | F45: Air Europa | G45: Pasaje de Regreso Madrid Venezuela | H45: 0 | I45: 0 | K45: 0 | L45: 0 | N45: 0 | O45: -432.55 | P45: =SUM(Table134726[[#This Row],[Cargos Bancarios]:[Avance]])+P44 -> -38776.399
B46: 45512 | F46: Jay Rozz | G46: Contrato Warner | H46: 200000 | I46: 0 | K46: -40000 | L46: -15000 | N46: 160000 | O46: 0 | P46: =SUM(Table134726[[#This Row],[Cargos Bancarios]:[Avance]])+P45-Table134726[[#This Row],[20% Comisión]] -> 106223.6
B47: 45515 | F47: Europa Air | G47: Madrid-Venezuela | H47: 0 | I47: 0 | K47: 0 | L47: 0 | N47: 0 | O47: -432.55 | P47: =SUM(Table134726[[#This Row],[Cargos Bancarios]:[Avance]])+P46 -> 105791.05
B48: 45516 | F48: Jay Rozz | G48: Adelanto Solicitado | H48: 0 | I48: 0 | K48: 0 | L48: 0 | N48: 0 | O48: -3500 | P48: =SUM(Table134726[[#This Row],[Cargos Bancarios]:[Avance]])+P47 -> 102291.05
B49: 45516 | F49: Jay Rozz | G49: Adelanto Solicitado | H49: 0 | I49: 0 | K49: 0 | L49: 0 | N49: 0 | O49: -1500 | P49: =SUM(Table134726[[#This Row],[Cargos Bancarios]:[Avance]])+P48 -> 100791.05
B50: 45522 | F50: Wingo | G50: Pasaje VEN-MED /MED-VEN (Cuñado Soccer) | H50: 0 | I50: 0 | K50: 0 | L50: 0 | N50: 0 | O50: -1544.54 | P50: =SUM(Table134726[[#This Row],[Cargos Bancarios]:[Avance]])+P49 -> 99246.511
B51: 45532 | F51: Jay Rozz | G51: Compra lo que quieras Corp | H51: 0 | I51: -25 | K51: 0 | L51: 0 | N51: 0 | O51: -3400 | P51: =SUM(Table134726[[#This Row],[Cargos Bancarios]:[Avance]])+P50 -> 95821.511
B52: 45532 | F52: Jay Rozz | G52: Compra lo que quieras Corp | H52: 0 | I52: -25 | K52: 0 | L52: 0 | N52: 0 | O52: -3500 | P52: =SUM(Table134726[[#This Row],[Cargos Bancarios]:[Avance]])+P51 -> 92296.511
B53: 45536 | F53: Airbnb | G53: Pago de Airbnb Medellin Colombia | H53: 0 | I53: 0 | K53: 0 | L53: 0 | N53: 0 | O53: -614 | P53: =SUM(Table134726[[#This Row],[Cargos Bancarios]:[Avance]])+P52 -> 91682.511
B54: 45536 | F54: Jay Rozz | G54: Adelanto Solicitado | H54: 0 | I54: 0 | K54: 0 | L54: 0 | N54: 0 | O54: -64600 | P54: =SUM(Table134726[[#This Row],[Cargos Bancarios]:[Avance]])+P53 -> 27082.511
B55: 45547 | F55: Jay Rozz | G55: Devolucion de Impuestos pagados en España | H55: 0 | I55: 0 | K55: 0 | L55: 0 | N55: 218.2 | O55: 0 | P55: =SUM(Table134726[[#This Row],[Cargos Bancarios]:[Avance]])+P54 -> 27300.711
B56: 45551 | F56: Jay Rozz | G56: Adelanto Solicitado | H56: 0 | I56: -25 | K56: 0 | L56: 0 | N56: 0 | O56: -3000 | P56: =SUM(Table134726[[#This Row],[Cargos Bancarios]:[Avance]])+P55 -> 24275.711
B57: 45554 | F57: Vueling Airlines | G57: Adelanto Solicitado | H57: 0 | I57: 0 | K57: 0 | L57: 0 | N57: 0 | O57: -2000 | P57: =SUM(Table134726[[#This Row],[Cargos Bancarios]:[Avance]])+P56 -> 22275.711
B58: 45568 | F58: Jay Rozz | G58: Adelanto Solicitado | H58: 0 | I58: 0 | K58: 0 | L58: 0 | N58: 0 | O58: -8497.46 | P58: =SUM(Table134726[[#This Row],[Cargos Bancarios]:[Avance]])+P57 -> 13778.251
... B61: 45666 | F61: Jay Rozz | G61: Adelanto Solicitado | H61: 0 | I61: 0 | K61: 0 | L61: 0 | N61: 0 | O61: -2500 | P61: =SUM(Table134726[[#This Row],[Cargos Bancarios]:[Avance]])+P60 -> 8433.2513
B62: 45674 | F62: Jay Rozz | G62: Contrato Warner Pago Pendiente 01/01/2025 | H62: 100000 | I62: 0 | K62: -20000 | L62: 0 | N62: 80000 | O62: 0 | P62: =SUM(Table134726[[#This Row],[Cargos Bancarios]:[Avance]])+P61-Table134726[[#This Row],[20% Comisión]] -> 88433.251
B63: 45675 | F63: Jay Rozz | G63: Hyatt BogotaConvention Center | H63: 0 | I63: 0 | K63: 0 | L63: 0 | N63: 0 | O63: -224.4 | P63: =SUM(Table134726[[#This Row],[Cargos Bancarios]:[Avance]])+P62 -> 88208.851
B64: 45676 | F64: Jay Rozz | G64: Pasaje Wingo de Caracas a Medellin | H64: 0 | I64: 0 | K64: 0 | L64: 0 | N64: 0 | O64: -176.3 | P64: =SUM(Table134726[[#This Row],[Cargos Bancarios]:[Avance]])+P63 -> 88032.551
B65: 45676 | F65: Taca Air | G65: Pasaje MDE BOG | H65: 0 | I65: 0 | K65: 0 | L65: 0 | N65: 0 | O65: -173.4 | P65: =SUM(Table134726[[#This Row],[Cargos Bancarios]:[Avance]])+P64 -> 87859.151
B66: 45677 | F66: Jay Rozz | G66: Pasaje de Avianca Medellin a Bogota (Pantera) | H66: 0 | I66: 0 | K66: 0 | L66: 0 | N66: 0 | O66: -143.4 | P66: =SUM(Table134726[[#This Row],[Cargos Bancarios]:[Avance]])+P65 -> 87715.751
B67: 45677 | F67: Jay Rozz | G67: Pasaje de Avianca Medellin a Bogota | H67: 0 | I67: 0 | K67: 0 | L67: 0 | N67: 0 | O67: -173.4 | P67: =SUM(Table134726[[#This Row],[Cargos Bancarios]:[Avance]])+P66 -> 87542.351
B68: 45677 | F68: Expedia | G68: Travel Expense Hyaat Hotel Visa-Jay Rozz - William Arteaga | H68: 0 | I68: 0 | K68: 0 | L68: 0 | N68: 0 | O68: -179.52 | P68: =SUM(Table134726[[#This Row],[Cargos Bancarios]:[Avance]])+P67 -> 87362.831
B69: 45679 | F69: Airbnb | G69: Pago de estadia Dajoy - Jeidi - Rozz | H69: 0 | I69: 0 | K69: 0 | L69: 0 | N69: 0 | O69: -100.80333 | P69: =SUM(Table134726[[#This Row],[Cargos Bancarios]:[Avance]])+P68 -> 87262.028
B70: 45679 | F70: Jay Rozz | G70: Adelanto Solicitado | H70: 0 | I70: 0 | K70: 0 | L70: 0 | N70: 0 | O70: -20000 | P70: =SUM(Table134726[[#This Row],[Cargos Bancarios]:[Avance]])+P69 -> 67262.028
B71: 45679 | F71: Airbnb | G71: Pago de estadia Dajoy - Jeidi - Rozz | H71: 0 | I71: 0 | K71: 0 | L71: 0 | N71: 0 | O71: -57.09 | P71: =SUM(Table134726[[#This Row],[Cargos Bancarios]:[Avance]])+P70 -> 67204.938
B72: 45684 | F72: Jay Rozz | G72: Adelanto Solicitado | H72: 0 | I72: 0 | K72: 0 | L72: 0 | N72: 0 | O72: -300 | P72: =SUM(Table134726[[#This Row],[Cargos Bancarios]:[Avance]])+P71 -> 66904.938
B73: 45689 | F73: AIRBNB | G73: AIRBNB VISA APPOINTMENT | H73: 0 | I73: 0 | K73: 0 | L73: 0 | N73: 0 | O73: -44.77 | P73: =SUM(Table134726[[#This Row],[Cargos Bancarios]:[Avance]])+P72 -> 66860.168
B74: 45690 | F74: JETBLUE 2797203672135 | G74: Gastos de Viaje Jay Rozz | H74: 0 | I74: 0 | K74: 0 | L74: 0 | N74: 0 | O74: -232.41 | P74: =SUM(Table134726[[#This Row],[Cargos Bancarios]:[Avance]])+P73 -> 66627.758
... B89: 45762 | F89: Plus Ultra | G89: Vuelo Caracas Madrid - La Toxica | H89: 0 | I89: 0 | K89: 0 | L89: 0 | N89: 0 | O89: -805.55 | P89: =SUM(Table134726[[#This Row],[Cargos Bancarios]:[Avance]])+P88 -> 46443.816
B90: 45768 | F90: Corporate Fillings | G90: Preparacion de Documentación de JROZZ LLC | I90: 0 | K90: 0 | L90: 0 | N90: 0 | O90: -19.99 | P90: =SUM(Table134726[[#This Row],[Cargos Bancarios]:[Avance]])+P89 -> 46423.826
B91: 45776 | F91: Air Europa | G91: Pagp de Vuelo - La Toxica | H91: 0 | I91: 0 | K91: 0 | L91: 0 | N91: 0 | O91: -323.44 | P91: =SUM(Table134726[[#This Row],[Cargos Bancarios]:[Avance]])+P90 -> 46100.386
B92: 45856 | F92: Jay Rozz | G92: Retencion de Ingresos de Bellakeo | H92: 0 | I92: 0 | K92: 0 | L92: 0 | N92: 0 | O92: -23182 | P92: =SUM(Table134726[[#This Row],[Cargos Bancarios]:[Avance]])+P91 -> 22918.386
B93: 45787 | F93: Jay Rozz | G93: Retencion de Gastos Legales de Bellakeo | H93: 0 | I93: 0 | K93: 0 | L93: 0 | N93: 0 | O93: -7500 | P93: =SUM(Table134726[[#This Row],[Cargos Bancarios]:[Avance]])+P92 -> 15418.386
B94: 45790 | F94: Jay Rozz | G94: Adelanto Solicitado | H94: 0 | I94: 0 | K94: 0 | L94: 0 | N94: 0 | O94: -10000 | P94: =SUM(Table134726[[#This Row],[Cargos Bancarios]:[Avance]])+P93 -> 5418.386
B95: 45804 | F95: Iberia | G95: Travel Expense Iriannys Pinzon (La Toxica) | H95: 0 | I95: 0 | K95: 0 | L95: 0 | N95: 0 | O95: -131.12 | P95: =SUM(Table134726[[#This Row],[Cargos Bancarios]:[Avance]])+P94 -> 5287.266
B96: 45805 | F96: Air Europa | G96: Travel Expense Juan Arias (Rozz) | H96: 0 | I96: 0 | K96: 0 | L96: 0 | N96: 0 | O96: -176.34 | P96: =SUM(Table134726[[#This Row],[Cargos Bancarios]:[Avance]])+P95 -> 5110.926
B97: 45828 | F97: Deposito Rozz | G97: Rozz Deposito en el Bofa | H97: 3000 | I97: 0 | K97: 0 | L97: 0 | N97: 3000 | O97: 0 | P97: =SUM(Table134726[[#This Row],[Cargos Bancarios]:[Avance]])+P96 -> 8110.926
B98: 45828 | F98: Diana Luz Vasquez | G98: Pago de estadia para Campamento en Colombia Vía Remitly | H98: 0 | I98: 0 | K98: 0 | L98: 0 | N98: 0 | O98: -2740 | P98: =SUM(Table134726[[#This Row],[Cargos Bancarios]:[Avance]])+P97 -> 5370.926
B99: 45862 | F99: Jay Rozz | G99: Adelanto Solicitado | H99: 0 | I99: 0 | K99: 0 | L99: 0 | N99: 0 | O99: -1870.93 | P99: =SUM(Table134726[[#This Row],[Cargos Bancarios]:[Avance]])+P98 -> 3499.996
B100: 45862 | F100: Jay Rozz | G100: Adelanto Solicitado | H100: 0 | I100: 0 | K100: 0 | L100: 0 | N100: 0 | O100: -3500 | P100: =SUM(Table134726[[#This Row],[Cargos Bancarios]:[Avance]])+P99 -> -0.004
G101: TOTAL | H101: =SUBTOTAL(109,Table134726[Valor de la Factura del Cliente]) -> 303000 | I101: =SUBTOTAL(109,Table134726[Cargos Bancarios]) -> -75 | K101: =SUBTOTAL(109,Table134726[20% Comisión]) -> -60000 | L101: =SUBTOTAL(109,Table134726[5% Legal]) -> -15000 | M101: =SUBTOTAL(109,Table134726[Retención de Impuestos]) -> 0 | N101: =SUBTOTAL(109,Table134726[Pagado por MVPX]) -> 243218.2 | O101: =SUBTOTAL(109,Table134726[Avance]) -> -228143.2 | P101: =+P100 -> -0.004

Sheet Marval
B2: Artista: | E2: Marval
B3: Nombre legal: | E3: Luis Marval
B4: Fecha de inicio: | E4: =MIN(Table134725[Fecha]) -> 45056
B5: Fecha fin: | E5: =MAX(Table134725[Fecha]) -> 45938
B7: ESTADO DE CUENTA
B8: Fecha | C8: Número | D8: Tipo | E8: Método de pago | F8: Nombre | G8: Concepto | H8: Valor de la Factura del Cliente | I8: Cargos Bancarios | J8: 50% Fee | K8: 20% Comisión | L8: 5% Legal | M8: Retención de Impuestos | N8: Pagado por MVPX | O8: Avance | P8: Balance
B9: x | F9: William Arteaga | G9: Gastos del Team Marval | N9: -1257.93 | P9: =SUM(Table134725[[#This Row],[Valor de la Factura del Cliente]:[Avance]]) -> -1257.93
B10: x | F10: Rene Da Silva | G10: Gastos del Team Marval | N10: -301.46167 | P10: =SUM(Table134725[[#This Row],[Valor de la Factura del Cliente]:[Avance]])+P9 -> -1559.3917
B11: x | F11: Cesar Dajoy | G11: Gastos del Team Marval | N11: -4788.3533 | P11: =SUM(Table134725[[#This Row],[Valor de la Factura del Cliente]:[Avance]])+P10 -> -6347.745
B12: 45056 | F12: Expedia | G12: Compra de Boleto para ir a Colombia | N12: -560 | P12: =SUM(Table134725[[#This Row],[Valor de la Factura del Cliente]:[Avance]])+P11 -> -6907.745
B13: 45097 | F13: Satena Bogota | G13: ADELANTO A RECUPERAR | N13: -391.01 | P13: =SUM(Table134725[[#This Row],[Valor de la Factura del Cliente]:[Avance]])+P12 -> -7298.755
B14: 45128 | F14: Luis Enrique Marval Paypal | G14: Adelanto a Recuperar | N14: -1000 | P14: =SUM(Table134725[[#This Row],[Valor de la Factura del Cliente]:[Avance]])+P13 -> -8298.755
B15: 45153 | F15: Luis Enrique Marval Paypal | G15: Adelanto a Recuperar | N15: -1000 | P15: =SUM(Table134725[[#This Row],[Valor de la Factura del Cliente]:[Avance]])+P14 -> -9298.755
B16: 45166 | F16: Godaddy luar lo pago | G16: Costo del dominio de MARVAL (macaiasongs.com) | N16: -66.22 | P16: =SUM(Table134725[[#This Row],[Valor de la Factura del Cliente]:[Avance]])+P15 -> -9364.975
B17: 45165 | F17: Coorporate Filing LLC | G17: Coorporate Filing | N17: -244 | P17: =SUM(Table134725[[#This Row],[Valor de la Factura del Cliente]:[Avance]])+P16 -> -9608.975
B18: 45175 | F18: Coorporate Filing LLC | G18: Amendment filing | N18: -125 | P18: =SUM(Table134725[[#This Row],[Valor de la Factura del Cliente]:[Avance]])+P17 -> -9733.975
B19: 45183 | F19: PAYPAL | G19: ADELANTO A RECUPERAR | N19: -2000 | P19: =SUM(Table134725[[#This Row],[Valor de la Factura del Cliente]:[Avance]])+P18 -> -11733.975
B20: 45184 | F20: PAYPAL | G20: Adelanto del contrato de Productor a Jeidi | N20: -7000 | P20: =SUM(Table134725[[#This Row],[Valor de la Factura del Cliente]:[Avance]])+P19 -> -18733.975
B21: 45211 | F21: Marval | G21: Marval Advanced | N21: -1000 | P21: =SUM(Table134725[[#This Row],[Valor de la Factura del Cliente]:[Avance]])+P20 -> -19733.975
B22: 45218 | F22: Microsoft- Discover | G22: Email Plus Expense (MicaiaSongs) | N22: -21.43 | P22: =SUM(Table134725[[#This Row],[Valor de la Factura del Cliente]:[Avance]])+P21 -> -19755.405
B23: 45219 | F23: Mr Marval | G23: Adelanto al Padre de Marval | N23: -9000 | P23: =SUM(Table134725[[#This Row],[Valor de la Factura del Cliente]:[Avance]])+P22 -> -28755.405
B24: 45226 | F24: Coorporate Filing LLC | G24: Coorporate Filing | N24: -9 | P24: =SUM(Table134725[[#This Row],[Valor de la Factura del Cliente]:[Avance]])+P23 -> -28764.405
B25: 45238 | G25: Advanced Payment | N25: -8100 | P25: =SUM(Table134725[[#This Row],[Valor de la Factura del Cliente]:[Avance]])+P24 -> -36864.405
B26: 45244 | F26: Luigi SCALETTA | G26: Avance Marval Compra de Computadora | N26: -1315 | P26: =SUM(Table134725[[#This Row],[Valor de la Factura del Cliente]:[Avance]])+P25 -> -38179.405
B27: 45265 | G27: Pasaje de MDE (Colombia) - CCS (Venezuela) | N27: -615 | P27: =SUM(Table134725[[#This Row],[Valor de la Factura del Cliente]:[Avance]])+P26 -> -38794.405
B28: 45266 | G28: Total Recibido a la fecha | H28: 125000 | N28: 0 | P28: =SUM(Table134725[[#This Row],[Valor de la Factura del Cliente]:[Avance]])+P27 -> 86205.595
G29: Pagado a Matt Greenberg (Legal Services Contrato Pub) | N29: -17500 | P29: =SUM(Table134725[[#This Row],[Valor de la Factura del Cliente]:[Avance]])+P28 -> 68705.595
G30: Pago del asesoramiento 10% | N30: -36000 | P30: =SUM(Table134725[[#This Row],[Valor de la Factura del Cliente]:[Avance]])+P29 -> 32705.595
G31: Dimelo Super | N31: -36000 | P31: =SUM(Table134725[[#This Row],[Valor de la Factura del Cliente]:[Avance]])+P30 -> -3294.405
B32: 45267 | G32: Avance | N32: -3053.34 | P32: =SUM(Table134725[[#This Row],[Valor de la Factura del Cliente]:[Avance]])+P31 -> -6347.745
B33: 45299 | F33: Zelle | G33: Advanced Payment | N33: -3000 | P33: =SUM(Table134725[[#This Row],[Valor de la Factura del Cliente]:[Avance]])+P32 -> -9347.745
B34: 45329 | F34: Zelle | G34: Avance | N34: -1000 | P34: =SUM(Table134725[[#This Row],[Valor de la Factura del Cliente]:[Avance]])+P33 -> -10347.745
B35: 45344 | F35: Zelle | G35: Avance | N35: -1000 | P35: =SUM(Table134725[[#This Row],[Valor de la Factura del Cliente]:[Avance]])+P34 -> -11347.745
B36: 45360 | F36: Zelle | G36: Pago por la empresa de MICAIA SONGS | N36: -238.75 | P36: =SUM(Table134725[[#This Row],[Valor de la Factura del Cliente]:[Avance]])+P35 -> -11586.495
B37: 45369 | F37: Zelle | G37: Adelanto de Video | N37: -750 | P37: =SUM(Table134725[[#This Row],[Valor de la Factura del Cliente]:[Avance]])+P36 -> -12336.495
B38: 45379 | F38: Zelle | G38: Adelanto de Video | N38: -1500 | P38: =SUM(Table134725[[#This Row],[Valor de la Factura del Cliente]:[Avance]])+P37 -> -13836.495
B39: 45398 | F39: Zelle | G39: Advanced Payment | N39: -1000 | P39: =SUM(Table134725[[#This Row],[Valor de la Factura del Cliente]:[Avance]])+P38 -> -14836.495
B40: 45414 | F40: Capital One | G40: Comida en Colombia | N40: -42.05 | P40: =SUM(Table134725[[#This Row],[Valor de la Factura del Cliente]:[Avance]])+P39 -> -14878.545
B41: 45423 | F41: Capital One | G41: AirBnB en Colombia | N41: -216.565 | P41: =SUM(Table134725[[#This Row],[Valor de la Factura del Cliente]:[Avance]])+P40 -> -15095.11
B42: 45434 | F42: Capital One | G42: Pago de AirBnB en Colombia | N42: -287.11 | P42: =SUM(Table134725[[#This Row],[Valor de la Factura del Cliente]:[Avance]])+P41 -> -15382.22
B43: 45440 | F43: Zelle | G43: Avance | N43: -1000 | P43: =SUM(Table134725[[#This Row],[Valor de la Factura del Cliente]:[Avance]])+P42 -> -16382.22
B44: 45445 | F44: Zelle | G44: VISA MARVAL PAGO A BILL MARTINEZ | N44: -5685 | P44: =SUM(Table134725[[#This Row],[Valor de la Factura del Cliente]:[Avance]])+P43 -> -22067.22
B45: 45461 | F45: Deposit Warner Music | G45: Deposit Warner Music | H45: 235000 | N45: 0 | P45: =SUM(Table134725[[#This Row],[Valor de la Factura del Cliente]:[Avance]])+P44 -> 212932.78
B46: 45463 | F46: Zelle Luis Enrique | G46: Avance | N46: -1300 | P46: =SUM(Table134725[[#This Row],[Valor de la Factura del Cliente]:[Avance]])+P45 -> 211632.78
B47: 45463 | F47: Zelle Natalia Romero | G47: Pasaje Madrid | N47: -685 | P47: =SUM(Table134725[[#This Row],[Valor de la Factura del Cliente]:[Avance]])+P46 -> 210947.78
B48: 45467 | F48: Zelle Luis Enrique | G48: Avance | N48: -2000 | P48: =SUM(Table134725[[#This Row],[Valor de la Factura del Cliente]:[Avance]])+P47 -> 208947.78
B49: 45467 | F49: Zelle Luis Enrique | G49: Avance | N49: -700 | P49: =SUM(Table134725[[#This Row],[Valor de la Factura del Cliente]:[Avance]])+P48 -> 208247.78
B50: 45478 | F50: Zelle Luis Enrique | G50: Avance | N50: -1200 | P50: =SUM(Table134725[[#This Row],[Valor de la Factura del Cliente]:[Avance]])+P49 -> 207047.78
B51: 45481 | F51: Europa Air | G51: Pasaje de Madrid a Amsterdam | N51: -224.1 | P51: =SUM(Table134725[[#This Row],[Valor de la Factura del Cliente]:[Avance]])+P50 -> 206823.68
B52: 45481 | F52: Zelle Luis Enrique | G52: Avance | N52: -1300 | P52: =SUM(Table134725[[#This Row],[Valor de la Factura del Cliente]:[Avance]])+P51 -> 205523.68
B53: 45484 | F53: Zelle Luis Enrique | N53: -2000 | P53: =SUM(Table134725[[#This Row],[Valor de la Factura del Cliente]:[Avance]])+P52 -> 203523.68
B54: 45488 | F54: Booking.com | G54: Gasto de Hotel en el Campamento de España (El Mariot) | N54: -1391.96 | P54: =SUM(Table134725[[#This Row],[Valor de la Factura del Cliente]:[Avance]])+P53 -> 202131.72
B55: 45494 | F55: El Molino | G55: Comida Grupal | N55: -52.046 | P55: =SUM(Table134725[[#This Row],[Valor de la Factura del Cliente]:[Avance]])+P54 -> 202079.67
B56: 45494 | F56: Media Market | G56: Compra de Disco Duro | N56: -171.72 | P56: =SUM(Table134725[[#This Row],[Valor de la Factura del Cliente]:[Avance]])+P55 -> 201907.95
B57: 45494 | F57: El Moli Menjars Valencians | G57: Se divide entre 5, marval, rozz, super y 2 de lopez | N57: -52.056 | P57: =SUM(Table134725[[#This Row],[Valor de la Factura del Cliente]:[Avance]])+P56 -> 201855.9
B58: 45502 | F58: Sesion en Madrid | G58: Gastos Asumidos por la Cancelación de la Sesion | N58: -75.11 | P58: =SUM(Table134725[[#This Row],[Valor de la Factura del Cliente]:[Avance]])+P57 -> 201780.79
B59: 45502 | F59: Gasoleos del Levante | G59: Gasolina en Valencia (42.62 Se dividio entre 3) | N59: -14.206667 | P59: =SUM(Table134725[[#This Row],[Valor de la Factura del Cliente]:[Avance]])+P58 -> 201766.58
B60: 45502 | F60: El Rincon de Maria | G60: Comida en España entre Rozz, Super, Lopez y Marval | N60: -61.6725 | P60: =SUM(Table134725[[#This Row],[Valor de la Factura del Cliente]:[Avance]])+P59 -> 201704.91
B61: 45506 | F61: Aroma De Mar | G61: Comida en España entre Rozz, Super, Lopez y Marval | N61: -65.5125 | P61: =SUM(Table134725[[#This Row],[Valor de la Factura del Cliente]:[Avance]])+P60 -> 201639.4
B62: 45507 | F62: Estacion Principe | G62: Comida en España Buffet Chino | N62: -17.46 | P62: =SUM(Table134725[[#This Row],[Valor de la Factura del Cliente]:[Avance]])+P61 -> 201621.94
B63: 45509 | F63: Avianca | G63: Pasaje Madrid-Colombia | N63: -836.8 | P63: =SUM(Table134725[[#This Row],[Valor de la Factura del Cliente]:[Avance]])+P62 -> 200785.14
B64: 45515 | F64: Remitly | G64: Pagado a Luis Marval Vía Remitly | N64: -3000 | P64: =SUM(Table134725[[#This Row],[Valor de la Factura del Cliente]:[Avance]])+P63 -> 197785.14
B65: 45515 | F65: Avianca | G65: Pago de Maleta Adicional de Madrid a MDE | N65: -218.64 | P65: =SUM(Table134725[[#This Row],[Valor de la Factura del Cliente]:[Avance]])+P64 -> 197566.5
... B109: 45731 | F109: Remitly | G109: Avance | N109: -203.99 | P109: =SUM(Table134725[[#This Row],[Valor de la Factura del Cliente]:[Avance]])+P108 -> 121301.58
B110: 45733 | F110: Dinamic Records | G110: Pago por Produccion del tema Mejor que tu | H110: 828.33333 | K110: =-Table134725[[#This Row],[Valor de la Factura del Cliente]]*0.2 -> -165.66667 | L110: =-Table134725[[#This Row],[Valor de la Factura del Cliente]]*0.05 -> -41.416667 | N110: 0 | P110: =SUM(Table134725[[#This Row],[Valor de la Factura del Cliente]:[Avance]])+P109 -> 121922.83
B111: 45734 | F111: Iberia | G111: Travel Expense Mia - Ibiza | N111: -642.535 | P111: =SUM(Table134725[[#This Row],[Valor de la Factura del Cliente]:[Avance]])+P110 -> 121280.29
B112: 45740 | F112: Vintage Kings | G112: Neumann U 87 AI Set Z | N112: -4012 | P112: =SUM(Table134725[[#This Row],[Valor de la Factura del Cliente]:[Avance]])+P111 -> 117268.29
B113: 45741 | F113: Iberia Air | G113: Madrid Ibiza | N113: -66.3 | P113: =SUM(Table134725[[#This Row],[Valor de la Factura del Cliente]:[Avance]])+P112 -> 117201.99
B114: 45742 | F114: Coorporate Filing | G114: Gastos del departamento de estado de la empresa MICAIA SONGS | N114: -239 | P114: =SUM(Table134725[[#This Row],[Valor de la Factura del Cliente]:[Avance]])+P113 -> 116962.99
B115: 45760 | F115: air europa | G115: Pago de Madrid a Caracas Ven 2 boletos - Marval - Jade | N115: -792.5 | P115: =SUM(Table134725[[#This Row],[Valor de la Factura del Cliente]:[Avance]])+P114 -> 116170.49
B116: 45760 | F116: Iberia | G116: Pago por equipaje | N116: -122.3 | P116: =SUM(Table134725[[#This Row],[Valor de la Factura del Cliente]:[Avance]])+P115 -> 116048.19
B117: 45803 | F117: Avianca | G117: Gastos de Viave | N117: -93.1 | P117: =SUM(Table134725[[#This Row],[Valor de la Factura del Cliente]:[Avance]])+P116 -> 115955.09
B118: 45805 | F118: JetBlue | G118: Pasajes Medellin Florida | N118: -305.11 | P118: =SUM(Table134725[[#This Row],[Valor de la Factura del Cliente]:[Avance]])+P117 -> 115649.98
B119: 45807 | F119: JetBlue | G119: Pasajes Medellin Florida | N119: -317.91 | P119: =SUM(Table134725[[#This Row],[Valor de la Factura del Cliente]:[Avance]])+P118 -> 115332.07
B120: 45838 | F120: Adelanto vía Zelle | G120: Adelanto vía Zelle Marval | N120: -3000 | P120: =SUM(Table134725[[#This Row],[Valor de la Factura del Cliente]:[Avance]])+P119 -> 112332.07
B121: 45874 | F121: Adelanto vía Zelle | G121: Adelanto vía Zelle Marval | N121: -2100 | P121: =SUM(Table134725[[#This Row],[Valor de la Factura del Cliente]:[Avance]])+P120 -> 110232.07
B122: 45873 | F122: Adelanto vía Zelle | G122: Adelanto vía Zelle Marval | N122: -900 | P122: =SUM(Table134725[[#This Row],[Valor de la Factura del Cliente]:[Avance]])+P121 -> 109332.07
... B125: 45938 | F125: Adelanto vía Zelle | G125: Adelanto vía Zelle Marval | N125: -3000 | P125: =SUM(Table134725[[#This Row],[Valor de la Factura del Cliente]:[Avance]])+P124 -> 101872.47
P126: =SUM(Table134725[[#This Row],[Valor de la Factura del Cliente]:[Avance]])+P125 -> 101872.47
G127: TOTAL | H127: =SUBTOTAL(109,Table134725[Valor de la Factura del Cliente]) -> 360828.33 | I127: =SUBTOTAL(109,Table134725[Cargos Bancarios]) -> 0 | K127: =SUBTOTAL(109,Table134725[20% Comisión]) -> -165.66667 | L127: =SUBTOTAL(109,Table134725[5% Legal]) -> -41.416667 | M127: =SUBTOTAL(109,Table134725[Retención de Impuestos]) -> 0 | N127: =SUBTOTAL(109,Table134725[Pagado por MVPX]) -> -258748.78 | O127: =SUBTOTAL(109,Table134725[Avance]) -> 0 | P127: =+P126 -> 101872.47

Sheet Dimelo Super
B2: Artista: | E2: Dimelo Super
B3: Nombre legal: | E3: Jesus Perea
B4: Fecha de inicio: | E4: =MIN(Table134724[Fecha]) -> 45109
B5: Fecha fin: | E5: =MAX(Table134724[Fecha]) -> 45665
B7: ESTADO DE CUENTA
B8: Fecha | C8: Número | D8: Tipo | E8: Método de pago | F8: Nombre | G8: Concepto | H8: Valor de la Factura del Cliente | I8: Cargos Bancarios | J8: 50% Fee | K8: 20% Comisión | L8: 5% Legal | M8: Retención de Impuestos | N8: Pagado por MVPX | O8: Avance | P8: Balance
G9: Ingreso del 10% del contrato de Marval | H9: 36500 | P9: =SUM(Table134724[[#This Row],[Valor de la Factura del Cliente]:[Avance]]) -> 36500
G10: Ingreso del 10% del contrato de JROZZ | H10: 30000 | P10: =SUM(Table134724[[#This Row],[Valor de la Factura del Cliente]:[Avance]])+P9 -> 66500
G11: Ingreso del 10% del contrato de JROZZ bmi | H11: 12500 | P11: =SUM(Table134724[[#This Row],[Valor de la Factura del Cliente]:[Avance]])+P10 -> 79000
G12: Pagado por Servicios de ECBY | N12: -1000 | P12: =SUM(Table134724[[#This Row],[Valor de la Factura del Cliente]:[Avance]])+P11 -> 78000
B13: 45109 | F13: Dimelo Super | G13: Avance Solicitado | I13: -7.99 | N13: -800 | P13: =SUM(Table134724[[#This Row],[Valor de la Factura del Cliente]:[Avance]])+P12 -> 77192.01
B14: 45139 | F14: Dimelo Super | G14: Avance Solicitado | I14: -7.99 | N14: -800 | P14: =SUM(Table134724[[#This Row],[Valor de la Factura del Cliente]:[Avance]])+P13 -> 76384.02
B15: 45175 | F15: Dimelo Super | G15: Avance Solicitado | I15: -7.99 | N15: -800 | P15: =SUM(Table134724[[#This Row],[Valor de la Factura del Cliente]:[Avance]])+P14 -> 75576.03
B16: 45191 | F16: Dimelo Super | G16: Avance Solicitado | I16: -7.99 | N16: -800 | P16: =SUM(Table134724[[#This Row],[Valor de la Factura del Cliente]:[Avance]])+P15 -> 74768.04
B17: 45233 | F17: Dimelo Super | G17: Avance Solicitado | I17: -7.99 | N17: -800 | P17: =SUM(Table134724[[#This Row],[Valor de la Factura del Cliente]:[Avance]])+P16 -> 73960.05
B18: 45233 | F18: Dimelo Super | G18: Avance Solicitado | I18: -25 | N18: -5000 | P18: =SUM(Table134724[[#This Row],[Valor de la Factura del Cliente]:[Avance]])+P17 -> 68935.05
B19: 45278 | F19: Dimelo Super | G19: Avance Solicitado | I19: -7.99 | N19: -1000 | P19: =SUM(Table134724[[#This Row],[Valor de la Factura del Cliente]:[Avance]])+P18 -> 67927.06
B20: 45279 | F20: Dimelo Super | G20: Avance Solicitado | I20: -25 | N20: -5000 | P20: =SUM(Table134724[[#This Row],[Valor de la Factura del Cliente]:[Avance]])+P19 -> 62902.06
B21: 45414 | F21: Causa Poblado | G21: Meal Covered | N21: -42.05 | P21: =SUM(Table134724[[#This Row],[Valor de la Factura del Cliente]:[Avance]])+P20 -> 62860.01
B22: 45464 | F22: Natalia Romero | G22: Pasajes Cubiertos, Juan Arias y Jerus Perea 1380 Natalia Romero | N22: -690 | P22: =SUM(Table134724[[#This Row],[Valor de la Factura del Cliente]:[Avance]])+P21 -> 62170.01
B23: 45486 | F23: EuropaAir | G23: Europa Air - Gastos Víaticos | N23: -224.1 | P23: =SUM(Table134724[[#This Row],[Valor de la Factura del Cliente]:[Avance]])+P22 -> 61945.91
B24: 45494 | F24: El Moli Menjars Valencians | G24: Se divide entre 5, marval, rozz, super y 2 de lopez | N24: -52.046 | P24: =SUM(Table134724[[#This Row],[Valor de la Factura del Cliente]:[Avance]])+P23 -> 61893.864
B25: 45502 | F25: El Rincon de Maria | G25: Comida en España entre Marval, Rozz, Lopez y Super | N25: -61.6725 | P25: =SUM(Table134724[[#This Row],[Valor de la Factura del Cliente]:[Avance]])+P24 -> 61832.191
B26: 45506 | F26: Aroma de Mar | G26: Comida en España entre Marval, Rozz, Lopez y Super | N26: -65.5125 | P26: =SUM(Table134724[[#This Row],[Valor de la Factura del Cliente]:[Avance]])+P25 -> 61766.679
B27: 45509 | F27: Avianca | G27: Pasaje Madrid-Colombia | N27: -836.8 | P27: =SUM(Table134724[[#This Row],[Valor de la Factura del Cliente]:[Avance]])+P26 -> 60929.879
B28: 45629 | F28: bofa | G28: Transferido vía bofa | N28: -600 | P28: =SUM(Table134724[[#This Row],[Valor de la Factura del Cliente]:[Avance]])+P27 -> 60329.879
B29: 45646 | F29: wingo | G29: cita de la visa que viajaron a Bogota | N29: -274.47 | P29: =SUM(Table134724[[#This Row],[Valor de la Factura del Cliente]:[Avance]])+P28 -> 60055.409
B30: 45658 | F30: remitly | G30: Pagado a Ingrid Katherin Virviescas Valbuena por la Visa | N30: -345 | P30: =SUM(Table134724[[#This Row],[Valor de la Factura del Cliente]:[Avance]])+P29 -> 59710.409
B31: 45660 | F31: TACA AIR | G31: MDE - BOG Gastos de Viaje | N31: -132.4 | P31: =SUM(Table134724[[#This Row],[Valor de la Factura del Cliente]:[Avance]])+P30 -> 59578.009
B32: 45660 | F32: EXPIDIA | G32: ESTADIA EN BOGOTA GASTOS COMPARTIDO CON MARVAL | N32: -135 | P32: =SUM(Table134724[[#This Row],[Valor de la Factura del Cliente]:[Avance]])+P31 -> 59443.009
B33: 45665 | F33: TACA AIR | G33: BOG - MDE | N33: -97.8 | P33: =SUM(Table134724[[#This Row],[Valor de la Factura del Cliente]:[Avance]])+P32 -> 59345.209
G34: TOTAL | H34: =SUBTOTAL(109,Table134724[Valor de la Factura del Cliente]) -> 79000 | I34: =SUBTOTAL(109,Table134724[Cargos Bancarios]) -> -97.94 | K34: =SUBTOTAL(109,Table134724[20% Comisión]) -> 0 | L34: =SUBTOTAL(109,Table134724[5% Legal]) -> 0 | M34: =SUBTOTAL(109,Table134724[Retención de Impuestos]) -> 0 | N34: =SUBTOTAL(109,Table134724[Pagado por MVPX]) -> -19556.851 | O34: =SUBTOTAL(109,Table134724[Avance]) -> 0 | P34: =+P33 -> 59345.209

Sheet Samuel Velazquez
B2: Artista: | E2: Samuel Velazquez
B3: Nombre legal: | E3: =+E2 -> Samuel Velazquez
B4: Fecha de inicio: | E4: =MIN(Table134710[Fecha]) -> 45219
B5: Fecha fin: | E5: =MAX(Table134710[Fecha]) -> 45555
B7: ESTADO DE CUENTA
B8: Fecha | C8: Número | D8: Tipo | E8: Método de pago | F8: Nombre | G8: Concepto | H8: Valor de la Factura del Cliente | I8: Cargos Bancarios | J8: 50% Fee | K8: 20% Comisión | L8: 5% Legal | M8: Retención de Impuestos | N8: Pagado por MVPX | O8: Avance | P8: Balance
B9: 45404 | F9: Samuel Velazquez | G9: Arreglo y produccion, post producción y Guitarras | H9: 3600 | P9: =SUM(Table134710[[#This Row],[Valor de la Factura del Cliente]:[Avance]]) -> 3600
B10: 45219 | F10: Samuel Velazquez | G10: Adelanto Solicitado | N10: -654.45 | P10: =SUM(Table134710[[#This Row],[Valor de la Factura del Cliente]:[Avance]])+P9 -> 2945.55
B11: 45413 | F11: Samuel Velazquez | G11: Adelanto Solicitado | N11: -804.99 | P11: =SUM(Table134710[[#This Row],[Valor de la Factura del Cliente]:[Avance]])+P10 -> 2140.56
B12: 45465 | F12: Samuel Velazquez | G12: Adelanto Solicitado | N12: -597 | P12: =SUM(Table134710[[#This Row],[Valor de la Factura del Cliente]:[Avance]])+P11 -> 1543.56
B13: 45553 | F13: Samuel Velazquez | G13: Adelanto Solicitado | N13: -550 | P13: =SUM(Table134710[[#This Row],[Valor de la Factura del Cliente]:[Avance]])+P12 -> 993.56
B14: 45554 | F14: 3 Val Tech | G14: Pago vía Bofa | N14: -160 | P14: =SUM(Table134710[[#This Row],[Valor de la Factura del Cliente]:[Avance]])+P13 -> 833.56
B15: 45555 | F15: Samuel Velazquez | G15: Adelanto Solicitado | N15: -832.5 | P15: =SUM(Table134710[[#This Row],[Valor de la Factura del Cliente]:[Avance]])+P14 -> 1.06
B16: 45332 | F16: Samuel Velazquez | G16: Adelanto Solicitado | N16: -841.99 | P16: =SUM(Table134710[[#This Row],[Valor de la Factura del Cliente]:[Avance]])+P15 -> -840.93
G17: TOTAL | H17: =SUBTOTAL(109,Table134710[Valor de la Factura del Cliente]) -> 3600 | I17: =SUBTOTAL(109,Table134710[Cargos Bancarios]) -> 0 | K17: =SUBTOTAL(109,Table134710[20% Comisión]) -> 0 | L17: =SUBTOTAL(109,Table134710[5% Legal]) -> 0 | M17: =SUBTOTAL(109,Table134710[Retención de Impuestos]) -> 0 | N17: =SUBTOTAL(109,Table134710[Pagado por MVPX]) -> -4440.93 | O17: =SUBTOTAL(109,Table134710[Avance]) -> 0 | P17: =+P16 -> -840.93

Sheet Alex Nuñez
B2: Artista: | E2: Alex Nuñez
B3: Nombre legal: | E3: Alex Nuñez
B4: Fecha de inicio: | E4: =MIN(Table13473[Fecha]) -> 45166
B5: Fecha fin: | E5: =MAX(Table13473[Fecha]) -> 45945
B7: ESTADO DE CUENTA
B8: Fecha | C8: Número | D8: Tipo | E8: Método de pago | F8: Nombre | G8: Concepto | H8: Valor de la Factura del Cliente | I8: Cargos Bancarios | J8: 50% Fee | K8: 20% Comisión | L8: 5% Legal | M8: Retención de Impuestos | N8: Pagado por MVPX | O8: Avance | P8: Balance
B9: 45166 | F9: Sra Sara Pimentel | G9: Adelanto Solicitado | N9: -20000 | P9: =SUM(Table13473[[#This Row],[Valor de la Factura del Cliente]:[Avance]]) -> -20000
B10: 45166 | F10: Sra Nancy Guzman | G10: Adelanto Solicitado | N10: -70000 | P10: =SUM(Table13473[[#This Row],[Valor de la Factura del Cliente]:[Avance]])+P9 -> -90000
B11: 45191 | F11: Alex Nuñez | G11: Adelanto Solicitado | N11: -5000 | P11: =SUM(Table13473[[#This Row],[Valor de la Factura del Cliente]:[Avance]])+P10 -> -95000
B12: 45199 | F12: Uber | G12: Transporte a la Filmacion | N12: -300 | P12: =SUM(Table13473[[#This Row],[Valor de la Factura del Cliente]:[Avance]])+P11 -> -95300
B13: 45200 | F13: SuperM Nacional | G13: Comida para la Filmación | N13: -12000 | P13: =SUM(Table13473[[#This Row],[Valor de la Factura del Cliente]:[Avance]])+P12 -> -107300
B14: 45375 | F14: Alex Nuñez | G14: Adelanto para la visa | N14: -28800 | P14: =SUM(Table13473[[#This Row],[Valor de la Factura del Cliente]:[Avance]])+P13 -> -136100
B15: 45386 | F15: Uber | G15: Transporte para el campamento | N15: -364.58 | P15: =SUM(Table13473[[#This Row],[Valor de la Factura del Cliente]:[Avance]])+P14 -> -136464.58
B16: 45387 | F16: SuperM Nacional | G16: Comida para campamento | N16: -8982.19 | P16: =SUM(Table13473[[#This Row],[Valor de la Factura del Cliente]:[Avance]])+P15 -> -145446.77
B17: 45387 | F17: Transporte al campamento | G17: Transporte para el campamento | N17: -2500 | P17: =SUM(Table13473[[#This Row],[Valor de la Factura del Cliente]:[Avance]])+P16 -> -147946.77
B18: 45396 | F18: Sara Esther Pimentel Nuñez | G18: Adelanto realizado vía remitly | N18: -9239 | P18: =SUM(Table13473[[#This Row],[Valor de la Factura del Cliente]:[Avance]])+P17 -> -157185.77
B19: 45400 | F19: Alex Nuñez | G19: Comida para el 2do Campamento | N19: -4075 | P19: =SUM(Table13473[[#This Row],[Valor de la Factura del Cliente]:[Avance]])+P18 -> -161260.77
B20: 45401 | F20: Uber | G20: Gastos de Transporte para el Campamento | N20: -421.92 | P20: =SUM(Table13473[[#This Row],[Valor de la Factura del Cliente]:[Avance]])+P19 -> -161682.69
B21: 45402 | F21: XIOMERI VELOZ | G21: Pago de Comida para el Campamento (Lo pago gesa) | N21: -7000 | P21: =SUM(Table13473[[#This Row],[Valor de la Factura del Cliente]:[Avance]])+P20 -> -168682.69
... B91: 45877 | F91: Pago de la renta | G91: Sara pago 7 y gesa 15 | N91: -15000 | P91: =SUM(Table13473[[#This Row],[Valor de la Factura del Cliente]:[Avance]])+P90 -> -1598525.1
B92: 45874 | F92: Ingreso | G92: Pgo del seguro por el carro | H92: 805103.56 | N92: 0 | P92: =SUM(Table13473[[#This Row],[Valor de la Factura del Cliente]:[Avance]])+P91 -> -793421.54
B93: 45883 | F93: Price Smart | G93: Compra de Comida para la casa de Alex | N93: -2349.5 | P93: =SUM(Table13473[[#This Row],[Valor de la Factura del Cliente]:[Avance]])+P92 -> -795771.04
B94: 45883 | F94: Bravo | G94: Compra de Comida para la casa de Alex | N94: -6890 | P94: =SUM(Table13473[[#This Row],[Valor de la Factura del Cliente]:[Avance]])+P93 -> -802661.04
B95: 45901 | F95: Colegio Niños | G95: Pago a Nancy Guzman por el 80% del monto adeudado | N95: -90400 | P95: =SUM(Table13473[[#This Row],[Valor de la Factura del Cliente]:[Avance]])+P94 -> -893061.04
B96: 45902 | F96: Max Ferretería | G96: Compra de Cuadernos para el colegio (40) | N96: -960 | P96: =SUM(Table13473[[#This Row],[Valor de la Factura del Cliente]:[Avance]])+P95 -> -894021.04
B97: 45902 | F97: Sirena | G97: Papel Cuadriculado y Resma de Papel | N97: -524 | P97: =SUM(Table13473[[#This Row],[Valor de la Factura del Cliente]:[Avance]])+P96 -> -894545.04
B98: 45902 | F98: Pago de la renta | G98: Sara pago 08 y gesa 14 | N98: -14000 | P98: =SUM(Table13473[[#This Row],[Valor de la Factura del Cliente]:[Avance]])+P97 -> -908545.04
B99: 45904 | F99: SR Julio y Surinach Perez | G99: Compra de Libros del colegio para los hijos de alex | N99: -8800 | P99: =SUM(Table13473[[#This Row],[Valor de la Factura del Cliente]:[Avance]])+P98 -> -917345.04
B100: 45906 | F100: Bravo | G100: Compra de Comida para la casa de Alex | N100: -7806 | P100: =SUM(Table13473[[#This Row],[Valor de la Factura del Cliente]:[Avance]])+P99 -> -925151.04
B101: 45912 | F101: Uber | G101: Gasto de Uber del colegio | N101: -195 | P101: =SUM(Table13473[[#This Row],[Valor de la Factura del Cliente]:[Avance]])+P100 -> -925346.04
B102: 45912 | F102: Price Smart | G102: Compra de Comida para la casa de Alex | N102: -540 | P102: =SUM(Table13473[[#This Row],[Valor de la Factura del Cliente]:[Avance]])+P101 -> -925886.04
B103: 45912 | F103: Price Smart | G103: Compra de Comida para la casa de Alex | N103: -1903.9 | P103: =SUM(Table13473[[#This Row],[Valor de la Factura del Cliente]:[Avance]])+P102 -> -927789.94
B104: 45913 | F104: Teomedes Cesar Isabel Placencio | G104: Pago a Musicos de Alex (1000 usd) | N104: -61580 | P104: =SUM(Table13473[[#This Row],[Valor de la Factura del Cliente]:[Avance]])+P103 -> -989369.94
... B110: 45945 | F110: Edesur | G110: Pago de la Luz | N110: -3744.39 | P110: =SUM(Table13473[[#This Row],[Valor de la Factura del Cliente]:[Avance]])+P109 -> -1106480.6
N111: 0 | P111: =SUM(Table13473[[#This Row],[Valor de la Factura del Cliente]:[Avance]])+P110 -> -1106480.6
N112: 0 | P112: =SUM(Table13473[[#This Row],[Valor de la Factura del Cliente]:[Avance]])+P111 -> -1106480.6
N113: 0 | P113: =SUM(Table13473[[#This Row],[Valor de la Factura del Cliente]:[Avance]])+P112 -> -1106480.6
N114: 0 | P114: =SUM(Table13473[[#This Row],[Valor de la Factura del Cliente]:[Avance]])+P113 -> -1106480.6
N115: 0 | P115: =SUM(Table13473[[#This Row],[Valor de la Factura del Cliente]:[Avance]])+P114 -> -1106480.6
N116: 0 | P116: =SUM(Table13473[[#This Row],[Valor de la Factura del Cliente]:[Avance]])+P115 -> -1106480.6
N117: 0 | P117: =SUM(Table13473[[#This Row],[Valor de la Factura del Cliente]:[Avance]])+P116 -> -1106480.6
N118: 0 | P118: =SUM(Table13473[[#This Row],[Valor de la Factura del Cliente]:[Avance]])+P117 -> -1106480.6
B119: 45945 | F119: Abraham Marte | N119: -10000 | P119: =SUM(Table13473[[#This Row],[Valor de la Factura del Cliente]:[Avance]])+P118 -> -1116480.6
B120: 45945 | F120: Roosevelt Martinez Rosario | N120: -16000 | P120: =SUM(Table13473[[#This Row],[Valor de la Factura del Cliente]:[Avance]])+P119 -> -1132480.6
G121: TOTAL | H121: =SUBTOTAL(109,Table13473[Valor de la Factura del Cliente]) -> 805103.56 | I121: =SUBTOTAL(109,Table13473[Cargos Bancarios]) -> 0 | K121: =SUBTOTAL(109,Table13473[20% Comisión]) -> 0 | L121: =SUBTOTAL(109,Table13473[5% Legal]) -> 0 | M121: =SUBTOTAL(109,Table13473[Retención de Impuestos]) -> 0 | N121: =SUBTOTAL(109,Table13473[Pagado por MVPX]) -> -1937584.2 | O121: =SUBTOTAL(109,Table13473[Avance]) -> 0 | P121: =+P120 -> -1132480.6

Sheet Divino
B2: Artista: | E2: Divino
B3: Nombre legal: | E3: Daniel Velazquez
B4: Fecha de inicio: | E4: =MIN(Table134723[Fecha]) -> 44692
B5: Fecha fin: | E5: =MAX(Table134723[Fecha]) -> 45930
B7: ESTADO DE CUENTA
B8: Fecha | C8: Número | D8: Tipo | E8: Método de pago | F8: Nombre | G8: Concepto | H8: Valor de la Factura del Cliente | I8: Cargos Bancarios | J8: 50% Fee | K8: 10% Comisión | L8: 5% Legal | M8: Retención de Impuestos | N8: Pagado por MVPX | O8: Avance | P8: Balance
B9: Enero 2023 | G9: Reporte ingresos por la Distribución de Todo a su Tiempo | H9: 0 | J9: =-Table134723[[#This Row],[Valor de la Factura del Cliente]]*0.5 -> 0 | P9: =SUM(Table134723[[#This Row],[Valor de la Factura del Cliente]:[Avance]]) -> 0
B10: Febrero 2023 | G10: Reporte ingresos por la Distribución de Todo a su Tiempo | H10: 112.88501 | J10: =-Table134723[[#This Row],[Valor de la Factura del Cliente]]*0.5 -> -56.442505 | P10: =SUM(Table134723[[#This Row],[Valor de la Factura del Cliente]:[Avance]])+P9 -> 56.442505
B11: Marzo 2023 | G11: Reporte ingresos por la Distribución de Todo a su Tiempo | H11: 168.6371 | J11: =-Table134723[[#This Row],[Valor de la Factura del Cliente]]*0.5 -> -84.318548 | P11: =SUM(Table134723[[#This Row],[Valor de la Factura del Cliente]:[Avance]])+P10 -> 140.76105
B12: Abril 2023 | G12: Reporte ingresos por la Distribución de Todo a su Tiempo | H12: 243.98148 | J12: =-Table134723[[#This Row],[Valor de la Factura del Cliente]]*0.5 -> -121.99074 | P12: =SUM(Table134723[[#This Row],[Valor de la Factura del Cliente]:[Avance]])+P11 -> 262.75179
B13: Mayo 2023 | G13: Reporte ingresos por la Distribución de Todo a su Tiempo | H13: 257.37564 | J13: =-Table134723[[#This Row],[Valor de la Factura del Cliente]]*0.5 -> -128.68782 | P13: =SUM(Table134723[[#This Row],[Valor de la Factura del Cliente]:[Avance]])+P12 -> 391.43961
B14: Junio 2023 | G14: Reporte ingresos por la Distribución de Todo a su Tiempo | H14: 335.23941 | J14: =-Table134723[[#This Row],[Valor de la Factura del Cliente]]*0.5 -> -167.6197 | P14: =SUM(Table134723[[#This Row],[Valor de la Factura del Cliente]:[Avance]])+P13 -> 559.05931
B15: Julio 2023 | G15: Reporte ingresos por la Distribución de Todo a su Tiempo | H15: 620.16151 | J15: =-Table134723[[#This Row],[Valor de la Factura del Cliente]]*0.5 -> -310.08075 | P15: =SUM(Table134723[[#This Row],[Valor de la Factura del Cliente]:[Avance]])+P14 -> 869.14007
B16: Agosto 2023 | G16: Reporte ingresos por la Distribución de Todo a su Tiempo | H16: 818.55702 | J16: =-Table134723[[#This Row],[Valor de la Factura del Cliente]]*0.5 -> -409.27851 | P16: =SUM(Table134723[[#This Row],[Valor de la Factura del Cliente]:[Avance]])+P15 -> 1278.4186
B17: Septiembre 2023 | G17: Reporte ingresos por la Distribución de Todo a su Tiempo | H17: 736.00881 | J17: =-Table134723[[#This Row],[Valor de la Factura del Cliente]]*0.5 -> -368.0044 | P17: =SUM(Table134723[[#This Row],[Valor de la Factura del Cliente]:[Avance]])+P16 -> 1646.423
B18: Octubre 2023 | G18: Reporte ingresos por la Distribución de Todo a su Tiempo | H18: 820.51103 | J18: =-Table134723[[#This Row],[Valor de la Factura del Cliente]]*0.5 -> -410.25552 | P18: =SUM(Table134723[[#This Row],[Valor de la Factura del Cliente]:[Avance]])+P17 -> 2056.6785
B19: Noviembre 2023 | G19: Reporte ingresos por la Distribución de Todo a su Tiempo | H19: 701.38358 | J19: =-Table134723[[#This Row],[Valor de la Factura del Cliente]]*0.5 -> -350.69179 | P19: =SUM(Table134723[[#This Row],[Valor de la Factura del Cliente]:[Avance]])+P18 -> 2407.3703
B20: Diciembre 2023 | G20: Reporte ingresos por la Distribución de Todo a su Tiempo | H20: 697.46252 | J20: =-Table134723[[#This Row],[Valor de la Factura del Cliente]]*0.5 -> -348.73126 | P20: =SUM(Table134723[[#This Row],[Valor de la Factura del Cliente]:[Avance]])+P19 -> 2756.1015
B21: Enero 2024 | G21: Reporte ingresos por la Distribución de Todo a su Tiempo | H21: 706.0576 | J21: =-Table134723[[#This Row],[Valor de la Factura del Cliente]]*0.5 -> -353.0288 | P21: =SUM(Table134723[[#This Row],[Valor de la Factura del Cliente]:[Avance]])+P20 -> 3109.1303
... B39: Julio 2025 | G39: Reporte ingresos por la Distribución de Todo a su Tiempo | H39: 3848.3893 | J39: =-Table134723[[#This Row],[Valor de la Factura del Cliente]]*0.5 -> -1924.1947 | P39: =SUM(Table134723[[#This Row],[Valor de la Factura del Cliente]:[Avance]])+P38 -> 14688.353
B40: Q32020 | G40: Reporte de Regalías Mecanicas | H40: 0 | K40: =-Table134723[[#This Row],[Valor de la Factura del Cliente]]*0.1 -> 0 | P40: =SUM(Table134723[[#This Row],[Valor de la Factura del Cliente]:[Avance]])+P39 -> 14688.353
B41: Q42020 | G41: Reporte de Regalías Mecanicas | H41: 385.77 | K41: =-Table134723[[#This Row],[Valor de la Factura del Cliente]]*0.1 -> -38.577 | P41: =SUM(Table134723[[#This Row],[Valor de la Factura del Cliente]:[Avance]])+P40 -> 15035.546
B42: Q12021 | G42: Reporte de Regalías Mecanicas | H42: 482.31 | K42: =-Table134723[[#This Row],[Valor de la Factura del Cliente]]*0.1 -> -48.231 | P42: =SUM(Table134723[[#This Row],[Valor de la Factura del Cliente]:[Avance]])+P41 -> 15469.625
B43: Q22021 | G43: Reporte de Regalías Mecanicas | H43: 237.31 | K43: =-Table134723[[#This Row],[Valor de la Factura del Cliente]]*0.1 -> -23.731 | P43: =SUM(Table134723[[#This Row],[Valor de la Factura del Cliente]:[Avance]])+P42 -> 15683.204
B44: Q32021 | G44: Reporte de Regalías Mecanicas | H44: 2649.44 | K44: =-Table134723[[#This Row],[Valor de la Factura del Cliente]]*0.1 -> -264.944 | P44: =SUM(Table134723[[#This Row],[Valor de la Factura del Cliente]:[Avance]])+P43 -> 18067.7
B45: Q42021 | G45: Reporte de Regalías Mecanicas | H45: 2165.34 | K45: =-Table134723[[#This Row],[Valor de la Factura del Cliente]]*0.1 -> -216.534 | P45: =SUM(Table134723[[#This Row],[Valor de la Factura del Cliente]:[Avance]])+P44 -> 20016.506
B46: Q12022 | G46: Reporte de Regalías Mecanicas | H46: 174.56 | K46: =-Table134723[[#This Row],[Valor de la Factura del Cliente]]*0.1 -> -17.456 | P46: =SUM(Table134723[[#This Row],[Valor de la Factura del Cliente]:[Avance]])+P45 -> 20173.61
B47: Q22022 | G47: Reporte de Regalías Mecanicas | H47: 333.31 | K47: =-Table134723[[#This Row],[Valor de la Factura del Cliente]]*0.1 -> -33.331 | P47: =SUM(Table134723[[#This Row],[Valor de la Factura del Cliente]:[Avance]])+P46 -> 20473.589
B48: Q32022 | G48: Reporte de Regalías Mecanicas | H48: 319.33 | K48: =-Table134723[[#This Row],[Valor de la Factura del Cliente]]*0.1 -> -31.933 | P48: =SUM(Table134723[[#This Row],[Valor de la Factura del Cliente]:[Avance]])+P47 -> 20760.986
B49: Q42022 | G49: Reporte de Regalías Mecanicas | H49: 306.61 | K49: =-Table134723[[#This Row],[Valor de la Factura del Cliente]]*0.1 -> -30.661 | P49: =SUM(Table134723[[#This Row],[Valor de la Factura del Cliente]:[Avance]])+P48 -> 21036.935
B50: Q12023 | G50: Reporte de Regalías Mecanicas | H50: 858.01 | K50: =-Table134723[[#This Row],[Valor de la Factura del Cliente]]*0.1 -> -85.801 | P50: =SUM(Table134723[[#This Row],[Valor de la Factura del Cliente]:[Avance]])+P49 -> 21809.144
B51: Q22023 | G51: Reporte de Regalías Mecanicas | H51: 1061.76 | K51: =-Table134723[[#This Row],[Valor de la Factura del Cliente]]*0.1 -> -106.176 | P51: =SUM(Table134723[[#This Row],[Valor de la Factura del Cliente]:[Avance]])+P50 -> 22764.728
... B59: Q22025 | G59: Reporte de Regalías Mecanicas | H59: 9070.07 | K59: =-Table134723[[#This Row],[Valor de la Factura del Cliente]]*0.1 -> -907.007 | P59: =SUM(Table134723[[#This Row],[Valor de la Factura del Cliente]:[Avance]])+P58 -> 64033.544
B60: 44692 | G60: Pagos Realizados | N60: -5583.7 | P60: =SUM(Table134723[[#This Row],[Valor de la Factura del Cliente]:[Avance]])+P59 -> 58449.844
B61: 45309 | G61: Pagos Realizados | N61: -2999.88 | P61: =SUM(Table134723[[#This Row],[Valor de la Factura del Cliente]:[Avance]])+P60 -> 55449.964
B62: 45547 | G62: Pagos Realizados | N62: -18661.99 | P62: =SUM(Table134723[[#This Row],[Valor de la Factura del Cliente]:[Avance]])+P61 -> 36787.974
B63: 45548 | G63: Pagos Realizados | N63: -9242.78 | P63: =SUM(Table134723[[#This Row],[Valor de la Factura del Cliente]:[Avance]])+P62 -> 27545.194
B64: 45806 | G64: Pagos Realizados | N64: -11873.59 | P64: =SUM(Table134723[[#This Row],[Valor de la Factura del Cliente]:[Avance]])+P63 -> 15671.604
B65: 45930 | G65: Pagos Realizados | N65: -9000 | P65: =SUM(Table134723[[#This Row],[Valor de la Factura del Cliente]:[Avance]])+P64 -> 6671.6043
G66: TOTAL | H66: =SUBTOTAL(109,Table134723[Valor de la Factura del Cliente]) -> 84204.697 | I66: =SUBTOTAL(109,Table134723[Cargos Bancarios]) -> 0 | K66: =SUBTOTAL(109,Table134723[10% Comisión]) -> -5482.799 | L66: =SUBTOTAL(109,Table134723[5% Legal]) -> 0 | M66: =SUBTOTAL(109,Table134723[Retención de Impuestos]) -> 0 | N66: =SUBTOTAL(109,Table134723[Pagado por MVPX]) -> -57361.94 | O66: =SUBTOTAL(109,Table134723[Avance]) -> 0 | P66: =+P65 -> 6671.6043

Sheet LANALIZER
B2: Artista: | E2: LANALIZER
B3: Nombre legal: | E3: =+'Base de datos'!E17 -> Yan Carlo Francisco Guzmán Velásquez
B4: Fecha de inicio: | E4: =MIN(Table134721[Fecha]) -> 43872
B5: Fecha fin: | E5: =MAX(Table134721[Fecha]) -> 45861
B7: ESTADO DE CUENTA
B8: Fecha | C8: Número | D8: Tipo | E8: Método de pago | F8: Nombre | G8: Concepto | H8: Valor de la Factura del Cliente | I8: Cargos Bancarios | J8: 50% Fee | K8: 20% Comisión | L8: 5% Legal | M8: Retención de Impuestos | N8: Pagado por MVPX | O8: Avance | P8: Balance
G9: Ganga | H9: 3418.2 | P9: =SUM(Table134721[[#This Row],[Valor de la Factura del Cliente]:[Avance]]) -> 3418.2
B10: 44309 | G10: Production Services for Maikel De la Calle & Lennis Rodriguez"Secreto" | H10: 4839.6 | K10: =-Table134721[[#This Row],[Valor de la Factura del Cliente]]*0.2 -> -967.92 | L10: =-Table134721[[#This Row],[Valor de la Factura del Cliente]]*0.05 -> -241.98 | P10: =SUM(Table134721[[#This Row],[Valor de la Factura del Cliente]:[Avance]])+P9 -> 7047.9
B11: 44127 | G11: Brytiago - Condena y Crush | H11: 3000 | K11: =-Table134721[[#This Row],[Valor de la Factura del Cliente]]*0.2 -> -600 | L11: =-Table134721[[#This Row],[Valor de la Factura del Cliente]]*0.05 -> -150 | P11: =SUM(Table134721[[#This Row],[Valor de la Factura del Cliente]:[Avance]])+P10 -> 9297.9
B12: 43872 | G12: Production Services for Ankhal new release "High Class" | H12: 2000 | K12: =-Table134721[[#This Row],[Valor de la Factura del Cliente]]*0.2 -> -400 | L12: =-Table134721[[#This Row],[Valor de la Factura del Cliente]]*0.05 -> -100 | P12: =SUM(Table134721[[#This Row],[Valor de la Factura del Cliente]:[Avance]])+P11 -> 10797.9
B13: 44055 | G13: Production services for Ankhal new release "FRESHY" | H13: 2500 | K13: =-Table134721[[#This Row],[Valor de la Factura del Cliente]]*0.2 -> -500 | L13: =-Table134721[[#This Row],[Valor de la Factura del Cliente]]*0.05 -> -125 | P13: =SUM(Table134721[[#This Row],[Valor de la Factura del Cliente]:[Avance]])+P12 -> 12672.9
B14: 44049 | G14: Production services for single "Mi Carta" by Beele | H14: 4000 | K14: =-Table134721[[#This Row],[Valor de la Factura del Cliente]]*0.2 -> -800 | L14: =-Table134721[[#This Row],[Valor de la Factura del Cliente]]*0.05 -> -200 | P14: =SUM(Table134721[[#This Row],[Valor de la Factura del Cliente]:[Avance]])+P13 -> 15672.9
B15: 45397 | G15: Lanalizer Deal | H15: 4000 | K15: =-Table134721[[#This Row],[Valor de la Factura del Cliente]]*0.2 -> -800 | L15: =-Table134721[[#This Row],[Valor de la Factura del Cliente]]*0.05 -> -200 | P15: =SUM(Table134721[[#This Row],[Valor de la Factura del Cliente]:[Avance]])+P14 -> 18672.9
B16: 45751 | G16: Under Water Music LLC - Porducción de tema Quikie para Deivi | H16: 2000 | K16: =-Table134721[[#This Row],[Valor de la Factura del Cliente]]*0.2 -> -400 | L16: =-Table134721[[#This Row],[Valor de la Factura del Cliente]]*0.05 -> -100 | P16: =SUM(Table134721[[#This Row],[Valor de la Factura del Cliente]:[Avance]])+P15 -> 20172.9
B17: Q32020 | G17: Reporte de Regalías de Ejecucion Publica | H17: 0 | J17: =-Table134721[[#This Row],[Valor de la Factura del Cliente]]*0.5 -> 0 | P17: =SUM(Table134721[[#This Row],[Valor de la Factura del Cliente]:[Avance]])+P16 -> 20172.9
B18: Q42020 | G18: Reporte de Regalías de Ejecucion Publica | H18: 0 | J18: =-Table134721[[#This Row],[Valor de la Factura del Cliente]]*0.5 -> 0 | P18: =SUM(Table134721[[#This Row],[Valor de la Factura del Cliente]:[Avance]])+P17 -> 20172.9
B19: Q12021 | G19: Reporte de Regalías de Ejecucion Publica | H19: 0.17 | J19: =-Table134721[[#This Row],[Valor de la Factura del Cliente]]*0.5 -> -0.085 | P19: =SUM(Table134721[[#This Row],[Valor de la Factura del Cliente]:[Avance]])+P18 -> 20172.985
B20: Q22021 | G20: Reporte de Regalías de Ejecucion Publica | H20: 0.76 | J20: =-Table134721[[#This Row],[Valor de la Factura del Cliente]]*0.5 -> -0.38 | P20: =SUM(Table134721[[#This Row],[Valor de la Factura del Cliente]:[Avance]])+P19 -> 20173.365
B21: Q32021 | G21: Reporte de Regalías de Ejecucion Publica | H21: 0.41 | J21: =-Table134721[[#This Row],[Valor de la Factura del Cliente]]*0.5 -> -0.205 | P21: =SUM(Table134721[[#This Row],[Valor de la Factura del Cliente]:[Avance]])+P20 -> 20173.57
B22: Q42021 | G22: Reporte de Regalías de Ejecucion Publica | H22: 0.3 | J22: =-Table134721[[#This Row],[Valor de la Factura del Cliente]]*0.5 -> -0.15 | P22: =SUM(Table134721[[#This Row],[Valor de la Factura del Cliente]:[Avance]])+P21 -> 20173.72
B23: Q12022 | G23: Reporte de Regalías de Ejecucion Publica | H23: 27.17 | J23: =-Table134721[[#This Row],[Valor de la Factura del Cliente]]*0.5 -> -13.585 | P23: =SUM(Table134721[[#This Row],[Valor de la Factura del Cliente]:[Avance]])+P22 -> 20187.305
B24: Q22022 | G24: Reporte de Regalías de Ejecucion Publica | H24: 16.18 | J24: =-Table134721[[#This Row],[Valor de la Factura del Cliente]]*0.5 -> -8.09 | P24: =SUM(Table134721[[#This Row],[Valor de la Factura del Cliente]:[Avance]])+P23 -> 20195.395
B25: Q32022 | G25: Reporte de Regalías de Ejecucion Publica | H25: 2.95 | J25: =-Table134721[[#This Row],[Valor de la Factura del Cliente]]*0.5 -> -1.475 | P25: =SUM(Table134721[[#This Row],[Valor de la Factura del Cliente]:[Avance]])+P24 -> 20196.87
B26: Q42022 | G26: Reporte de Regalías de Ejecucion Publica | H26: 6.55 | J26: =-Table134721[[#This Row],[Valor de la Factura del Cliente]]*0.5 -> -3.275 | P26: =SUM(Table134721[[#This Row],[Valor de la Factura del Cliente]:[Avance]])+P25 -> 20200.145
B27: Q12023 | G27: Reporte de Regalías de Ejecucion Publica | H27: 2.98 | J27: =-Table134721[[#This Row],[Valor de la Factura del Cliente]]*0.5 -> -1.49 | P27: =SUM(Table134721[[#This Row],[Valor de la Factura del Cliente]:[Avance]])+P26 -> 20201.635
B28: Q22023 | G28: Reporte de Regalías de Ejecucion Publica | H28: 1.82 | J28: =-Table134721[[#This Row],[Valor de la Factura del Cliente]]*0.5 -> -0.91 | P28: =SUM(Table134721[[#This Row],[Valor de la Factura del Cliente]:[Avance]])+P27 -> 20202.545
... B36: Q22025 | G36: Reporte de Regalías de Ejecucion Publica | H36: 1981.21 | J36: =-Table134721[[#This Row],[Valor de la Factura del Cliente]]*0.5 -> -990.605 | P36: =SUM(Table134721[[#This Row],[Valor de la Factura del Cliente]:[Avance]])+P35 -> 25403.445
B37: Q32020 | G37: Reporte de Regalías Mecanicas | H37: 0.11 | K37: =-Table134721[[#This Row],[Valor de la Factura del Cliente]]*0.2 -> -0.022 | L37: =-Table134721[[#This Row],[Valor de la Factura del Cliente]]*0.05 -> -0.0055 | P37: =SUM(Table134721[[#This Row],[Valor de la Factura del Cliente]:[Avance]])+P36 -> 25403.528
B38: Q42020 | G38: Reporte de Regalías Mecanicas | H38: 51.13 | K38: =-Table134721[[#This Row],[Valor de la Factura del Cliente]]*0.2 -> -10.226 | L38: =-Table134721[[#This Row],[Valor de la Factura del Cliente]]*0.05 -> -2.5565 | P38: =SUM(Table134721[[#This Row],[Valor de la Factura del Cliente]:[Avance]])+P37 -> 25441.875
B39: Q12021 | G39: Reporte de Regalías Mecanicas | H39: 611.62 | K39: =-Table134721[[#This Row],[Valor de la Factura del Cliente]]*0.2 -> -122.324 | L39: =-Table134721[[#This Row],[Valor de la Factura del Cliente]]*0.05 -> -30.581 | P39: =SUM(Table134721[[#This Row],[Valor de la Factura del Cliente]:[Avance]])+P38 -> 25900.59
B40: Q22021 | G40: Reporte de Regalías Mecanicas | H40: 201.45 | K40: =-Table134721[[#This Row],[Valor de la Factura del Cliente]]*0.2 -> -40.29 | L40: =-Table134721[[#This Row],[Valor de la Factura del Cliente]]*0.05 -> -10.0725 | P40: =SUM(Table134721[[#This Row],[Valor de la Factura del Cliente]:[Avance]])+P39 -> 26051.678
B41: Q32021 | G41: Reporte de Regalías Mecanicas | H41: 206 | K41: =-Table134721[[#This Row],[Valor de la Factura del Cliente]]*0.2 -> -41.2 | L41: =-Table134721[[#This Row],[Valor de la Factura del Cliente]]*0.05 -> -10.3 | P41: =SUM(Table134721[[#This Row],[Valor de la Factura del Cliente]:[Avance]])+P40 -> 26206.178
B42: Q42021 | G42: Reporte de Regalías Mecanicas | H42: 322.21 | K42: =-Table134721[[#This Row],[Valor de la Factura del Cliente]]*0.2 -> -64.442 | L42: =-Table134721[[#This Row],[Valor de la Factura del Cliente]]*0.05 -> -16.1105 | P42: =SUM(Table134721[[#This Row],[Valor de la Factura del Cliente]:[Avance]])+P41 -> 26447.835
B43: Q12022 | G43: Reporte de Regalías Mecanicas | H43: 660.16 | K43: =-Table134721[[#This Row],[Valor de la Factura del Cliente]]*0.2 -> -132.032 | L43: =-Table134721[[#This Row],[Valor de la Factura del Cliente]]*0.05 -> -33.008 | P43: =SUM(Table134721[[#This Row],[Valor de la Factura del Cliente]:[Avance]])+P42 -> 26942.955
B44: Q22022 | G44: Reporte de Regalías Mecanicas | H44: 255.32 | K44: =-Table134721[[#This Row],[Valor de la Factura del Cliente]]*0.2 -> -51.064 | L44: =-Table134721[[#This Row],[Valor de la Factura del Cliente]]*0.05 -> -12.766 | P44: =SUM(Table134721[[#This Row],[Valor de la Factura del Cliente]:[Avance]])+P43 -> 27134.445
B45: Q32022 | G45: Reporte de Regalías Mecanicas | H45: 210.92 | K45: =-Table134721[[#This Row],[Valor de la Factura del Cliente]]*0.2 -> -42.184 | L45: =-Table134721[[#This Row],[Valor de la Factura del Cliente]]*0.05 -> -10.546 | P45: =SUM(Table134721[[#This Row],[Valor de la Factura del Cliente]:[Avance]])+P44 -> 27292.635
B46: Q42022 | G46: Reporte de Regalías Mecanicas | H46: 153.43 | K46: =-Table134721[[#This Row],[Valor de la Factura del Cliente]]*0.2 -> -30.686 | L46: =-Table134721[[#This Row],[Valor de la Factura del Cliente]]*0.05 -> -7.6715 | P46: =SUM(Table134721[[#This Row],[Valor de la Factura del Cliente]:[Avance]])+P45 -> 27407.708
B47: Q12023 | G47: Reporte de Regalías Mecanicas | H47: 147.06 | K47: =-Table134721[[#This Row],[Valor de la Factura del Cliente]]*0.2 -> -29.412 | L47: =-Table134721[[#This Row],[Valor de la Factura del Cliente]]*0.05 -> -7.353 | P47: =SUM(Table134721[[#This Row],[Valor de la Factura del Cliente]:[Avance]])+P46 -> 27518.003
B48: Q22023 | G48: Reporte de Regalías Mecanicas | H48: 708.79 | K48: =-Table134721[[#This Row],[Valor de la Factura del Cliente]]*0.2 -> -141.758 | L48: =-Table134721[[#This Row],[Valor de la Factura del Cliente]]*0.05 -> -35.4395 | P48: =SUM(Table134721[[#This Row],[Valor de la Factura del Cliente]:[Avance]])+P47 -> 28049.595
... B56: Q22025 | G56: Reporte de Regalías Mecanicas | H56: 11801.73 | K56: =-Table134721[[#This Row],[Valor de la Factura del Cliente]]*0.2 -> -2360.346 | L56: =-Table134721[[#This Row],[Valor de la Factura del Cliente]]*0.05 -> -590.0865 | P56: =SUM(Table134721[[#This Row],[Valor de la Factura del Cliente]:[Avance]])+P55 -> 59099.033
B57: 44309 | G57: ProducƟon Services for Maikel De la Calle & Lennis Rodriguez"Secreto" | N57: -3629.7 | P57: =SUM(Table134721[[#This Row],[Valor de la Factura del Cliente]:[Avance]])+P56 -> 55469.333
B58: 44127 | G58: Brytiago - Condena y Crush | N58: -2250 | P58: =SUM(Table134721[[#This Row],[Valor de la Factura del Cliente]:[Avance]])+P57 -> 53219.333
B59: 43872 | G59: Production Services for Ankhal new release "High Class" | N59: -1500 | P59: =SUM(Table134721[[#This Row],[Valor de la Factura del Cliente]:[Avance]])+P58 -> 51719.333
B60: 44055 | G60: Production services for Ankhal new release "FRESHY" | N60: -1875 | P60: =SUM(Table134721[[#This Row],[Valor de la Factura del Cliente]:[Avance]])+P59 -> 49844.333
B61: 44049 | G61: Production services for single "Mi Carta" by Beele | N61: -1600 | P61: =SUM(Table134721[[#This Row],[Valor de la Factura del Cliente]:[Avance]])+P60 -> 48244.333
B62: 44519 | G62: Avance Lanalizer | O62: -559 | P62: =SUM(Table134721[[#This Row],[Valor de la Factura del Cliente]:[Avance]])+P61 -> 47685.333
B63: 44118 | G63: Avance Lanalizer | O63: -1400 | P63: =SUM(Table134721[[#This Row],[Valor de la Factura del Cliente]:[Avance]])+P62 -> 46285.333
B64: 43942 | G64: Avance Lanalizer | O64: -1000 | P64: =SUM(Table134721[[#This Row],[Valor de la Factura del Cliente]:[Avance]])+P63 -> 45285.333
B65: 43936 | G65: Avance Lanalizer | O65: -1000 | P65: =SUM(Table134721[[#This Row],[Valor de la Factura del Cliente]:[Avance]])+P64 -> 44285.333
B66: 44013 | G66: Royalty payment for music publishing | N66: -100 | P66: =SUM(Table134721[[#This Row],[Valor de la Factura del Cliente]:[Avance]])+P65 -> 44185.333
B67: 44722 | G67: Pago Regalia de Ganga | N67: -1959.94 | P67: =SUM(Table134721[[#This Row],[Valor de la Factura del Cliente]:[Avance]])+P66 -> 42225.393
B68: 45092 | G68: Avance Lanalizer | O68: -1734.76 | P68: =SUM(Table134721[[#This Row],[Valor de la Factura del Cliente]:[Avance]])+P67 -> 40490.633
B69: 45401 | G69: Avance Lanalizer | O69: -4566 | P69: =SUM(Table134721[[#This Row],[Valor de la Factura del Cliente]:[Avance]])+P68 -> 35924.633
B70: 45491 | G70: Pago lanalizer | N70: -2765 | P70: =SUM(Table134721[[#This Row],[Valor de la Factura del Cliente]:[Avance]])+P69 -> 33159.633
B71: 45548 | G71: Compra de Equipo Hecha en favor de Lanalizer en Best Buy | N71: -2258.72 | P71: =SUM(Table134721[[#This Row],[Valor de la Factura del Cliente]:[Avance]])+P70 -> 30900.913
B72: 45628 | G72: Avance Lanalizer | O72: -3822.45 | P72: =SUM(Table134721[[#This Row],[Valor de la Factura del Cliente]:[Avance]])+P71 -> 27078.463
B73: 45705 | G73: Avance Lanalizer | O73: -2811.11 | P73: =SUM(Table134721[[#This Row],[Valor de la Factura del Cliente]:[Avance]])+P72 -> 24267.353
B74: 45780 | G74: Avance Lanalizer | O74: -10922.23 | P74: =SUM(Table134721[[#This Row],[Valor de la Factura del Cliente]:[Avance]])+P73 -> 13345.123
B75: 45861 | G75: Avance Lanalizer | O75: -5103.3 | P75: =SUM(Table134721[[#This Row],[Valor de la Factura del Cliente]:[Avance]])+P74 -> 8241.8225
G76: TOTAL | H76: =SUBTOTAL(109,Table134721[Valor de la Factura del Cliente]) -> 81146.34 | I76: =SUBTOTAL(109,Table134721[Cargos Bancarios]) -> 0 | J76: =SUBTOTAL(109,Table134721[50% Fee]) -> -5230.545 | K76: =SUBTOTAL(109,Table134721[20% Comisión]) -> -13453.41 | L76: =SUBTOTAL(109,Table134721[5% Legal]) -> -3363.3525 | M76: =SUBTOTAL(109,Table134721[Retención de Impuestos]) -> 0 | N76: =SUBTOTAL(109,Table134721[Pagado por MVPX]) -> -17938.36 | O76: =SUBTOTAL(109,Table134721[Avance]) -> -32918.85 | P76: =+P75 -> 8241.8225

Sheet SXNTHI
B2: Artista: | E2: SXNTHI
B3: Nombre legal:
B4: Fecha de inicio: | E4: =MIN(Table134720[Fecha]) -> 45044
B5: Fecha fin: | E5: =MAX(Table134720[Fecha]) -> 45328
B7: ESTADO DE CUENTA
B8: Fecha | C8: Número | D8: Tipo | E8: Método de pago | F8: Nombre | G8: Concepto | H8: Valor de la Factura del Cliente | I8: Cargos Bancarios | J8: 50% Fee | K8: 20% Comisión | L8: 5% Legal | M8: Retención de Impuestos | N8: Pagado por MVPX | O8: Avance | P8: Balance
B9: 45294 | F9: SXNTHI | G9: Ingresos | H9: 585.16 | K9: =-Table134720[[#This Row],[Valor de la Factura del Cliente]]*0.2 -> -117.032 | L9: =-Table134720[[#This Row],[Valor de la Factura del Cliente]]*0.05 -> -29.258 | P9: =SUM(Table134720[[#This Row],[Valor de la Factura del Cliente]:[Avance]]) -> 438.87
B10: 45044 | F10: SXNTHI | G10: Adelanto Solicitado | O10: -200 | P10: =SUM(Table134720[[#This Row],[Valor de la Factura del Cliente]:[Avance]])+P9 -> 238.87
B11: 45104 | F11: SXNTHI | G11: Video Ahora con Yeezy | O11: -665 | P11: =SUM(Table134720[[#This Row],[Valor de la Factura del Cliente]:[Avance]])+P10 -> -426.13
B12: 45167 | F12: SXNTHI | G12: Video Yisus Plan | O12: -475 | P12: =SUM(Table134720[[#This Row],[Valor de la Factura del Cliente]:[Avance]])+P11 -> -901.13
B13: 45264 | F13: SXNTHI | G13: Avance Video me dicen el sol | O13: -600 | P13: =SUM(Table134720[[#This Row],[Valor de la Factura del Cliente]:[Avance]])+P12 -> -1501.13
B14: 45328 | F14: SXNTHI | G14: Avance de video Ja Morant | O14: -500 | P14: =SUM(Table134720[[#This Row],[Valor de la Factura del Cliente]:[Avance]])+P13 -> -2001.13
G15: TOTAL | H15: =SUBTOTAL(109,Table134720[Valor de la Factura del Cliente]) -> 585.16 | I15: =SUBTOTAL(109,Table134720[Cargos Bancarios]) -> 0 | K15: =SUBTOTAL(109,Table134720[20% Comisión]) -> -117.032 | L15: =SUBTOTAL(109,Table134720[5% Legal]) -> -29.258 | M15: =SUBTOTAL(109,Table134720[Retención de Impuestos]) -> 0 | N15: =SUBTOTAL(109,Table134720[Pagado por MVPX]) -> 0 | O15: =SUBTOTAL(109,Table134720[Avance]) -> -2440 | P15: =+P14 -> -2001.13

Sheet GianBeat
B2: Artista: | E2: GianBeat
B3: Nombre legal:
B4: Fecha de inicio: | E4: =MIN(Table134719[Fecha]) -> 45387
B5: Fecha fin: | E5: =MAX(Table134719[Fecha]) -> 45616
B7: ESTADO DE CUENTA
B8: Fecha | C8: Número | D8: Tipo | E8: Método de pago | F8: Nombre | G8: Concepto | H8: Valor de la Factura del Cliente | I8: Cargos Bancarios | J8: 50% Fee | K8: 20% Comisión | L8: 5% Legal | M8: Retención de Impuestos | N8: Pagado por MVPX | O8: Avance | P8: Balance
B9: x | G9: Ingresos 2020Q1-2025Q1 | H9: 2899.27 | K9: =-Table134719[[#This Row],[Valor de la Factura del Cliente]]*0.2 -> -579.854 | L9: =-Table134719[[#This Row],[Valor de la Factura del Cliente]]*0.05 -> -144.9635 | P9: =SUM(Table134719[[#This Row],[Valor de la Factura del Cliente]:[Avance]]) -> 2174.4525
B10: 45387 | G10: Pago por motivo de regalías | N10: -450 | P10: =SUM(Table134719[[#This Row],[Valor de la Factura del Cliente]:[Avance]])+P9 -> 1724.4525
B11: 45616 | G11: Pago por motivo de regalías | N11: -718.48 | P11: =SUM(Table134719[[#This Row],[Valor de la Factura del Cliente]:[Avance]])+P10 -> 1005.9725
G12: TOTAL | H12: =SUBTOTAL(109,Table134719[Valor de la Factura del Cliente]) -> 2899.27 | I12: =SUBTOTAL(109,Table134719[Cargos Bancarios]) -> 0 | K12: =SUBTOTAL(109,Table134719[20% Comisión]) -> -579.854 | L12: =SUBTOTAL(109,Table134719[5% Legal]) -> -144.9635 | M12: =SUBTOTAL(109,Table134719[Retención de Impuestos]) -> 0 | N12: =SUBTOTAL(109,Table134719[Pagado por MVPX]) -> -1168.48 | O12: =SUBTOTAL(109,Table134719[Avance]) -> 0 | P12: =+P11 -> 1005.9725

Sheet Carlos Manuel Jr. Agosto
B2: Artista: | E2: Carlos Manuel Jr. Agosto
B3: Nombre legal: | E3: =+E2 -> Carlos Manuel Jr. Agosto
B4: Fecha de inicio: | E4: =MIN(Table134718[Fecha]) -> 45205
B5: Fecha fin: | E5: =MAX(Table134718[Fecha]) -> 45863
B7: ESTADO DE CUENTA
B8: Fecha | C8: Número | D8: Tipo | E8: Método de pago | F8: Nombre | G8: Concepto | H8: Valor de la Factura del Cliente | I8: Cargos Bancarios | J8: 50% Fee | K8: 20% Comisión | L8: 5% Legal | M8: Retención de Impuestos | N8: Pagado por MVPX | O8: Avance | P8: Balance
B9: 45863 | F9: Carlos Manuel Jr Agosto | G9: Regalías Mecanicas | H9: 2086.72 | K9: -692.05 | P9: =SUM(Table134718[[#This Row],[Valor de la Factura del Cliente]:[Pagado por MVPX]]) -> 1394.67
B10: 45205 | F10: Carlos Manuel Jr Agosto | G10: Abono por Regalías Mecanicas | N10: -444.6 | P10: =SUM(Table134718[[#This Row],[Valor de la Factura del Cliente]:[Pagado por MVPX]])+P9 -> 950.07
B11: 45286 | F11: Carlos Manuel Jr Agosto | G11: Abono por Regalías Mecanicas | N11: -67.19 | P11: =SUM(Table134718[[#This Row],[Valor de la Factura del Cliente]:[Pagado por MVPX]])+P10 -> 882.88
B12: 45572 | F12: Carlos Manuel Jr Agosto | G12: Abono por Regalías Mecanicas | N12: -395.83 | P12: =SUM(Table134718[[#This Row],[Valor de la Factura del Cliente]:[Pagado por MVPX]])+P11 -> 487.05
B13: 45749 | F13: Carlos Manuel Jr Agosto | G13: Abono por Regalías Mecanicas | N13: -561.1 | P13: =SUM(Table134718[[#This Row],[Valor de la Factura del Cliente]:[Pagado por MVPX]])+P12 -> -74.05
G14: TOTAL | H14: =SUBTOTAL(109,Table134718[Valor de la Factura del Cliente]) -> 2086.72 | I14: =SUBTOTAL(109,Table134718[Cargos Bancarios]) -> 0 | K14: =SUBTOTAL(109,Table134718[20% Comisión]) -> -692.05 | L14: =SUBTOTAL(109,Table134718[5% Legal]) -> 0 | M14: =SUBTOTAL(109,Table134718[Retención de Impuestos]) -> 0 | N14: =SUBTOTAL(109,Table134718[Pagado por MVPX]) -> -1468.72 | O14: =SUBTOTAL(109,Table134718[Avance]) -> 0 | P14: =+P13 -> -74.05

Sheet MozartMuzik
O1: 66-0928468
O2: admin@mvpxmusic.com
O3: Tel Ofi: 787-761-9125
B6: Artista: | E6: =+'Base de datos'!B18 -> MozartMuzik
B7: Nombre legal: | E7: =_xlfn.CONCAT('Base de datos'!C18," ",'Base de datos'!D18) -> Nizco Chaparro Jose Luis
B8: Fecha de inicio: | E8: =MIN(Table1[Fecha]) -> 44204
B9: Fecha fin: | E9: =MAX(Table1[Fecha]) -> 45937
B11: ESTADO DE CUENTA
B12: Fecha | C12: Número | D12: Tipo | E12: Método de pago | F12: Nombre | G12: Concepto | H12: Valor de la Factura del Cliente | I12: Cargos Bancarios | J12: 50% Fee | K12: 20% Comisión | L12: 5% Legal | M12: Retención de Impuestos | N12: Pagado por MVPX | O12: Avance | P12: Balance
B13: 44265 | F13: Sirius XM Radio Inc | G13: SECH Virtual Event | H13: 120 | K13: =Table1[[#This Row],[Valor de la Factura del Cliente]]*0.2*-1 -> -24 | L13: =Table1[[#This Row],[Valor de la Factura del Cliente]]*0.05*-1 -> -6 | N13: -90 | P13: =SUM(Table1[[#This Row],[Valor de la Factura del Cliente]:[Avance]]) -> 0
B14: 44204 | F14: UMG Recordings Inc | G14: Production & Mix services for Ecko "Cama Vacia" | H14: 1550 | I14: -15 | K14: =Table1[[#This Row],[Valor de la Factura del Cliente]]*0.2*-1 -> -310 | L14: =Table1[[#This Row],[Valor de la Factura del Cliente]]*0.05*-1 -> -77.5 | N14: -1147.5 | P14: =SUM(Table1[[#This Row],[Valor de la Factura del Cliente]:[Avance]])+P13 -> 0
B15: 44214 | F15: Bartives SA | G15: Production & mixing services for Valen Madanes single "Nadie Tiene que saberlo" (s/OC#00008) | H15: 1500 | I15: -15 | K15: =Table1[[#This Row],[Valor de la Factura del Cliente]]*0.2*-1 -> -300 | L15: =Table1[[#This Row],[Valor de la Factura del Cliente]]*0.05*-1 -> -75 | M15: -7.2 | N15: -1102.8 | P15: =SUM(Table1[[#This Row],[Valor de la Factura del Cliente]:[Avance]])+P14 -> 0
B16: 44271 | F16: UMG Recordings Inc | G16: Production services for Ecko single "Reggaeton De Antes" | H16: 1750 | I16: -15 | K16: =Table1[[#This Row],[Valor de la Factura del Cliente]]*0.2*-1 -> -350 | L16: =Table1[[#This Row],[Valor de la Factura del Cliente]]*0.05*-1 -> -87.5 | N16: -1297.5 | P16: =SUM(Table1[[#This Row],[Valor de la Factura del Cliente]:[Avance]])+P15 -> 0
B17: 44284 | F17: Bartives SA | G17: Production & mixing services for Valen Madanes single "Too Late" (s/ OC#00008) | H17: 1000 | I17: -15 | K17: =Table1[[#This Row],[Valor de la Factura del Cliente]]*0.2*-1 -> -200 | L17: =Table1[[#This Row],[Valor de la Factura del Cliente]]*0.05*-1 -> -50 | M17: -6 | N17: -729 | P17: =SUM(Table1[[#This Row],[Valor de la Factura del Cliente]:[Avance]])+P16 -> 0
B18: 44340 | F18: Young Golden Inc | G18: Producer payment for Cambio De Estado | H18: 1500 | I18: -7.5 | K18: =Table1[[#This Row],[Valor de la Factura del Cliente]]*0.2*-1 -> -300 | L18: =Table1[[#This Row],[Valor de la Factura del Cliente]]*0.05*-1 -> -75 | N18: -1117.5 | P18: =SUM(Table1[[#This Row],[Valor de la Factura del Cliente]:[Avance]])+P17 -> 0
B19: 44340 | F19: Young Golden Inc | G19: Production services for "Pa que vuelva"- Ecko | H19: 750 | I19: -7.5 | K19: =Table1[[#This Row],[Valor de la Factura del Cliente]]*0.2*-1 -> -150 | L19: =Table1[[#This Row],[Valor de la Factura del Cliente]]*0.05*-1 -> -37.5 | N19: -555 | P19: =SUM(Table1[[#This Row],[Valor de la Factura del Cliente]:[Avance]])+P18 -> 0
B20: 44340 | F20: Young Golden Inc | G20: Production services Ecko, Lyanno for "Como Antes" | H20: 1500 | I20: 0 | K20: =Table1[[#This Row],[Valor de la Factura del Cliente]]*0.2*-1 -> -300 | L20: =Table1[[#This Row],[Valor de la Factura del Cliente]]*0.05*-1 -> -75 | P20: =SUM(Table1[[#This Row],[Valor de la Factura del Cliente]:[Avance]])+P19 -> 1125
B21: 44340 | F21: Young Golden Inc | G21: Mixing services for Ecko, Lyanno "Como Antes" | H21: 2000 | I21: -15 | K21: =Table1[[#This Row],[Valor de la Factura del Cliente]]*0.2*-1 -> -400 | L21: =Table1[[#This Row],[Valor de la Factura del Cliente]]*0.05*-1 -> -100 | N21: -1485 | P21: =SUM(Table1[[#This Row],[Valor de la Factura del Cliente]:[Avance]])+P20 -> 1125
B22: 44342 | F22: Young Golden Inc | G22: Producer payment for Ecko "GO" | H22: 1500 | I22: -7.5 | K22: =Table1[[#This Row],[Valor de la Factura del Cliente]]*0.2*-1 -> -300 | L22: =Table1[[#This Row],[Valor de la Factura del Cliente]]*0.05*-1 -> -75 | N22: -1117.5 | P22: =SUM(Table1[[#This Row],[Valor de la Factura del Cliente]:[Avance]])+P21 -> 1125
B23: 44342 | F23: Young Golden Inc | G23: Mixing services payment for Ecko "GO" | H23: 500 | I23: -7.5 | K23: =Table1[[#This Row],[Valor de la Factura del Cliente]]*0.2*-1 -> -100 | L23: =Table1[[#This Row],[Valor de la Factura del Cliente]]*0.05*-1 -> -25 | N23: -367.5 | P23: =SUM(Table1[[#This Row],[Valor de la Factura del Cliente]:[Avance]])+P22 -> 1125
B24: 44425 | F24: CYC Music Inc. | G24: Production services for Cauty single "Tenemos Gente" | H24: 1500 | I24: -15 | K24: =Table1[[#This Row],[Valor de la Factura del Cliente]]*0.2*-1 -> -300 | L24: =Table1[[#This Row],[Valor de la Factura del Cliente]]*0.05*-1 -> -75 | P24: =SUM(Table1[[#This Row],[Valor de la Factura del Cliente]:[Avance]])+P23 -> 2235
B25: 44441 | F25: Bartives SA | G25: Production services for Valen Madanes "Donde Quedo" | H25: 1000 | I25: -15 | K25: =Table1[[#This Row],[Valor de la Factura del Cliente]]*0.2*-1 -> -200 | L25: =Table1[[#This Row],[Valor de la Factura del Cliente]]*0.05*-1 -> -50 | M25: -6 | P25: =SUM(Table1[[#This Row],[Valor de la Factura del Cliente]:[Avance]])+P24 -> 2964
B26: 44473 | F26: SAYCE | G26: Music jury urban category contest performed by Mozart Muzik | H26: 1333.33 | I26: -25 | K26: -200 | L26: -50 | M26: -333.33 | P26: =SUM(Table1[[#This Row],[Valor de la Factura del Cliente]:[Avance]])+P25 -> 3689
B27: 44648 | F27: Young Golden Inc | G27: Servicios de Produccion COPACABANA | H27: 3000 | K27: =Table1[[#This Row],[Valor de la Factura del Cliente]]*0.2*-1 -> -600 | L27: =Table1[[#This Row],[Valor de la Factura del Cliente]]*0.05*-1 -> -150 | P27: =SUM(Table1[[#This Row],[Valor de la Factura del Cliente]:[Avance]])+P26 -> 5939
B28: 44707 | F28: WK RECORDS LLC | G28: Services of a musical production Cancion Seven Kayne-Si Supieras | H28: 2500 | K28: =Table1[[#This Row],[Valor de la Factura del Cliente]]*0.2*-1 -> -500 | L28: =Table1[[#This Row],[Valor de la Factura del Cliente]]*0.05*-1 -> -125 | P28: =SUM(Table1[[#This Row],[Valor de la Factura del Cliente]:[Avance]])+P27 -> 7814
G29: Computer (Producto: MK183E/A Serie: WXXP02J4KH) | K29: =Table1[[#This Row],[Valor de la Factura del Cliente]]*0.2*-1 -> 0 | L29: =Table1[[#This Row],[Valor de la Factura del Cliente]]*0.05*-1 -> 0 | N29: -3090 | P29: =SUM(Table1[[#This Row],[Valor de la Factura del Cliente]:[Avance]])+P28 -> 4724
G30: Microphone Purchase | K30: =Table1[[#This Row],[Valor de la Factura del Cliente]]*0.2*-1 -> 0 | L30: =Table1[[#This Row],[Valor de la Factura del Cliente]]*0.05*-1 -> 0 | N30: -3529.93 | P30: =SUM(Table1[[#This Row],[Valor de la Factura del Cliente]:[Avance]])+P29 -> 1194.07
B31: 45099 | F31: Q12020-Q12025 | G31: Royalty BMI | H31: 3253.505 | P31: =SUM(Table1[[#This Row],[Valor de la Factura del Cliente]:[Avance]])+P30 -> 4447.575
B32: 45093 | F32: Q12025 | G32: Regalías Mecanicas | H32: 11757.77 | K32: =Table1[[#This Row],[Valor de la Factura del Cliente]]*0.2*-1 -> -2351.554 | L32: =Table1[[#This Row],[Valor de la Factura del Cliente]]*0.05*-1 -> -587.8885 | P32: =SUM(Table1[[#This Row],[Valor de la Factura del Cliente]:[Avance]])+P31 -> 13265.903
B33: 44769 | F33: Guitar Center | K33: =Table1[[#This Row],[Valor de la Factura del Cliente]]*0.2*-1 -> 0 | L33: =Table1[[#This Row],[Valor de la Factura del Cliente]]*0.05*-1 -> 0 | N33: -3561.09 | P33: =SUM(Table1[[#This Row],[Valor de la Factura del Cliente]:[Avance]])+P32 -> 9704.8125
B34: 44866 | F34: Mozart Musik | G34: Pago Avance a Futura Factura | K34: =Table1[[#This Row],[Valor de la Factura del Cliente]]*0.2*-1 -> 0 | L34: =Table1[[#This Row],[Valor de la Factura del Cliente]]*0.05*-1 -> 0 | N34: -2145 | P34: =SUM(Table1[[#This Row],[Valor de la Factura del Cliente]:[Avance]])+P33 -> 7559.8125
B35: 44873 | F35: Cross Latam LLC | H35: 11800 | K35: =Table1[[#This Row],[Valor de la Factura del Cliente]]*0.2*-1 -> -2360 | L35: =Table1[[#This Row],[Valor de la Factura del Cliente]]*0.05*-1 -> -590 | M35: -573.78 | P35: =SUM(Table1[[#This Row],[Valor de la Factura del Cliente]:[Avance]])+P34 -> 15836.032
B36: 44999 | F36: Sweetwater Sound INC. | G36: Pago Avance a Futura Factura | K36: =Table1[[#This Row],[Valor de la Factura del Cliente]]*0.2*-1 -> 0 | L36: =Table1[[#This Row],[Valor de la Factura del Cliente]]*0.05*-1 -> 0 | N36: -4194.4 | P36: =SUM(Table1[[#This Row],[Valor de la Factura del Cliente]:[Avance]])+P35 -> 11641.632
B37: 45007 | F37: Mozart Musik | G37: Pago Avance a Futura Factura | K37: =Table1[[#This Row],[Valor de la Factura del Cliente]]*0.2*-1 -> 0 | L37: =Table1[[#This Row],[Valor de la Factura del Cliente]]*0.05*-1 -> 0 | N37: -3148.58 | P37: =SUM(Table1[[#This Row],[Valor de la Factura del Cliente]:[Avance]])+P36 -> 8493.0525
B38: 45068 | F38: Mozart Musik | G38: La Viste Venir LLC | H38: 8000 | I38: -25 | K38: =Table1[[#This Row],[Valor de la Factura del Cliente]]*0.2*-1 -> -1600 | L38: =Table1[[#This Row],[Valor de la Factura del Cliente]]*0.05*-1 -> -400 | P38: =SUM(Table1[[#This Row],[Valor de la Factura del Cliente]:[Avance]])+P37 -> 14468.052
B39: 45071 | F39: Sweetwater Sound INC. | K39: =Table1[[#This Row],[Valor de la Factura del Cliente]]*0.2*-1 -> 0 | L39: =Table1[[#This Row],[Valor de la Factura del Cliente]]*0.05*-1 -> 0 | N39: -3849.86 | P39: =SUM(Table1[[#This Row],[Valor de la Factura del Cliente]:[Avance]])+P38 -> 10618.192
B40: 45077 | F40: Mozart Musik | G40: Boutique SRL | H40: 5000 | I40: -25 | K40: =Table1[[#This Row],[Valor de la Factura del Cliente]]*0.2*-1 -> -1000 | L40: =Table1[[#This Row],[Valor de la Factura del Cliente]]*0.05*-1 -> -250 | P40: =SUM(Table1[[#This Row],[Valor de la Factura del Cliente]:[Avance]])+P39 -> 14343.192
B41: 45099 | F41: Mozart Musik | G41: Avance Solicitado | K41: =Table1[[#This Row],[Valor de la Factura del Cliente]]*0.2*-1 -> 0 | L41: =Table1[[#This Row],[Valor de la Factura del Cliente]]*0.05*-1 -> 0 | N41: -4405.66 | P41: =SUM(Table1[[#This Row],[Valor de la Factura del Cliente]:[Avance]])+P40 -> 9937.5325
B42: 45184 | F42: Mozart Musik | G42: Pago Avance | K42: =Table1[[#This Row],[Valor de la Factura del Cliente]]*0.2*-1 -> 0 | L42: =Table1[[#This Row],[Valor de la Factura del Cliente]]*0.05*-1 -> 0 | N42: -800 | P42: =SUM(Table1[[#This Row],[Valor de la Factura del Cliente]:[Avance]])+P41 -> 9137.5325
B43: 45252 | F43: Mozart Musik | G43: Pago Realizado | I43: -25 | K43: =Table1[[#This Row],[Valor de la Factura del Cliente]]*0.2*-1 -> 0 | L43: =Table1[[#This Row],[Valor de la Factura del Cliente]]*0.05*-1 -> 0 | N43: -1518 | P43: =SUM(Table1[[#This Row],[Valor de la Factura del Cliente]:[Avance]])+P42 -> 7594.5325
B44: 45288 | F44: Mozart Musik | G44: Avance Solicitado | K44: =Table1[[#This Row],[Valor de la Factura del Cliente]]*0.2*-1 -> 0 | L44: =Table1[[#This Row],[Valor de la Factura del Cliente]]*0.05*-1 -> 0 | N44: -500 | P44: =SUM(Table1[[#This Row],[Valor de la Factura del Cliente]:[Avance]])+P43 -> 7094.5325
B45: 45309 | F45: Mozart Musik | G45: Avance Solicitado | K45: =Table1[[#This Row],[Valor de la Factura del Cliente]]*0.2*-1 -> 0 | L45: =Table1[[#This Row],[Valor de la Factura del Cliente]]*0.05*-1 -> 0 | N45: -3723.5 | P45: =SUM(Table1[[#This Row],[Valor de la Factura del Cliente]:[Avance]])+P44 -> 3371.0325
B46: 45310 | F46: Mozart Musik | G46: Devolución SweetWater Sound realizada | H46: 3849.86 | P46: =SUM(Table1[[#This Row],[Valor de la Factura del Cliente]:[Avance]])+P45 -> 7220.8925
B47: 45354 | F47: Mozart Musik | G47: Avance Solicitado | K47: =Table1[[#This Row],[Valor de la Factura del Cliente]]*0.2*-1 -> 0 | L47: =Table1[[#This Row],[Valor de la Factura del Cliente]]*0.05*-1 -> 0 | N47: -3000 | P47: =SUM(Table1[[#This Row],[Valor de la Factura del Cliente]:[Avance]])+P46 -> 4220.8925
B48: 45369 | F48: Mozart Musik | G48: Avance Solicitado | K48: =Table1[[#This Row],[Valor de la Factura del Cliente]]*0.2*-1 -> 0 | L48: =Table1[[#This Row],[Valor de la Factura del Cliente]]*0.05*-1 -> 0 | N48: -966.81 | P48: =SUM(Table1[[#This Row],[Valor de la Factura del Cliente]:[Avance]])+P47 -> 3254.0825
B49: 45370 | F49: Mozart Musik | G49: Studio Rental Neon16 | H49: 400 | I49: -15 | K49: =Table1[[#This Row],[Valor de la Factura del Cliente]]*0.2*-1 -> -80 | L49: =Table1[[#This Row],[Valor de la Factura del Cliente]]*0.05*-1 -> -20 | P49: =SUM(Table1[[#This Row],[Valor de la Factura del Cliente]:[Avance]])+P48 -> 3539.0825
B50: 45371 | F50: Mozart Musik | G50: Studio Rental Neon16 | H50: 0 | I50: 0 | K50: =Table1[[#This Row],[Valor de la Factura del Cliente]]*0.2*-1 -> 0 | L50: =Table1[[#This Row],[Valor de la Factura del Cliente]]*0.05*-1 -> 0 | N50: -848.6 | P50: =SUM(Table1[[#This Row],[Valor de la Factura del Cliente]:[Avance]])+P49 -> 2690.4825
B51: 45444 | F51: Mozart Musik | G51: Adelanto | H51: 0 | I51: 0 | K51: =Table1[[#This Row],[Valor de la Factura del Cliente]]*0.2*-1 -> 0 | L51: =Table1[[#This Row],[Valor de la Factura del Cliente]]*0.05*-1 -> 0 | N51: -131 | P51: =SUM(Table1[[#This Row],[Valor de la Factura del Cliente]:[Avance]])+P50 -> 2559.4825
B52: 45463 | F52: Mozart Musik | G52: Adelanto | H52: 0 | I52: 0 | K52: =Table1[[#This Row],[Valor de la Factura del Cliente]]*0.2*-1 -> 0 | L52: =Table1[[#This Row],[Valor de la Factura del Cliente]]*0.05*-1 -> 0 | N52: -2000 | P52: =SUM(Table1[[#This Row],[Valor de la Factura del Cliente]:[Avance]])+P51 -> 559.4825
B53: 45677 | F53: Mozart Musik | G53: Adelanto | H53: 0 | I53: 0 | K53: =Table1[[#This Row],[Valor de la Factura del Cliente]]*0.2*-1 -> 0 | L53: =Table1[[#This Row],[Valor de la Factura del Cliente]]*0.05*-1 -> 0 | N53: -754.99 | P53: =SUM(Table1[[#This Row],[Valor de la Factura del Cliente]:[Avance]])+P52 -> -195.5075
B54: 45692 | F54: Mozart Musik | G54: Adelanto | H54: 0 | I54: 0 | K54: =Table1[[#This Row],[Valor de la Factura del Cliente]]*0.2*-1 -> 0 | L54: =Table1[[#This Row],[Valor de la Factura del Cliente]]*0.05*-1 -> 0 | N54: -200 | P54: =SUM(Table1[[#This Row],[Valor de la Factura del Cliente]:[Avance]])+P53 -> -395.5075
B55: 45784 | F55: Bartives SA | G55: Servicios de Produccion de José Luis Nisco Chaparro en el Proyecto "POSITIVO" | H55: 400 | I55: -15 | K55: =Table1[[#This Row],[Valor de la Factura del Cliente]]*0.2*-1 -> -80 | L55: =Table1[[#This Row],[Valor de la Factura del Cliente]]*0.05*-1 -> -20 | N55: 0 | P55: =SUM(Table1[[#This Row],[Valor de la Factura del Cliente]:[Avance]])+P54 -> -110.5075
B56: 45797 | F56: Mozart Musik | G56: Adelanto | H56: 0 | I56: 0 | K56: =Table1[[#This Row],[Valor de la Factura del Cliente]]*0.2*-1 -> 0 | L56: =Table1[[#This Row],[Valor de la Factura del Cliente]]*0.05*-1 -> 0 | N56: -249.99 | P56: =SUM(Table1[[#This Row],[Valor de la Factura del Cliente]:[Avance]])+P55 -> -360.4975
B57: 45804 | F57: 22 Label Group | G57: Producción NASHY-NASHAI "Como Le Digo" Mozart Musik | H57: 800 | I57: -42.3 | K57: =Table1[[#This Row],[Valor de la Factura del Cliente]]*0.2*-1 -> -160 | L57: =Table1[[#This Row],[Valor de la Factura del Cliente]]*0.05*-1 -> -40 | N57: 0 | P57: =SUM(Table1[[#This Row],[Valor de la Factura del Cliente]:[Avance]])+P56 -> 197.2025
B58: 45805 | F58: Paranoid Filmes | G58: Licensing fees Reggaeton de Antes "DNA do Crime" | H58: 2500 | I58: -92 | K58: =Table1[[#This Row],[Valor de la Factura del Cliente]]*0.2*-1 -> -500 | L58: =Table1[[#This Row],[Valor de la Factura del Cliente]]*0.05*-1 -> -125 | N58: 0 | P58: =SUM(Table1[[#This Row],[Valor de la Factura del Cliente]:[Avance]])+P57 -> 1980.2025
B59: 45810 | F59: Mozart Musik | G59: Adelanto | H59: 0 | I59: 0 | K59: =Table1[[#This Row],[Valor de la Factura del Cliente]]*0.2*-1 -> 0 | L59: =Table1[[#This Row],[Valor de la Factura del Cliente]]*0.05*-1 -> 0 | N59: -2458.28 | P59: =SUM(Table1[[#This Row],[Valor de la Factura del Cliente]:[Avance]])+P58 -> -478.0775
B60: 45814 | F60: Line of Blue LLC | G60: Mozart en la cancion Hablando Mal Mhtresuno | H60: 1000 | I60: -15 | K60: =Table1[[#This Row],[Valor de la Factura del Cliente]]*0.2*-1 -> -200 | L60: =Table1[[#This Row],[Valor de la Factura del Cliente]]*0.05*-1 -> -50 | N60: 0 | P60: =SUM(Table1[[#This Row],[Valor de la Factura del Cliente]:[Avance]])+P59 -> 256.9225
B61: 45860 | F61: Mozart Musik | G61: Adelanto | H61: 0 | I61: 0 | K61: =Table1[[#This Row],[Valor de la Factura del Cliente]]*0.2*-1 -> 0 | L61: =Table1[[#This Row],[Valor de la Factura del Cliente]]*0.05*-1 -> 0 | N61: -254.99 | P61: =SUM(Table1[[#This Row],[Valor de la Factura del Cliente]:[Avance]])+P60 -> 1.9325
... B65: 45937 | F65: Mozart Musik | G65: Adelanto | H65: 0 | I65: -25 | K65: =Table1[[#This Row],[Valor de la Factura del Cliente]]*0.2*-1 -> 0 | L65: =Table1[[#This Row],[Valor de la Factura del Cliente]]*0.05*-1 -> 0 | N65: -3159 | P65: =SUM(Table1[[#This Row],[Valor de la Factura del Cliente]:[Avance]])+P64 -> 725.4325
G66: TOTAL | H66: =SUBTOTAL(109,Table1[Valor de la Factura del Cliente]) -> 77014.465 | I66: =SUBTOTAL(109,Table1[Cargos Bancarios]) -> -469.3 | K66: =SUBTOTAL(109,Table1[20% Comisión]) -> -13915.554 | L66: =SUBTOTAL(109,Table1[5% Legal]) -> -3478.8885 | M66: =SUBTOTAL(109,Table1[Retención de Impuestos]) -> -926.31 | N66: =SUBTOTAL(109,Table1[Pagado por MVPX]) -> -57498.98 | O66: =SUBTOTAL(109,Table1[Avance]) -> 0 | P66: =SUM(Table1[[#Totals],[Valor de la Factura del Cliente]:[Avance]]) -> 725.4325

Sheet HACHE
B2: Artista: | E2: =+'Base de datos'!B19 -> Hache
B3: Nombre legal: | E3: =+_xlfn.CONCAT('Base de datos'!C19," ",'Base de datos'!D19) -> Taveras Bryan Argenis
B4: Fecha de inicio: | E4: =MIN(Table134[Fecha]) -> 43907
B5: Fecha fin: | E5: =MAX(Table134[Fecha]) -> 45899
B7: ESTADO DE CUENTA
B8: Fecha | C8: Número | D8: Tipo | E8: Método de pago | F8: Nombre | G8: Concepto | H8: Valor de la Factura del Cliente | I8: Cargos Bancarios | J8: 50% Fee | K8: 20% Comisión | L8: 5% Legal | M8: Retención de Impuestos | N8: Pagado por MVPX | O8: Avance | P8: Balance
B9: 43907 | F9: Bryan A. Taveras/798923892 | G9: Pago al Compositor | O9: 929.99 | P9: =SUM(Table134[[#This Row],[Valor de la Factura del Cliente]:[Avance]]) -> 929.99
B10: 43910 | F10: Bryan A. Taveras/798923892 | G10: VTMAC | O10: 300 | P10: =+P9+Table134[[#This Row],[Avance]]-Table134[[#This Row],[Pagado por MVPX]] -> 1229.99
B11: 44196 | F11: Eco Music Services | H11: 1344.54 | K11: -268.908 | N11: =+Table134[[#This Row],[Valor de la Factura del Cliente]]+Table134[[#This Row],[20% Comisión]] -> 1075.632 | P11: =+P10+Table134[[#This Row],[Avance]]-Table134[[#This Row],[Pagado por MVPX]] -> 154.358
B12: 44232 | F12: Aracelis Marte | G12: Pago de un Serv, de H | K12: 0 | O12: 167.18141 | P12: =+P11+Table134[[#This Row],[Avance]]-Table134[[#This Row],[Pagado por MVPX]] -> 321.53941
B13: 44306 | F13: YSMEL STEVEN ABREU/8300360562 | G13: Arte Video Hache | K13: 0 | O13: 211.17652 | P13: =+P12+Table134[[#This Row],[Avance]]-Table134[[#This Row],[Pagado por MVPX]] -> 532.71593
B14: 44306 | F14: IVETTE VIRGINIA BATISTA/798312948 | G14: Video Vestuario, Conjunto Rojo, Crema | K14: 0 | O14: 105.2187 | P14: =+P13+Table134[[#This Row],[Avance]]-Table134[[#This Row],[Pagado por MVPX]] -> 637.93463
B15: 44307 | F15: IVETTE VIRGINIA BATISTA/798312948 | G15: Video Vestuario, Conjunto Rojo, Crema | K15: 0 | O15: 98.549041 | P15: =+P14+Table134[[#This Row],[Avance]]-Table134[[#This Row],[Pagado por MVPX]] -> 736.48367
B16: 44310 | F16: SR ELIO E LISSANDRELLO NUNEZ/820708964 | G16: Pago Servicios de Peluqueria | K16: 0 | O16: 35.196086 | P16: =+P15+Table134[[#This Row],[Avance]]-Table134[[#This Row],[Pagado por MVPX]] -> 771.67975
B17: 44315 | F17: YSMEL STEVEN ABREU/8300360562 | G17: Pago Video de Hache | K17: 0 | O17: 167.18141 | P17: =+P16+Table134[[#This Row],[Avance]]-Table134[[#This Row],[Pagado por MVPX]] -> 938.86116
B18: 44358 | F18: JULIAN E ROA/793978644 | G18: Alquiler de Un Equipo | K18: 0 | O18: 140.78434 | P18: =+P17+Table134[[#This Row],[Avance]]-Table134[[#This Row],[Pagado por MVPX]] -> 1079.6455
B19: 44358 | F19: JUAN CARLOS PAULINO/809934821 | G19: Pago del Video de H | K19: 0 | O19: 244.77 | P19: =+P18+Table134[[#This Row],[Avance]]-Table134[[#This Row],[Pagado por MVPX]] -> 1324.4155
B20: 44361 | F20: ERIC ALVAREZ/86277847673 | K20: 0 | O20: 107 | P20: =+P19+Table134[[#This Row],[Avance]]-Table134[[#This Row],[Pagado por MVPX]] -> 1431.4155
B21: 44364 | G21: Pago Marcio Y Recorte de Video | K21: 0 | O21: 200 | P21: =+P20+Table134[[#This Row],[Avance]]-Table134[[#This Row],[Pagado por MVPX]] -> 1631.4155
B22: 44380 | F22: Mono Polio Midia | G22: Mercadeo del Video de H | K22: 0 | O22: 1000 | P22: =+P21+Table134[[#This Row],[Avance]]-Table134[[#This Row],[Pagado por MVPX]] -> 2631.4155
B23: 44442 | F23: JUAN CARLOS PAULINO/809934821 | G23: Pago del Video de H | K23: 0 | O23: 334.29243 | P23: =+P22+Table134[[#This Row],[Avance]]-Table134[[#This Row],[Pagado por MVPX]] -> 2965.7079
B24: 44442 | F24: YSMEL STEVEN ABREU/8300360562 | K24: 0 | O24: 124.74481 | P24: =+P23+Table134[[#This Row],[Avance]]-Table134[[#This Row],[Pagado por MVPX]] -> 3090.4527
B25: 44442 | F25: Eduardo Dreyer | G25: Director de Camara | K25: 0 | O25: 1200 | P25: =+P24+Table134[[#This Row],[Avance]]-Table134[[#This Row],[Pagado por MVPX]] -> 4290.4527
B26: 44442 | F26: Hunter | G26: Asistente de Camara | K26: 0 | O26: 180 | P26: =+P25+Table134[[#This Row],[Avance]]-Table134[[#This Row],[Pagado por MVPX]] -> 4470.4527
B27: 44442 | F27: Alfonso | G27: Gaffer | K27: 0 | O27: 140 | P27: =+P26+Table134[[#This Row],[Avance]]-Table134[[#This Row],[Pagado por MVPX]] -> 4610.4527
B28: 44442 | F28: Joan | G28: Asist De Arte | K28: 0 | O28: 93 | P28: =+P27+Table134[[#This Row],[Avance]]-Table134[[#This Row],[Pagado por MVPX]] -> 4703.4527
B29: 44442 | F29: Jacu | G29: Grafitti | K29: 0 | O29: 157 | P29: =+P28+Table134[[#This Row],[Avance]]-Table134[[#This Row],[Pagado por MVPX]] -> 4860.4527
B30: 44442 | G30: Pintura Graffiti y Prints | K30: 0 | O30: 188 | P30: =+P29+Table134[[#This Row],[Avance]]-Table134[[#This Row],[Pagado por MVPX]] -> 5048.4527
B31: 44442 | G31: Snorricam | K31: 0 | O31: 100 | P31: =+P30+Table134[[#This Row],[Avance]]-Table134[[#This Row],[Pagado por MVPX]] -> 5148.4527
B32: 44442 | G32: Modelo Principal | K32: 0 | O32: 98 | P32: =+P31+Table134[[#This Row],[Avance]]-Table134[[#This Row],[Pagado por MVPX]] -> 5246.4527
B33: 44442 | G33: Cocinera | K33: 0 | O33: 72 | P33: =+P32+Table134[[#This Row],[Avance]]-Table134[[#This Row],[Pagado por MVPX]] -> 5318.4527
B34: 44442 | G34: Comida | K34: 0 | O34: 132 | P34: =+P33+Table134[[#This Row],[Avance]]-Table134[[#This Row],[Pagado por MVPX]] -> 5450.4527
B35: 44442 | G35: Bebidas | K35: 0 | O35: 69 | P35: =+P34+Table134[[#This Row],[Avance]]-Table134[[#This Row],[Pagado por MVPX]] -> 5519.4527
B36: 44442 | G36: Miselaneous | K36: 0 | O36: 178.9 | P36: =+P35+Table134[[#This Row],[Avance]]-Table134[[#This Row],[Pagado por MVPX]] -> 5698.3527
B37: 44901 | F37: Elisabeth Comabella ( Eco Music) | G37: Colaboraciones con lennis | H37: 1779.02 | K37: -355.804 | N37: 1423.216 | P37: =+P36+Table134[[#This Row],[Avance]]-Table134[[#This Row],[Pagado por MVPX]] -> 4275.1367
B38: 44923 | G38: Comida | K38: 0 | O38: 218.18182 | P38: =+P37+Table134[[#This Row],[Avance]]-Table134[[#This Row],[Pagado por MVPX]] -> 4493.3186
B39: 44959 | F39: Star Island LLC / La familia | G39: Soltera & Soltera Remix | H39: 57951.01 | K39: -11590.202 | N39: 46360.808 | P39: =+P38+Table134[[#This Row],[Avance]]-Table134[[#This Row],[Pagado por MVPX]] -> -41867.489
B40: 44985 | G40: Comida | O40: 20.71 | P40: =+P39+Table134[[#This Row],[Avance]]-Table134[[#This Row],[Pagado por MVPX]] -> -41846.779
B41: 44985 | F41: Frontier | G41: Trip Luggage | O41: 118.38 | P41: =+P40+Table134[[#This Row],[Avance]]-Table134[[#This Row],[Pagado por MVPX]] -> -41728.399
B42: 44986 | F42: jetblue | G42: Trip Luggage | O42: 260.2 | P42: =+P41+Table134[[#This Row],[Avance]]-Table134[[#This Row],[Pagado por MVPX]] -> -41468.199
B43: 44986 | F43: jetblue | G43: Flight | O43: 30 | P43: =+P42+Table134[[#This Row],[Avance]]-Table134[[#This Row],[Pagado por MVPX]] -> -41438.199
B44: 44987 | F44: Bebos Café | G44: Food | O44: 20.71 | P44: =+P43+Table134[[#This Row],[Avance]]-Table134[[#This Row],[Pagado por MVPX]] -> -41417.489
B45: 44995 | F45: Avance | G45: Avance H | O45: 1000 | P45: =+P44+Table134[[#This Row],[Avance]]-Table134[[#This Row],[Pagado por MVPX]] -> -40417.489
B46: 45003 | F46: APPLE STORE | G46: PHONE | O46: 1350 | P46: =+P45+Table134[[#This Row],[Avance]]-Table134[[#This Row],[Pagado por MVPX]] -> -39067.489
B47: 45028 | F47: Premium Gold | G47: Hotel | O47: 142.38 | P47: =+P46+Table134[[#This Row],[Avance]]-Table134[[#This Row],[Pagado por MVPX]] -> -38925.109
B48: 45041 | F48: Avance | G48: Avance H | O48: 1000 | P48: =+P47+Table134[[#This Row],[Avance]]-Table134[[#This Row],[Pagado por MVPX]] -> -37925.109
B49: 45051 | F49: Gastos en USA | G49: Desde el 06-03-2023 / 04-27-2023 | O49: 15631.02 | P49: =+P48+Table134[[#This Row],[Avance]]-Table134[[#This Row],[Pagado por MVPX]] -> -22294.089
B50: 45055 | F50: Retenciones de BMI | G50: Desde el 2018-03 Hasta 2024-04. | O50: 11095.32 | P50: =+P49+Table134[[#This Row],[Avance]]-Table134[[#This Row],[Pagado por MVPX]] -> -11198.769
B51: 45007 | F51: Adelanto Solicitado | G51: Adelanto Solicitado | O51: 2000 | P51: =+P50+Table134[[#This Row],[Avance]]-Table134[[#This Row],[Pagado por MVPX]] -> -9198.7694
B52: 45057 | F52: Adelanto Solicitado | G52: Adelanto Solicitado | O52: 2000 | P52: =+P51+Table134[[#This Row],[Avance]]-Table134[[#This Row],[Pagado por MVPX]] -> -7198.7694
B53: 45047 | F53: Vuelo Mia-Sto Dgo | G53: Vuelo Mia-Sto Dgo | O53: 244.25 | P53: =+P52+Table134[[#This Row],[Avance]]-Table134[[#This Row],[Pagado por MVPX]] -> -6954.5194
F54: Legendary Music | G54: Reguetonera Anuel | H54: 20000 | K54: -4000 | N54: 16000 | P54: =+P53+Table134[[#This Row],[Avance]]-Table134[[#This Row],[Pagado por MVPX]] -> -22954.519
F55: APPLE STORE | G55: Pago del Security Theft | O55: 150 | P55: =+P54+Table134[[#This Row],[Avance]]-Table134[[#This Row],[Pagado por MVPX]] -> -22804.519
B56: 45093 | F56: Ingresos SongTrust | G56: Ingresos SongTrust | H56: 74.73 | K56: -18.6825 | N56: 59.7875 | P56: =+P55+Table134[[#This Row],[Avance]]-Table134[[#This Row],[Pagado por MVPX]] -> -22864.307
B57: 45090 | F57: Avance | G57: Avance H paypal | O57: 3500 | P57: =+P56+Table134[[#This Row],[Avance]]-Table134[[#This Row],[Pagado por MVPX]] -> -19364.307
B58: 45113 | F58: Avance | G58: Avance H Remitly | O58: 2000 | P58: =+P57+Table134[[#This Row],[Avance]]-Table134[[#This Row],[Pagado por MVPX]] -> -17364.307
B59: 45134 | F59: Avance | G59: Avance H paypal | O59: 1000 | P59: =+P58+Table134[[#This Row],[Avance]]-Table134[[#This Row],[Pagado por MVPX]] -> -16364.307
B60: 45145 | F60: Avance | G60: Avance H Remitly | O60: 1000 | P60: =+P59+Table134[[#This Row],[Avance]]-Table134[[#This Row],[Pagado por MVPX]] -> -15364.307
B61: 45188 | G61: Avance Solicitado | O61: 15364.31 | P61: =+P60+Table134[[#This Row],[Avance]]-Table134[[#This Row],[Pagado por MVPX]] -> 0.0030610592
G62: Regalías Mecanicas | H62: 7288.39 | K62: -2056 | N62: 5232.39 | P62: =+P61+Table134[[#This Row],[Avance]]-Table134[[#This Row],[Pagado por MVPX]] -> -5232.3869
G63: Retenciones BMI | O63: 1813.9085 | P63: =+P62+Table134[[#This Row],[Avance]]-Table134[[#This Row],[Pagado por MVPX]] -> -3418.4784
B64: 45278 | G64: Avance H Remitly | O64: 700 | P64: =+P63+Table134[[#This Row],[Avance]]-Table134[[#This Row],[Pagado por MVPX]] -> -2718.4784
B65: 45294 | G65: Solicitud de Avance | O65: 85.32 | P65: =+P64+Table134[[#This Row],[Avance]]-Table134[[#This Row],[Pagado por MVPX]] -> -2633.1584
B66: 45296 | G66: Avance realizado (TYS) | H66: 457 | K66: -91.4 | N66: 365.6 | O66: 457 | P66: =+P65+Table134[[#This Row],[Avance]]-Table134[[#This Row],[Pagado por MVPX]] -> -2541.7584
B67: 45316 | G67: Avance H Remitly | O67: 500 | P67: =+P66+Table134[[#This Row],[Avance]]-Table134[[#This Row],[Pagado por MVPX]] -> -2041.7584
B68: 45322 | G68: Seguro de Apple | O68: 14.99 | P68: =+P67+Table134[[#This Row],[Avance]]-Table134[[#This Row],[Pagado por MVPX]] -> -2026.7684
B69: 45349 | G69: Avance Hache Remitly | O69: 500 | P69: =+P68+Table134[[#This Row],[Avance]]-Table134[[#This Row],[Pagado por MVPX]] -> -1526.7684
B70: 45349 | G70: Seguro de Apple | O70: 14.99 | P70: =+P69+Table134[[#This Row],[Avance]]-Table134[[#This Row],[Pagado por MVPX]] -> -1511.7784
B71: 45378 | G71: Avance Hache Remitly | O71: 500 | P71: =+P70+Table134[[#This Row],[Avance]]-Table134[[#This Row],[Pagado por MVPX]] -> -1011.7784
B72: 45382 | G72: Seguro de Apple | O72: 14.99 | P72: =+P71+Table134[[#This Row],[Avance]]-Table134[[#This Row],[Pagado por MVPX]] -> -996.78844
B73: 45382 | G73: Seguro de Apple | O73: 14.99 | P73: =+P72+Table134[[#This Row],[Avance]]-Table134[[#This Row],[Pagado por MVPX]] -> -981.79844
B74: 45443 | G74: Compra de Pasajes para campamento en Colombia | O74: 415.64 | P74: =+P73+Table134[[#This Row],[Avance]]-Table134[[#This Row],[Pagado por MVPX]] -> -566.15844
B75: 45473 | G75: Seguro de Apple | O75: 14.99 | P75: =+P74+Table134[[#This Row],[Avance]]-Table134[[#This Row],[Pagado por MVPX]] -> -551.16844
B76: 45503 | G76: Seguro de Apple | O76: 14.99 | P76: =+P75+Table134[[#This Row],[Avance]]-Table134[[#This Row],[Pagado por MVPX]] -> -536.17844
B77: 45534 | G77: Seguro de Apple | O77: 14.99 | P77: =+P76+Table134[[#This Row],[Avance]]-Table134[[#This Row],[Pagado por MVPX]] -> -521.18844
B78: 45565 | G78: Seguro de Apple | O78: 14.99 | P78: =+P77+Table134[[#This Row],[Avance]]-Table134[[#This Row],[Pagado por MVPX]] -> -506.19844
... B89: 45899 | G89: Seguro de Apple | O89: 14.99 | P89: =+P88+Table134[[#This Row],[Avance]]-Table134[[#This Row],[Pagado por MVPX]] -> -341.30844
G90: TOTAL | H90: =SUBTOTAL(109,Table134[Valor de la Factura del Cliente]) -> 88894.69 | I90: =SUBTOTAL(109,Table134[Cargos Bancarios]) -> 0 | K90: =SUBTOTAL(109,Table134[20% Comisión]) -> -18380.997 | L90: =SUBTOTAL(109,Table134[5% Legal]) -> 0 | M90: =SUBTOTAL(109,Table134[Retención de Impuestos]) -> 0 | N90: =SUBTOTAL(109,Table134[Pagado por MVPX]) -> 70517.434 | O90: =SUBTOTAL(109,Table134[Avance]) -> 70176.125 | P90: =+P89 -> -341.30844

Sheet Borngud
O1: 66-0928468
O2: admin@mvpxmusic.com
O3: Tel Ofi: 787-761-9125
B6: Artista: | E6: =+'Base de datos'!B15 -> Borngud
B7: Nombre legal: | E7: =+'Base de datos'!E15 -> Jhon Emanuel
B8: Fecha de inicio: | E8: =MIN(Table135[Fecha]) -> 45447
B9: Fecha fin: | E9: =MAX(Table135[Fecha]) -> 45923
B11: ESTADO DE CUENTA
B12: Fecha | C12: Número | D12: Tipo | E12: Método de pago | F12: Nombre | G12: Concepto | H12: Valor de la Factura del Cliente | I12: Cargos Bancarios | J12: 50% Fee | K12: 20% Comisión | L12: 5% Legal | M12: Retención de Impuestos | N12: Pagado por MVPX | O12: Avance | P12: Balance
B13: 45447 | F13: Orlando Ferrer | G13: Mastering Selfless | H13: 0 | I13: 0 | K13: 0 | L13: 0 | M13: 0 | N13: -125 | P13: =SUM(Table135[[#This Row],[Valor de la Factura del Cliente]:[Avance]]) -> -125
B14: 45490 | F14: Joseph Emeka | G14: Pago Productor Joseph Emeka | H14: 0 | I14: 0 | K14: 0 | L14: 0 | M14: 0 | N14: -267.99 | P14: =SUM(Table135[[#This Row],[Valor de la Factura del Cliente]:[Avance]])+P13 -> -392.99
B15: 45489 | F15: Studio | G15: Studio Hours | H15: 0 | I15: 0 | K15: 0 | L15: 0 | M15: 0 | N15: -50 | P15: =SUM(Table135[[#This Row],[Valor de la Factura del Cliente]:[Avance]])+P14 -> -442.99
B16: 45505 | F16: Emmanuel John | G16: Borngud | H16: 0 | I16: 0 | K16: 0 | L16: 0 | M16: 0 | N16: -212.99 | P16: =SUM(Table135[[#This Row],[Valor de la Factura del Cliente]:[Avance]])+P15 -> -655.98
B17: 45674 | F17: Emmanuel John | G17: Adelanto Para sacar el Pasaporte | H17: 0 | I17: 0 | K17: 0 | L17: 0 | M17: 0 | N17: -150 | P17: =SUM(Table135[[#This Row],[Valor de la Factura del Cliente]:[Avance]])+P16 -> -805.98
B18: 45692 | F18: Emmanuel John | G18: Compra de temas - Pago de Productores | H18: 0 | I18: 0 | K18: 0 | L18: 0 | M18: 0 | N18: -50 | P18: =SUM(Table135[[#This Row],[Valor de la Factura del Cliente]:[Avance]])+P17 -> -855.98
B19: 45714 | F19: Emmanuel John | G19: Compra de temas - Pago de Productores | H19: 0 | I19: 0 | K19: 0 | L19: 0 | M19: 0 | N19: -200 | P19: =SUM(Table135[[#This Row],[Valor de la Factura del Cliente]:[Avance]])+P18 -> -1055.98
B20: 45737 | F20: Emmanuel John | G20: Compra de temas - Pago de Productores | H20: 0 | I20: 0 | K20: 0 | L20: 0 | M20: 0 | N20: -70 | P20: =SUM(Table135[[#This Row],[Valor de la Factura del Cliente]:[Avance]])+P19 -> -1125.98
B21: 45741 | F21: Emmanuel John | G21: Compra de temas - Pago de Productores | H21: 0 | I21: 0 | K21: 0 | L21: 0 | M21: 0 | N21: -200 | P21: =SUM(Table135[[#This Row],[Valor de la Factura del Cliente]:[Avance]])+P20 -> -1325.98
B22: 45797 | F22: Emmanuel John | G22: Compra de temas - Pago de Productores | H22: 0 | I22: 0 | K22: 0 | L22: 0 | M22: 0 | N22: -520 | P22: =SUM(Table135[[#This Row],[Valor de la Factura del Cliente]:[Avance]])+P21 -> -1845.98
B23: 45829 | F23: Emmanuel John | G23: Compra de temas - Pago de Productores | H23: 0 | I23: 0 | K23: 0 | L23: 0 | M23: 0 | N23: -400 | P23: =SUM(Table135[[#This Row],[Valor de la Factura del Cliente]:[Avance]])+P22 -> -2245.98
B24: 45853 | F24: Emmanuel John | G24: Compra de temas - Pago de Productores | H24: 0 | I24: 0 | K24: 0 | L24: 0 | M24: 0 | N24: -600 | P24: =SUM(Table135[[#This Row],[Valor de la Factura del Cliente]:[Avance]])+P23 -> -2845.98
B25: 45862 | F25: Emmanuel John | G25: Compra de temas - Pago de Productores | H25: 0 | I25: 0 | K25: 0 | L25: 0 | M25: 0 | N25: -600 | P25: =SUM(Table135[[#This Row],[Valor de la Factura del Cliente]:[Avance]])+P24 -> -3445.98
... B27: 45923 | F27: Emmanuel John | G27: Compra de temas - Pago de Productores | H27: 0 | I27: 0 | K27: 0 | L27: 0 | M27: 0 | N27: -900 | P27: =SUM(Table135[[#This Row],[Valor de la Factura del Cliente]:[Avance]])+P26 -> -4645.98
G28: TOTAL | H28: =SUBTOTAL(109,Table135[Valor de la Factura del Cliente]) -> 0 | I28: =SUBTOTAL(109,Table135[Cargos Bancarios]) -> 0 | K28: =SUBTOTAL(109,Table135[20% Comisión]) -> 0 | L28: =SUBTOTAL(109,Table135[5% Legal]) -> 0 | M28: =SUBTOTAL(109,Table135[Retención de Impuestos]) -> 0 | N28: =SUBTOTAL(109,Table135[Pagado por MVPX]) -> -4645.98 | O28: =SUBTOTAL(109,Table135[Avance]) -> 0 | P28: =SUM(Table135[[#Totals],[Valor de la Factura del Cliente]:[Avance]]) -> -4645.98

Sheet Johan Strauss
O1: 66-0928468
O2: admin@mvpxmusic.com
O3: Tel Ofi: 787-761-9125
B6: Artista: | E6: Johan Strauss
B7: Nombre legal:
B8: Fecha de inicio: | E8: =MIN(Table136[Fecha]) -> 44927
B9: Fecha fin: | E9: =MAX(Table136[Fecha]) -> 45406
B11: ESTADO DE CUENTA
B12: Fecha | C12: Número | D12: Tipo | E12: Método de pago | F12: Nombre | G12: Concepto | H12: Valor de la Factura del Cliente | I12: Cargos Bancarios | J12: 50% Fee | K12: 20% Comisión | L12: 5% Legal | M12: Retención de Impuestos | N12: Pagado por MVPX | O12: Avance | P12: Balance
B13: 44927 | F13: Johan Strauss * | G13: Advance Payment | H13: 0 | I13: 0 | K13: 0 | L13: 0 | M13: 0 | N13: -500 | P13: =SUM(Table136[[#This Row],[Valor de la Factura del Cliente]:[Avance]]) -> -500
B14: 44936 | F14: Johan Strauss * | G14: Advance Payment | H14: 0 | I14: 0 | K14: 0 | L14: 0 | M14: 0 | N14: -400 | P14: =SUM(Table136[[#This Row],[Valor de la Factura del Cliente]:[Avance]])+P13 -> -900
B15: 44937 | F15: Johan Strauss * | G15: Food Payment Johan Strauss | H15: 0 | I15: 0 | K15: 0 | L15: 0 | M15: 0 | N15: -29.83 | P15: =SUM(Table136[[#This Row],[Valor de la Factura del Cliente]:[Avance]])+P14 -> -929.83
B16: 44939 | F16: Johan Strauss * | G16: Advance Payment | H16: 0 | I16: 0 | K16: 0 | L16: 0 | M16: 0 | N16: -70 | P16: =SUM(Table136[[#This Row],[Valor de la Factura del Cliente]:[Avance]])+P15 -> -999.83
B17: 44945 | F17: Johan Strauss * | G17: Johan Strauss Expended $140 US ATH 1210 | H17: 0 | I17: 0 | K17: 0 | L17: 0 | M17: 0 | N17: -140 | P17: =SUM(Table136[[#This Row],[Valor de la Factura del Cliente]:[Avance]])+P16 -> -1139.83
B18: 44945 | F18: Johan Strauss * | G18: Food Payment Johan Strauss | H18: 0 | I18: 0 | K18: 0 | L18: 0 | M18: 0 | N18: -24.9 | P18: =SUM(Table136[[#This Row],[Valor de la Factura del Cliente]:[Avance]])+P17 -> -1164.73
B19: 44951 | F19: Johan Strauss * | G19: Food Payment Johan Strauss | H19: 0 | I19: 0 | K19: 0 | L19: 0 | M19: 0 | N19: -25 | P19: =SUM(Table136[[#This Row],[Valor de la Factura del Cliente]:[Avance]])+P18 -> -1189.73
B20: 44951 | F20: Johan Strauss * | G20: Food Payment Johan Strauss | H20: 0 | I20: 0 | K20: 0 | L20: 0 | M20: 0 | N20: -45 | P20: =SUM(Table136[[#This Row],[Valor de la Factura del Cliente]:[Avance]])+P19 -> -1234.73
B21: 44952 | F21: Johan Strauss * | G21: SuperMax Food payment | H21: 0 | I21: 0 | K21: 0 | L21: 0 | M21: 0 | N21: -19.14 | P21: =SUM(Table136[[#This Row],[Valor de la Factura del Cliente]:[Avance]])+P20 -> -1253.87
B22: 44952 | F22: Johan Strauss * | G22: Food Payment Johan Strauss | H22: 0 | I22: 0 | K22: 0 | L22: 0 | M22: 0 | N22: -19.5 | P22: =SUM(Table136[[#This Row],[Valor de la Factura del Cliente]:[Avance]])+P21 -> -1273.37
B23: 44956 | F23: Johan Strauss * | G23: Food SUPERMAX Johan Strauss | H23: 0 | I23: 0 | K23: 0 | L23: 0 | M23: 0 | N23: -13.77 | P23: =SUM(Table136[[#This Row],[Valor de la Factura del Cliente]:[Avance]])+P22 -> -1287.14
B24: 44956 | F24: Johan Strauss * | G24: Food SUPERMAX Johan Strauss | H24: 0 | I24: 0 | K24: 0 | L24: 0 | M24: 0 | N24: -33.45 | P24: =SUM(Table136[[#This Row],[Valor de la Factura del Cliente]:[Avance]])+P23 -> -1320.59
B25: 44958 | F25: Johan Strauss * | G25: Advanced Payment a Johan Strauss x envio Zelle. | H25: 0 | I25: 0 | K25: 0 | L25: 0 | M25: 0 | N25: -1000 | P25: =SUM(Table136[[#This Row],[Valor de la Factura del Cliente]:[Avance]])+P24 -> -2320.59
... B43: 45406 | F43: ATT | G43: Para darle disponibilidad a la cuenta de mvp | H43: 0 | I43: 0 | K43: 0 | L43: 0 | M43: 0 | N43: -510 | P43: =SUM(Table136[[#This Row],[Valor de la Factura del Cliente]:[Avance]])+P42 -> -7079.16
G44: TOTAL | H44: =SUBTOTAL(109,Table136[Valor de la Factura del Cliente]) -> 0 | I44: =SUBTOTAL(109,Table136[Cargos Bancarios]) -> 0 | K44: =SUBTOTAL(109,Table136[20% Comisión]) -> 0 | L44: =SUBTOTAL(109,Table136[5% Legal]) -> 0 | M44: =SUBTOTAL(109,Table136[Retención de Impuestos]) -> 0 | N44: =SUBTOTAL(109,Table136[Pagado por MVPX]) -> -7079.16 | O44: =SUBTOTAL(109,Table136[Avance]) -> 0 | P44: =SUM(Table136[[#Totals],[Valor de la Factura del Cliente]:[Avance]]) -> -7079.16

Sheet Dayan
B2: Artista: | E2: Dayan
B3: Nombre legal: | E3: =+'Base de datos'!E8 -> Dayan Giler
B4: Fecha de inicio: | E4: =MIN(Table13478[Fecha]) -> 44799
B5: Fecha fin: | E5: =MAX(Table13478[Fecha]) -> 45887
B7: ESTADO DE CUENTA
B8: Fecha | C8: Número | D8: Tipo | E8: Método de pago | F8: Nombre | G8: Concepto | H8: Valor de la Factura del Cliente | I8: Cargos Bancarios | J8: 50% Fee | K8: 20% Comisión | L8: 5% Legal | M8: Retención de Impuestos | N8: Pagado por MVPX | O8: Avance | P8: Balance
B9: 45208 | F9: SongTrust | G9: Ingresos SongTrust | H9: 31.83 | I9: 0 | K9: =Table13478[[#This Row],[Valor de la Factura del Cliente]]*0.2 -> 6.366 | L9: =+Table13478[[#This Row],[Valor de la Factura del Cliente]]*0.05 -> 1.5915 | M9: 0 | N9: 0 | O9: 0 | P9: =+Table13478[[#This Row],[Valor de la Factura del Cliente]]-Table13478[[#This Row],[Cargos Bancarios]]-Table13478[[#This Row],[20% Comisión]]-Table13478[[#This Row],[5% Legal]]-Table13478[[#This Row],[Retención de Impuestos]]-Table13478[[#This Row],[Pagado por MVPX]]+Table13478[[#This Row],[Avance]] -> 23.8725
B10: 45208 | F10: Symphonic | G10: Ingresos Symphonic | H10: 237.4 | I10: 0 | K10: =Table13478[[#This Row],[Valor de la Factura del Cliente]]*0.2 -> 47.48 | L10: =+Table13478[[#This Row],[Valor de la Factura del Cliente]]*0.05 -> 11.87 | M10: 0 | N10: 0 | O10: 0 | P10: =+Table13478[[#This Row],[Valor de la Factura del Cliente]]-Table13478[[#This Row],[Cargos Bancarios]]-Table13478[[#This Row],[20% Comisión]]-Table13478[[#This Row],[5% Legal]]-Table13478[[#This Row],[Retención de Impuestos]]-Table13478[[#This Row],[Pagado por MVPX]]+Table13478[[#This Row],[Avance]]+P9 -> 201.9225
B11: 44799 | F11: Artist; Dayan | G11: Payment made to the producer making Dayans new almun "Heracles" | H11: 0 | I11: 0 | K11: =Table13478[[#This Row],[Valor de la Factura del Cliente]]*0.2 -> 0 | L11: =+Table13478[[#This Row],[Valor de la Factura del Cliente]]*0.05 -> 0 | M11: 0 | N11: 372.99 | O11: 0 | P11: =+Table13478[[#This Row],[Valor de la Factura del Cliente]]-Table13478[[#This Row],[Cargos Bancarios]]-Table13478[[#This Row],[20% Comisión]]-Table13478[[#This Row],[5% Legal]]-Table13478[[#This Row],[Retención de Impuestos]]-Table13478[[#This Row],[Pagado por MVPX]]+Table13478[[#This Row],[Avance]]+P10 -> -171.0675
B12: 44830 | F12: Artist; Dayan | G12: Payment made to the producer making Dayans new almun "Heracles" | H12: 0 | I12: 0 | K12: =Table13478[[#This Row],[Valor de la Factura del Cliente]]*0.2 -> 0 | L12: =+Table13478[[#This Row],[Valor de la Factura del Cliente]]*0.05 -> 0 | M12: 0 | N12: 360.99 | O12: 0 | P12: =+Table13478[[#This Row],[Valor de la Factura del Cliente]]-Table13478[[#This Row],[Cargos Bancarios]]-Table13478[[#This Row],[20% Comisión]]-Table13478[[#This Row],[5% Legal]]-Table13478[[#This Row],[Retención de Impuestos]]-Table13478[[#This Row],[Pagado por MVPX]]+Table13478[[#This Row],[Avance]]+P11 -> -532.0575
B13: 44845 | F13: Artist; Dayan | G13: Payment made to the producer making Dayans new almun "Heracles" | H13: 0 | I13: 0 | K13: =Table13478[[#This Row],[Valor de la Factura del Cliente]]*0.2 -> 0 | L13: =+Table13478[[#This Row],[Valor de la Factura del Cliente]]*0.05 -> 0 | M13: 0 | N13: 360.99 | O13: 0 | P13: =+Table13478[[#This Row],[Valor de la Factura del Cliente]]-Table13478[[#This Row],[Cargos Bancarios]]-Table13478[[#This Row],[20% Comisión]]-Table13478[[#This Row],[5% Legal]]-Table13478[[#This Row],[Retención de Impuestos]]-Table13478[[#This Row],[Pagado por MVPX]]+Table13478[[#This Row],[Avance]]+P12 -> -893.0475
B14: 44872 | F14: Artist; Dayan | G14: To Record Weekenes video marketing expenses | H14: 0 | I14: 0 | K14: =Table13478[[#This Row],[Valor de la Factura del Cliente]]*0.2 -> 0 | L14: =+Table13478[[#This Row],[Valor de la Factura del Cliente]]*0.05 -> 0 | M14: 0 | N14: 1620 | O14: 0 | P14: =+Table13478[[#This Row],[Valor de la Factura del Cliente]]-Table13478[[#This Row],[Cargos Bancarios]]-Table13478[[#This Row],[20% Comisión]]-Table13478[[#This Row],[5% Legal]]-Table13478[[#This Row],[Retención de Impuestos]]-Table13478[[#This Row],[Pagado por MVPX]]+Table13478[[#This Row],[Avance]]+P13 -> -2513.0475
B15: 44875 | F15: Artist; Dayan | G15: Payment made to the producers making Dayans new album | H15: 0 | I15: 0 | K15: =Table13478[[#This Row],[Valor de la Factura del Cliente]]*0.2 -> 0 | L15: =+Table13478[[#This Row],[Valor de la Factura del Cliente]]*0.05 -> 0 | M15: 0 | N15: 360.99 | O15: 0 | P15: =+Table13478[[#This Row],[Valor de la Factura del Cliente]]-Table13478[[#This Row],[Cargos Bancarios]]-Table13478[[#This Row],[20% Comisión]]-Table13478[[#This Row],[5% Legal]]-Table13478[[#This Row],[Retención de Impuestos]]-Table13478[[#This Row],[Pagado por MVPX]]+Table13478[[#This Row],[Avance]]+P14 -> -2874.0375
B16: 44890 | F16: Artist; Dayan | G16: Payment made to the producers making DAYAN`s new discography | H16: 0 | I16: 0 | K16: =Table13478[[#This Row],[Valor de la Factura del Cliente]]*0.2 -> 0 | L16: =+Table13478[[#This Row],[Valor de la Factura del Cliente]]*0.05 -> 0 | M16: 0 | N16: 460.99 | O16: 0 | P16: =+Table13478[[#This Row],[Valor de la Factura del Cliente]]-Table13478[[#This Row],[Cargos Bancarios]]-Table13478[[#This Row],[20% Comisión]]-Table13478[[#This Row],[5% Legal]]-Table13478[[#This Row],[Retención de Impuestos]]-Table13478[[#This Row],[Pagado por MVPX]]+Table13478[[#This Row],[Avance]]+P15 -> -3335.0275
B17: 44923 | F17: Artist; Dayan | G17: Payment made to the producers making DAYAN`s new discography | H17: 0 | I17: 0 | K17: =Table13478[[#This Row],[Valor de la Factura del Cliente]]*0.2 -> 0 | L17: =+Table13478[[#This Row],[Valor de la Factura del Cliente]]*0.05 -> 0 | M17: 0 | N17: 460.99 | O17: 0 | P17: =+Table13478[[#This Row],[Valor de la Factura del Cliente]]-Table13478[[#This Row],[Cargos Bancarios]]-Table13478[[#This Row],[20% Comisión]]-Table13478[[#This Row],[5% Legal]]-Table13478[[#This Row],[Retención de Impuestos]]-Table13478[[#This Row],[Pagado por MVPX]]+Table13478[[#This Row],[Avance]]+P16 -> -3796.0175
B18: 44966 | F18: Artist; Dayan | G18: Mastering WEEKENES | H18: 0 | I18: 0 | K18: =Table13478[[#This Row],[Valor de la Factura del Cliente]]*0.2 -> 0 | L18: =+Table13478[[#This Row],[Valor de la Factura del Cliente]]*0.05 -> 0 | M18: 0 | N18: 69.7 | O18: 0 | P18: =+Table13478[[#This Row],[Valor de la Factura del Cliente]]-Table13478[[#This Row],[Cargos Bancarios]]-Table13478[[#This Row],[20% Comisión]]-Table13478[[#This Row],[5% Legal]]-Table13478[[#This Row],[Retención de Impuestos]]-Table13478[[#This Row],[Pagado por MVPX]]+Table13478[[#This Row],[Avance]]+P17 -> -3865.7175
B19: 44966 | F19: Artist; Dayan | G19: Mastering Mar y Sol | H19: 0 | I19: 0 | K19: =Table13478[[#This Row],[Valor de la Factura del Cliente]]*0.2 -> 0 | L19: =+Table13478[[#This Row],[Valor de la Factura del Cliente]]*0.05 -> 0 | M19: 0 | N19: 69.7 | O19: 0 | P19: =+Table13478[[#This Row],[Valor de la Factura del Cliente]]-Table13478[[#This Row],[Cargos Bancarios]]-Table13478[[#This Row],[20% Comisión]]-Table13478[[#This Row],[5% Legal]]-Table13478[[#This Row],[Retención de Impuestos]]-Table13478[[#This Row],[Pagado por MVPX]]+Table13478[[#This Row],[Avance]]+P18 -> -3935.4175
B20: 44967 | F20: Artist; Dayan | G20: Mastering Bandida | H20: 0 | I20: 0 | K20: =Table13478[[#This Row],[Valor de la Factura del Cliente]]*0.2 -> 0 | L20: =+Table13478[[#This Row],[Valor de la Factura del Cliente]]*0.05 -> 0 | M20: 0 | N20: 62.49 | O20: 0 | P20: =+Table13478[[#This Row],[Valor de la Factura del Cliente]]-Table13478[[#This Row],[Cargos Bancarios]]-Table13478[[#This Row],[20% Comisión]]-Table13478[[#This Row],[5% Legal]]-Table13478[[#This Row],[Retención de Impuestos]]-Table13478[[#This Row],[Pagado por MVPX]]+Table13478[[#This Row],[Avance]]+P19 -> -3997.9075
B21: 44967 | F21: Artist; Dayan | G21: Mastering QHPCU | H21: 0 | I21: 0 | K21: =Table13478[[#This Row],[Valor de la Factura del Cliente]]*0.2 -> 0 | L21: =+Table13478[[#This Row],[Valor de la Factura del Cliente]]*0.05 -> 0 | M21: 0 | N21: 62.49 | O21: 0 | P21: =+Table13478[[#This Row],[Valor de la Factura del Cliente]]-Table13478[[#This Row],[Cargos Bancarios]]-Table13478[[#This Row],[20% Comisión]]-Table13478[[#This Row],[5% Legal]]-Table13478[[#This Row],[Retención de Impuestos]]-Table13478[[#This Row],[Pagado por MVPX]]+Table13478[[#This Row],[Avance]]+P20 -> -4060.3975
... B55: 45413 | F55: Artist; Dayan | G55: Producers Payment - Luar | H55: 0 | I55: 0 | K55: =Table13478[[#This Row],[Valor de la Factura del Cliente]]*0.2 -> 0 | L55: =+Table13478[[#This Row],[Valor de la Factura del Cliente]]*0.05 -> 0 | M55: 0 | N55: 804.99 | O55: 0 | P55: =+Table13478[[#This Row],[Valor de la Factura del Cliente]]-Table13478[[#This Row],[Cargos Bancarios]]-Table13478[[#This Row],[20% Comisión]]-Table13478[[#This Row],[5% Legal]]-Table13478[[#This Row],[Retención de Impuestos]]-Table13478[[#This Row],[Pagado por MVPX]]+Table13478[[#This Row],[Avance]]+P54 -> -26704.218
B56: 45428 | G56: Manuel Hernandez Toicen - Producer Payment | H56: 0 | I56: 0 | K56: =Table13478[[#This Row],[Valor de la Factura del Cliente]]*0.2 -> 0 | L56: =+Table13478[[#This Row],[Valor de la Factura del Cliente]]*0.05 -> 0 | M56: 0 | N56: 672 | O56: 0 | P56: =+Table13478[[#This Row],[Valor de la Factura del Cliente]]-Table13478[[#This Row],[Cargos Bancarios]]-Table13478[[#This Row],[20% Comisión]]-Table13478[[#This Row],[5% Legal]]-Table13478[[#This Row],[Retención de Impuestos]]-Table13478[[#This Row],[Pagado por MVPX]]+Table13478[[#This Row],[Avance]]+P55 -> -27376.218
B57: 45442 | F57: Taca Air | G57: Flight to Colombia | H57: 0 | I57: 0 | K57: =Table13478[[#This Row],[Valor de la Factura del Cliente]]*0.2 -> 0 | L57: =+Table13478[[#This Row],[Valor de la Factura del Cliente]]*0.05 -> 0 | M57: 0 | N57: 208.75 | O57: 0 | P57: =+Table13478[[#This Row],[Valor de la Factura del Cliente]]-Table13478[[#This Row],[Cargos Bancarios]]-Table13478[[#This Row],[20% Comisión]]-Table13478[[#This Row],[5% Legal]]-Table13478[[#This Row],[Retención de Impuestos]]-Table13478[[#This Row],[Pagado por MVPX]]+Table13478[[#This Row],[Avance]]+P56 -> -27584.968
B58: 45444 | F58: Taca Air | G58: Fliaght Colombia Quito | H58: 0 | I58: 0 | K58: =Table13478[[#This Row],[Valor de la Factura del Cliente]]*0.2 -> 0 | L58: =+Table13478[[#This Row],[Valor de la Factura del Cliente]]*0.05 -> 0 | M58: 0 | N58: 204.5 | O58: 0 | P58: =+Table13478[[#This Row],[Valor de la Factura del Cliente]]-Table13478[[#This Row],[Cargos Bancarios]]-Table13478[[#This Row],[20% Comisión]]-Table13478[[#This Row],[5% Legal]]-Table13478[[#This Row],[Retención de Impuestos]]-Table13478[[#This Row],[Pagado por MVPX]]+Table13478[[#This Row],[Avance]]+P57 -> -27789.468
B59: 45456 | F59: Mateo Damian | G59: Mateo Damian Sanchez Serrano Pago de Productor sencillo SOLA | H59: 0 | I59: 19.99 | K59: =Table13478[[#This Row],[Valor de la Factura del Cliente]]*0.2 -> 0 | L59: =+Table13478[[#This Row],[Valor de la Factura del Cliente]]*0.05 -> 0 | M59: 0 | N59: 2000 | O59: 0 | P59: =+Table13478[[#This Row],[Valor de la Factura del Cliente]]-Table13478[[#This Row],[Cargos Bancarios]]-Table13478[[#This Row],[20% Comisión]]-Table13478[[#This Row],[5% Legal]]-Table13478[[#This Row],[Retención de Impuestos]]-Table13478[[#This Row],[Pagado por MVPX]]+Table13478[[#This Row],[Avance]]+P58 -> -29809.458
B60: 45465 | F60: Dayan | G60: Saldo de Mateo Damian Sanchez Serrano y adelanto | H60: 0 | I60: 19.99 | K60: =Table13478[[#This Row],[Valor de la Factura del Cliente]]*0.2 -> 0 | L60: =+Table13478[[#This Row],[Valor de la Factura del Cliente]]*0.05 -> 0 | M60: 0 | N60: 2000 | O60: 0 | P60: =+Table13478[[#This Row],[Valor de la Factura del Cliente]]-Table13478[[#This Row],[Cargos Bancarios]]-Table13478[[#This Row],[20% Comisión]]-Table13478[[#This Row],[5% Legal]]-Table13478[[#This Row],[Retención de Impuestos]]-Table13478[[#This Row],[Pagado por MVPX]]+Table13478[[#This Row],[Avance]]+P59 -> -31829.448
B61: 45467 | F61: ECBY | G61: Adelanto Dayan | H61: 0 | I61: 0 | K61: =Table13478[[#This Row],[Valor de la Factura del Cliente]]*0.2 -> 0 | L61: =+Table13478[[#This Row],[Valor de la Factura del Cliente]]*0.05 -> 0 | M61: 0 | N61: 255.41 | O61: 0 | P61: =+Table13478[[#This Row],[Valor de la Factura del Cliente]]-Table13478[[#This Row],[Cargos Bancarios]]-Table13478[[#This Row],[20% Comisión]]-Table13478[[#This Row],[5% Legal]]-Table13478[[#This Row],[Retención de Impuestos]]-Table13478[[#This Row],[Pagado por MVPX]]+Table13478[[#This Row],[Avance]]+P60 -> -32084.858
B62: 45490 | F62: ECBY | G62: Adelanto Dayan | H62: 0 | I62: 0 | K62: =Table13478[[#This Row],[Valor de la Factura del Cliente]]*0.2 -> 0 | L62: =+Table13478[[#This Row],[Valor de la Factura del Cliente]]*0.05 -> 0 | M62: 0 | N62: 267.99 | O62: 0 | P62: =+Table13478[[#This Row],[Valor de la Factura del Cliente]]-Table13478[[#This Row],[Cargos Bancarios]]-Table13478[[#This Row],[20% Comisión]]-Table13478[[#This Row],[5% Legal]]-Table13478[[#This Row],[Retención de Impuestos]]-Table13478[[#This Row],[Pagado por MVPX]]+Table13478[[#This Row],[Avance]]+P61 -> -32352.848
B63: 45530 | F63: Diffusonix | G63: Pago de Mastering Sola | H63: 0 | I63: 0 | K63: =Table13478[[#This Row],[Valor de la Factura del Cliente]]*0.2 -> 0 | L63: =+Table13478[[#This Row],[Valor de la Factura del Cliente]]*0.05 -> 0 | M63: 0 | N63: 125 | O63: 0 | P63: =+Table13478[[#This Row],[Valor de la Factura del Cliente]]-Table13478[[#This Row],[Cargos Bancarios]]-Table13478[[#This Row],[20% Comisión]]-Table13478[[#This Row],[5% Legal]]-Table13478[[#This Row],[Retención de Impuestos]]-Table13478[[#This Row],[Pagado por MVPX]]+Table13478[[#This Row],[Avance]]+P62 -> -32477.848
B64: 45601 | F64: IRYO.EU | G64: Pago por subscribcion de creacion de contenido para dayan | H64: 0 | I64: 0 | K64: =Table13478[[#This Row],[Valor de la Factura del Cliente]]*0.2 -> 0 | L64: =+Table13478[[#This Row],[Valor de la Factura del Cliente]]*0.05 -> 0 | M64: 0 | N64: 20.74 | O64: 0 | P64: =+Table13478[[#This Row],[Valor de la Factura del Cliente]]-Table13478[[#This Row],[Cargos Bancarios]]-Table13478[[#This Row],[20% Comisión]]-Table13478[[#This Row],[5% Legal]]-Table13478[[#This Row],[Retención de Impuestos]]-Table13478[[#This Row],[Pagado por MVPX]]+Table13478[[#This Row],[Avance]]+P63 -> -32498.588
B65: 45839 | F65: Dayan | G65: Adelanto para gastos EP Ultimo Intento | H65: 0 | I65: 2.99 | K65: =Table13478[[#This Row],[Valor de la Factura del Cliente]]*0.2 -> 0 | L65: =+Table13478[[#This Row],[Valor de la Factura del Cliente]]*0.05 -> 0 | M65: 0 | N65: 125 | O65: 0 | P65: =+Table13478[[#This Row],[Valor de la Factura del Cliente]]-Table13478[[#This Row],[Cargos Bancarios]]-Table13478[[#This Row],[20% Comisión]]-Table13478[[#This Row],[5% Legal]]-Table13478[[#This Row],[Retención de Impuestos]]-Table13478[[#This Row],[Pagado por MVPX]]+Table13478[[#This Row],[Avance]]+P64 -> -32626.578
B66: 45841 | F66: Facebk | G66: Gastos de Marcketing | H66: 0 | I66: 0 | K66: =Table13478[[#This Row],[Valor de la Factura del Cliente]]*0.2 -> 0 | L66: =+Table13478[[#This Row],[Valor de la Factura del Cliente]]*0.05 -> 0 | M66: 0 | N66: 2 | O66: 0 | P66: =+Table13478[[#This Row],[Valor de la Factura del Cliente]]-Table13478[[#This Row],[Cargos Bancarios]]-Table13478[[#This Row],[20% Comisión]]-Table13478[[#This Row],[5% Legal]]-Table13478[[#This Row],[Retención de Impuestos]]-Table13478[[#This Row],[Pagado por MVPX]]+Table13478[[#This Row],[Avance]]+P65 -> -32628.578
B67: 45841 | F67: Facebk | G67: Gastos de Marcketing | H67: 0 | I67: 0 | K67: =Table13478[[#This Row],[Valor de la Factura del Cliente]]*0.2 -> 0 | L67: =+Table13478[[#This Row],[Valor de la Factura del Cliente]]*0.05 -> 0 | M67: 0 | N67: 3 | O67: 0 | P67: =+Table13478[[#This Row],[Valor de la Factura del Cliente]]-Table13478[[#This Row],[Cargos Bancarios]]-Table13478[[#This Row],[20% Comisión]]-Table13478[[#This Row],[5% Legal]]-Table13478[[#This Row],[Retención de Impuestos]]-Table13478[[#This Row],[Pagado por MVPX]]+Table13478[[#This Row],[Avance]]+P66 -> -32631.578
B68: 45842 | F68: Facebk | G68: Gastos de Marcketing | H68: 0 | I68: 0 | K68: =Table13478[[#This Row],[Valor de la Factura del Cliente]]*0.2 -> 0 | L68: =+Table13478[[#This Row],[Valor de la Factura del Cliente]]*0.05 -> 0 | M68: 0 | N68: 4 | O68: 0 | P68: =+Table13478[[#This Row],[Valor de la Factura del Cliente]]-Table13478[[#This Row],[Cargos Bancarios]]-Table13478[[#This Row],[20% Comisión]]-Table13478[[#This Row],[5% Legal]]-Table13478[[#This Row],[Retención de Impuestos]]-Table13478[[#This Row],[Pagado por MVPX]]+Table13478[[#This Row],[Avance]]+P67 -> -32635.578
... B80: 45887 | F80: Dayan | G80: Adelanto para gastos EP Ultimo Intento | H80: 0 | I80: 7.99 | K80: =Table13478[[#This Row],[Valor de la Factura del Cliente]]*0.2 -> 0 | L80: =+Table13478[[#This Row],[Valor de la Factura del Cliente]]*0.05 -> 0 | M80: 0 | N80: 700 | O80: 0 | P80: =+Table13478[[#This Row],[Valor de la Factura del Cliente]]-Table13478[[#This Row],[Cargos Bancarios]]-Table13478[[#This Row],[20% Comisión]]-Table13478[[#This Row],[5% Legal]]-Table13478[[#This Row],[Retención de Impuestos]]-Table13478[[#This Row],[Pagado por MVPX]]+Table13478[[#This Row],[Avance]]+P79 -> -34621.268
G81: TOTAL | H81: =SUBTOTAL(109,Table13478[Valor de la Factura del Cliente]) -> 269.23 | I81: =SUBTOTAL(109,Table13478[Cargos Bancarios]) -> 114.89 | K81: =SUBTOTAL(109,Table13478[20% Comisión]) -> 53.846 | L81: =SUBTOTAL(109,Table13478[5% Legal]) -> 13.4615 | M81: =SUBTOTAL(109,Table13478[Retención de Impuestos]) -> 0 | N81: =SUBTOTAL(109,Table13478[Pagado por MVPX]) -> 34708.3 | O81: =SUBTOTAL(109,Table13478[Avance]) -> 0 | P81: =P80 -> -34621.268

Sheet ErickAnt
B2: Artista: | E2: ErickAnt
B3: Nombre legal: | E3: Erick Andres Celis Marin
B4: Fecha de inicio: | E4: =MIN(Table13479[Fecha]) -> 45064
B5: Fecha fin: | E5: =MAX(Table13479[Fecha]) -> 45918
B7: ESTADO DE CUENTA
B8: Fecha | C8: Número | D8: Tipo | E8: Método de pago | F8: Nombre | G8: Concepto | H8: Valor de la Factura del Cliente | I8: Cargos Bancarios | J8: 50% Fee | K8: 20% Comisión | L8: 5% Legal | M8: Retención de Impuestos | N8: Pagado por MVPX | O8: Avance | P8: Balance
F9: Ingreso de Regalías Mecanicas | G9: Ingreso de Regalías Mecanicas | H9: 7744.94 | I9: 0 | K9: =Table13479[[#This Row],[Valor de la Factura del Cliente]]*0.2 -> 1548.988 | L9: =Table13479[[#This Row],[Valor de la Factura del Cliente]]*0.05 -> 387.247 | M9: 0 | N9: 0 | O9: 0 | P9: =+Table13479[[#This Row],[Valor de la Factura del Cliente]]-SUM(Table13479[[#This Row],[Cargos Bancarios]:[Avance]]) -> 5808.705
F10: Ingreso de Regalías Por Ejecución | G10: Ingreso de Regalías Por Ejecución | H10: 90.54 | I10: 0 | K10: =Table13479[[#This Row],[Valor de la Factura del Cliente]]*0.2 -> 18.108 | L10: =Table13479[[#This Row],[Valor de la Factura del Cliente]]*0.05 -> 4.527 | M10: 0 | N10: 0 | O10: 0 | P10: =+Table13479[[#This Row],[Valor de la Factura del Cliente]]-SUM(Table13479[[#This Row],[Cargos Bancarios]:[Avance]])+P9 -> 5876.61
B11: 45064 | F11: Erick Andres Celis Marin | G11: Avance Solicitado | H11: 0 | I11: 0 | K11: =Table13479[[#This Row],[Valor de la Factura del Cliente]]*0.2 -> 0 | L11: =Table13479[[#This Row],[Valor de la Factura del Cliente]]*0.05 -> 0 | M11: 0 | N11: 0 | O11: 1006.99 | P11: =+Table13479[[#This Row],[Valor de la Factura del Cliente]]-SUM(Table13479[[#This Row],[Cargos Bancarios]:[Avance]])+P10 -> 4869.62
B12: 45287 | F12: Erick Andres Celis Marin | G12: Avance Solicitado | H12: 0 | I12: 0 | K12: =Table13479[[#This Row],[Valor de la Factura del Cliente]]*0.2 -> 0 | L12: =Table13479[[#This Row],[Valor de la Factura del Cliente]]*0.05 -> 0 | M12: 0 | N12: 0 | O12: 501.99 | P12: =+Table13479[[#This Row],[Valor de la Factura del Cliente]]-SUM(Table13479[[#This Row],[Cargos Bancarios]:[Avance]])+P11 -> 4367.63
B13: 45296 | F13: Erick Andres Celis Marin | G13: Avance Solicitado | H13: 0 | I13: 0 | K13: =Table13479[[#This Row],[Valor de la Factura del Cliente]]*0.2 -> 0 | L13: =Table13479[[#This Row],[Valor de la Factura del Cliente]]*0.05 -> 0 | M13: 0 | N13: 0 | O13: 1501.99 | P13: =+Table13479[[#This Row],[Valor de la Factura del Cliente]]-SUM(Table13479[[#This Row],[Cargos Bancarios]:[Avance]])+P12 -> 2865.64
B14: 45297 | F14: Erick Andres Celis Marin | G14: Avance Solicitado | H14: 0 | I14: 0 | K14: =Table13479[[#This Row],[Valor de la Factura del Cliente]]*0.2 -> 0 | L14: =Table13479[[#This Row],[Valor de la Factura del Cliente]]*0.05 -> 0 | M14: 0 | N14: 0 | O14: 501.99 | P14: =+Table13479[[#This Row],[Valor de la Factura del Cliente]]-SUM(Table13479[[#This Row],[Cargos Bancarios]:[Avance]])+P13 -> 2363.65
B15: 45354 | F15: Erick Andres Celis Marin | G15: Avance Solicitado | H15: 0 | I15: 0 | K15: =Table13479[[#This Row],[Valor de la Factura del Cliente]]*0.2 -> 0 | L15: =Table13479[[#This Row],[Valor de la Factura del Cliente]]*0.05 -> 0 | M15: 0 | N15: 0 | O15: 1501.99 | P15: =+Table13479[[#This Row],[Valor de la Factura del Cliente]]-SUM(Table13479[[#This Row],[Cargos Bancarios]:[Avance]])+P14 -> 861.66
B16: 45387 | F16: Erick Andres Celis Marin | G16: Pago Otro Round Myke Towers | H16: 20000 | I16: 0 | K16: =Table13479[[#This Row],[Valor de la Factura del Cliente]]*0.2 -> 4000 | L16: =Table13479[[#This Row],[Valor de la Factura del Cliente]]*0.05 -> 1000 | M16: 0 | N16: 0 | O16: 0 | P16: =+Table13479[[#This Row],[Valor de la Factura del Cliente]]-SUM(Table13479[[#This Row],[Cargos Bancarios]:[Avance]])+P15 -> 15861.66
B17: 45388 | F17: EQ | G17: Pago a productor por Servicios en Otro Round | H17: 0 | I17: 0 | K17: =Table13479[[#This Row],[Valor de la Factura del Cliente]]*0.2 -> 0 | L17: =Table13479[[#This Row],[Valor de la Factura del Cliente]]*0.05 -> 0 | M17: 0 | N17: 0 | O17: 3000 | P17: =+Table13479[[#This Row],[Valor de la Factura del Cliente]]-SUM(Table13479[[#This Row],[Cargos Bancarios]:[Avance]])+P16 -> 12861.66
B18: 45388 | F18: Rogelio | G18: Pago a productor por Servicios en Otro Round | I18: 0 | K18: =Table13479[[#This Row],[Valor de la Factura del Cliente]]*0.2 -> 0 | L18: =Table13479[[#This Row],[Valor de la Factura del Cliente]]*0.05 -> 0 | M18: 0 | N18: 0 | O18: 6000 | P18: =+Table13479[[#This Row],[Valor de la Factura del Cliente]]-SUM(Table13479[[#This Row],[Cargos Bancarios]:[Avance]])+P17 -> 6861.66
B19: 45388 | G19: Mike Towers Messiah | H19: 4000 | I19: 0 | K19: =Table13479[[#This Row],[Valor de la Factura del Cliente]]*0.2 -> 800 | L19: =Table13479[[#This Row],[Valor de la Factura del Cliente]]*0.05 -> 200 | M19: 0 | N19: 0 | O19: 0 | P19: =+Table13479[[#This Row],[Valor de la Factura del Cliente]]-SUM(Table13479[[#This Row],[Cargos Bancarios]:[Avance]])+P18 -> 9861.66
B20: 45388 | F20: Rogelio | G20: Pago a productor por Servicios en Messiah | H20: 0 | I20: 0 | K20: =Table13479[[#This Row],[Valor de la Factura del Cliente]]*0.2 -> 0 | L20: =Table13479[[#This Row],[Valor de la Factura del Cliente]]*0.05 -> 0 | M20: 0 | N20: 0 | O20: 1100 | P20: =+Table13479[[#This Row],[Valor de la Factura del Cliente]]-SUM(Table13479[[#This Row],[Cargos Bancarios]:[Avance]])+P19 -> 8761.66
B21: 45388 | F21: Cromo | G21: Pago a productor por Servicios en Messiah | H21: 0 | I21: 0 | K21: =Table13479[[#This Row],[Valor de la Factura del Cliente]]*0.2 -> 0 | L21: =Table13479[[#This Row],[Valor de la Factura del Cliente]]*0.05 -> 0 | M21: 0 | N21: 0 | O21: 800 | P21: =+Table13479[[#This Row],[Valor de la Factura del Cliente]]-SUM(Table13479[[#This Row],[Cargos Bancarios]:[Avance]])+P20 -> 7961.66
B22: 45407 | F22: ErickAnt | G22: Adelanto Vía Remitly | H22: 0 | I22: 0 | K22: =Table13479[[#This Row],[Valor de la Factura del Cliente]]*0.2 -> 0 | L22: =Table13479[[#This Row],[Valor de la Factura del Cliente]]*0.05 -> 0 | M22: 0 | N22: 0 | O22: 1501.99 | P22: =+Table13479[[#This Row],[Valor de la Factura del Cliente]]-SUM(Table13479[[#This Row],[Cargos Bancarios]:[Avance]])+P21 -> 6459.67
B23: 45408 | F23: ErickAnt | G23: Avance Solicitado | H23: 0 | I23: 0 | K23: =Table13479[[#This Row],[Valor de la Factura del Cliente]]*0.2 -> 0 | L23: =Table13479[[#This Row],[Valor de la Factura del Cliente]]*0.05 -> 0 | M23: 0 | N23: 0 | O23: 2167.15 | P23: =+Table13479[[#This Row],[Valor de la Factura del Cliente]]-SUM(Table13479[[#This Row],[Cargos Bancarios]:[Avance]])+P22 -> 4292.52
B24: 45589 | F24: ErickAnt | G24: Avance Solicitado | H24: 0 | I24: 0 | K24: =Table13479[[#This Row],[Valor de la Factura del Cliente]]*0.2 -> 0 | L24: =Table13479[[#This Row],[Valor de la Factura del Cliente]]*0.05 -> 0 | M24: 0 | N24: 0 | O24: 602.11 | P24: =+Table13479[[#This Row],[Valor de la Factura del Cliente]]-SUM(Table13479[[#This Row],[Cargos Bancarios]:[Avance]])+P23 -> 3690.41
B25: 45669 | F25: ErickAnt | G25: Avance Solicitado | H25: 0 | I25: 0 | K25: =Table13479[[#This Row],[Valor de la Factura del Cliente]]*0.2 -> 0 | L25: =Table13479[[#This Row],[Valor de la Factura del Cliente]]*0.05 -> 0 | M25: 0 | N25: 0 | O25: 501.99 | P25: =+Table13479[[#This Row],[Valor de la Factura del Cliente]]-SUM(Table13479[[#This Row],[Cargos Bancarios]:[Avance]])+P24 -> 3188.42
B26: 45741 | F26: ErickAnt | G26: Avance Solicitado | H26: 0 | I26: 0 | K26: =Table13479[[#This Row],[Valor de la Factura del Cliente]]*0.2 -> 0 | L26: =Table13479[[#This Row],[Valor de la Factura del Cliente]]*0.05 -> 0 | M26: 0 | N26: 0 | O26: 876.61 | P26: =+Table13479[[#This Row],[Valor de la Factura del Cliente]]-SUM(Table13479[[#This Row],[Cargos Bancarios]:[Avance]])+P25 -> 2311.81
B27: 45834 | F27: ErickAnt | G27: Avance Solicitado | H27: 0 | I27: 0 | K27: =Table13479[[#This Row],[Valor de la Factura del Cliente]]*0.2 -> 0 | L27: =Table13479[[#This Row],[Valor de la Factura del Cliente]]*0.05 -> 0 | M27: 0 | N27: 0 | O27: 508.75 | P27: =+Table13479[[#This Row],[Valor de la Factura del Cliente]]-SUM(Table13479[[#This Row],[Cargos Bancarios]:[Avance]])+P26 -> 1803.06
B28: 45918 | F28: ErickAnt | G28: Avance Solicitado 1803.06 + 3.99 fee | H28: 0 | I28: 0 | K28: =Table13479[[#This Row],[Valor de la Factura del Cliente]]*0.2 -> 0 | L28: =Table13479[[#This Row],[Valor de la Factura del Cliente]]*0.05 -> 0 | M28: 0 | N28: 0 | O28: 1807 | P28: =+Table13479[[#This Row],[Valor de la Factura del Cliente]]-SUM(Table13479[[#This Row],[Cargos Bancarios]:[Avance]])+P27 -> -3.94
G29: TOTAL | H29: =SUBTOTAL(109,Table13479[Valor de la Factura del Cliente]) -> 31835.48 | I29: =SUBTOTAL(109,Table13479[Cargos Bancarios]) -> 0 | K29: =SUBTOTAL(109,Table13479[20% Comisión]) -> 6367.096 | L29: =SUBTOTAL(109,Table13479[5% Legal]) -> 1591.774 | M29: =SUBTOTAL(109,Table13479[Retención de Impuestos]) -> 0 | N29: =SUBTOTAL(109,Table13479[Pagado por MVPX]) -> 0 | O29: =SUBTOTAL(109,Table13479[Avance]) -> 23880.55 | P29: =+P28 -> -3.94

Sheet V1FRO
B2: Artista: | E2: V1FRO
B3: Nombre legal: | E3: Aroldo Contreras
B4: Fecha de inicio: | E4: =MIN(Table134711[Fecha]) -> 43944
B5: Fecha fin: | E5: =MAX(Table134711[Fecha]) -> 45184
B7: ESTADO DE CUENTA
B8: Fecha | C8: Número | D8: Tipo | E8: Método de pago | F8: Nombre | G8: Concepto | H8: Valor de la Factura del Cliente | I8: Cargos Bancarios | J8: 50% Fee | K8: 20% Comisión | L8: 5% Legal | M8: Retención de Impuestos | N8: Pagado por MVPX | O8: Avance | P8: Balance
B9: 43944 | D9: Bill | G9: To register portion of Dielo's contract atributable to Vfro's work | N9: 7500 | P9: =+Table134711[[#This Row],[Pagado por MVPX]]+Table134711[[#This Row],[Avance]] -> 7500
B10: 43965 | C10: 1 | D10: Invoice | F10: Warner Music Mexico | G10: Production services- Nib, Justin Quilters, Danny Ocean, Feid - Cuando Amanezca | H10: 5000 | I10: -15 | K10: =Table134711[[#This Row],[Valor de la Factura del Cliente]]*-0.2 -> -1000 | L10: =+Table134711[[#This Row],[Valor de la Factura del Cliente]]*-0.05 -> -250 | N10: 3735 | P10: =+Table134711[[#This Row],[Pagado por MVPX]]+Table134711[[#This Row],[Avance]]+P9 -> 11235
B11: 44038 | D11: CR Jul 2020 (2) | G11: Paid by Luar Collective Inc in favor of debt to Vfro for Warner Music (payable to Luar) | O11: -200 | P11: =+Table134711[[#This Row],[Pagado por MVPX]]+Table134711[[#This Row],[Avance]]+P10 -> 11035
B12: 44029 | D12: CR Jul 2020 | G12: Paid by Luar Collective Inc in favor of debt to Vfro for Warner Music (payable to Luar) | O12: -500 | P12: =+Table134711[[#This Row],[Pagado por MVPX]]+Table134711[[#This Row],[Avance]]+P11 -> 10535
B13: 44053 | E13: PAYPAL | G13: For services to Warner Music Mexico | O13: -1500 | P13: =+Table134711[[#This Row],[Pagado por MVPX]]+Table134711[[#This Row],[Avance]]+P12 -> 9035
B14: 44029 | E14: Zelle | F14: Aroldo Contreras / Vfro | G14: Transfer Conf # e9abc98e9. Contreras, Aroldo Vfro. | O14: -100 | P14: =+Table134711[[#This Row],[Pagado por MVPX]]+Table134711[[#This Row],[Avance]]+P13 -> 8935
B15: 44102 | E15: PAYPAL | F15: Aroldo Contreras / Vfro | G15: Eventhough it was an advance, we owed vfro for Warner's invoice | O15: -250 | P15: =+Table134711[[#This Row],[Pagado por MVPX]]+Table134711[[#This Row],[Avance]]+P14 -> 8685
B16: 44048 | D16: CR Aug 2020 (2) | F16: Aroldo Contreras / Vfro | G16: Travel expense for Dielo's video (Jet Blue paid by Owner). Will reduce debt to Vfro for Warner Music | O16: -193.15 | P16: =+Table134711[[#This Row],[Pagado por MVPX]]+Table134711[[#This Row],[Avance]]+P15 -> 8491.85
B17: 44050 | D17: CR Aug 2020 | F17: Aroldo Contreras / Vfro | G17: Payment made by owner to pay part of bill due to Vfro (was send by ATH Movil to Dielo) | O17: -200 | P17: =+Table134711[[#This Row],[Pagado por MVPX]]+Table134711[[#This Row],[Avance]]+P16 -> 8291.85
B18: 44062 | D18: CR Aug 2020 (3) | F18: Aroldo Contreras / Vfro | G18: Travel expense for Dielo's video (Jet Blue paid by Owner). Will reduce debt to Vfro for Warner Music | O18: -223.12 | P18: =+Table134711[[#This Row],[Pagado por MVPX]]+Table134711[[#This Row],[Avance]]+P17 -> 8068.73
B19: 44082 | D19: CR Sep 2020 | F19: Aroldo Contreras / Vfro | G19: Speakers bought thorugh Luar Collective Inc for Vfro as an Advance | O19: -249 | P19: =+Table134711[[#This Row],[Pagado por MVPX]]+Table134711[[#This Row],[Avance]]+P18 -> 7819.73
B20: 44102 | E20: PAYPAL | F20: Aroldo Contreras / Vfro | G20: Dielo's interscope deal agreement (Payment) | O20: -400 | P20: =+Table134711[[#This Row],[Pagado por MVPX]]+Table134711[[#This Row],[Avance]]+P19 -> 7419.73
B21: 44126 | E21: PAYPAL | F21: Aroldo Contreras / Vfro | G21: Advance for Dielo's contract with interscope | O21: -1000 | P21: =+Table134711[[#This Row],[Pagado por MVPX]]+Table134711[[#This Row],[Avance]]+P20 -> 6419.73
B22: 44166 | E22: PAYPAL | F22: Aroldo Contreras / Vfro | G22: Advance made of 25% due to us (Bellella's services) applied to invoice due ($250) | O22: -985 | P22: =+Table134711[[#This Row],[Pagado por MVPX]]+Table134711[[#This Row],[Avance]]+P21 -> 5434.73
B23: 44166 | E23: PAYPAL | G23: Eventhough there were payments made as an advance, it was applied to other bills due | O23: -2500 | P23: =+Table134711[[#This Row],[Pagado por MVPX]]+Table134711[[#This Row],[Avance]]+P22 -> 2934.73
B24: 44135 | C24: 13 | D24: Invoice | F24: Bellella Records LLC | G24: Per Diem charges related to artist "Danny Ocean" | H24: 1000 | I24: -15 | K24: =Table134711[[#This Row],[Valor de la Factura del Cliente]]*-0.2 -> -200 | L24: =+Table134711[[#This Row],[Valor de la Factura del Cliente]]*-0.05 -> -50 | N24: 735 | P24: =+Table134711[[#This Row],[Pagado por MVPX]]+Table134711[[#This Row],[Avance]]+P23 -> 3669.73
B25: 44144 | C25: 14 | D25: Invoice | F25: Bellella Records LLC | G25: Per Diem charge related to artist "Danny Ocean" | H25: 1500 | I25: -15 | K25: =Table134711[[#This Row],[Valor de la Factura del Cliente]]*-0.2 -> -300 | L25: =+Table134711[[#This Row],[Valor de la Factura del Cliente]]*-0.05 -> -75 | N25: 1110 | P25: =+Table134711[[#This Row],[Pagado por MVPX]]+Table134711[[#This Row],[Avance]]+P24 -> 4779.73
B26: 44186 | C26: 17 | D26: Invoice | F26: Bellella Records LLC | G26: Production services for artist "Danny Ocean" | H26: 1000 | I26: -15 | K26: =Table134711[[#This Row],[Valor de la Factura del Cliente]]*-0.2 -> -200 | L26: =+Table134711[[#This Row],[Valor de la Factura del Cliente]]*-0.05 -> -50 | N26: 735 | P26: =+Table134711[[#This Row],[Pagado por MVPX]]+Table134711[[#This Row],[Avance]]+P25 -> 5514.73
B27: 44219 | D27: Bill | G27: Mixing fee " Sin Prisa" | N27: 500 | P27: =+Table134711[[#This Row],[Pagado por MVPX]]+Table134711[[#This Row],[Avance]]+P26 -> 6014.73
B28: 44219 | D28: Bill | G28: Mixing fee" El General" | N28: 500 | P28: =+Table134711[[#This Row],[Pagado por MVPX]]+Table134711[[#This Row],[Avance]]+P27 -> 6514.73
B29: 44219 | D29: Bill | G29: Mixing fee " Mucha Weed" | N29: 500 | P29: =+Table134711[[#This Row],[Pagado por MVPX]]+Table134711[[#This Row],[Avance]]+P28 -> 7014.73
B30: 44237 | C30: 23 | D30: Invoice | F30: Remezcla LLC 2656 | G30: Licensing use: "Canito Flex" for project: Jack Daniels (Job# 2561) | H30: 200 | K30: =Table134711[[#This Row],[Valor de la Factura del Cliente]]*-0.2 -> -40 | L30: =+Table134711[[#This Row],[Valor de la Factura del Cliente]]*-0.05 -> -10 | N30: 150 | P30: =+Table134711[[#This Row],[Pagado por MVPX]]+Table134711[[#This Row],[Avance]]+P29 -> 7164.73
B31: 44237 | C31: 24 | D31: Invoice | F31: Remezcla LLC | G31: Licensing use: "Vomba y Andie (Dielo)" for project: Toyota Sienna (Job# 2557) | H31: 300 | K31: =Table134711[[#This Row],[Valor de la Factura del Cliente]]*-0.2 -> -60 | L31: =+Table134711[[#This Row],[Valor de la Factura del Cliente]]*-0.05 -> -15 | N31: 225 | P31: =+Table134711[[#This Row],[Pagado por MVPX]]+Table134711[[#This Row],[Avance]]+P30 -> 7389.73
B32: 44244 | C32: 19 | D32: Invoice | F32: Bellella Records LLC | G32: Production services for Danny Ocean single "Doritos y Pepsicola" | H32: 2500 | I32: -15 | K32: =Table134711[[#This Row],[Valor de la Factura del Cliente]]*-0.2 -> -500 | L32: =+Table134711[[#This Row],[Valor de la Factura del Cliente]]*-0.05 -> -125 | N32: 1860 | P32: =+Table134711[[#This Row],[Pagado por MVPX]]+Table134711[[#This Row],[Avance]]+P31 -> 9249.73
B33: 44201 | E33: PAYPAL | G33: Paid $250 as an advance used for other liabilities due. Had to only pay $735 and instead paid $985. | K33: =Table134711[[#This Row],[Valor de la Factura del Cliente]]*-0.2 -> 0 | L33: =+Table134711[[#This Row],[Valor de la Factura del Cliente]]*-0.05 -> 0 | O33: -985 | P33: =+Table134711[[#This Row],[Pagado por MVPX]]+Table134711[[#This Row],[Avance]]+P32 -> 8264.73
B34: 44291 | E34: PAYPAL | G34: dvance paid over what was due for Remezcla's LLC service ($125 advance applied to any other invoice) | K34: =Table134711[[#This Row],[Valor de la Factura del Cliente]]*-0.2 -> 0 | L34: =+Table134711[[#This Row],[Valor de la Factura del Cliente]]*-0.05 -> 0 | O34: -125 | P34: =+Table134711[[#This Row],[Pagado por MVPX]]+Table134711[[#This Row],[Avance]]+P33 -> 8139.73
B35: 44291 | E35: PAYPAL | K35: =Table134711[[#This Row],[Valor de la Factura del Cliente]]*-0.2 -> 0 | L35: =+Table134711[[#This Row],[Valor de la Factura del Cliente]]*-0.05 -> 0 | O35: -375 | P35: =+Table134711[[#This Row],[Pagado por MVPX]]+Table134711[[#This Row],[Avance]]+P34 -> 7764.73
B36: 44305 | E36: PAYPAL | K36: =Table134711[[#This Row],[Valor de la Factura del Cliente]]*-0.2 -> 0 | L36: =+Table134711[[#This Row],[Valor de la Factura del Cliente]]*-0.05 -> 0 | O36: -500 | P36: =+Table134711[[#This Row],[Pagado por MVPX]]+Table134711[[#This Row],[Avance]]+P35 -> 7264.73
B37: 44375 | K37: =Table134711[[#This Row],[Valor de la Factura del Cliente]]*-0.2 -> 0 | L37: =+Table134711[[#This Row],[Valor de la Factura del Cliente]]*-0.05 -> 0 | O37: -500 | P37: =+Table134711[[#This Row],[Pagado por MVPX]]+Table134711[[#This Row],[Avance]]+P36 -> 6764.73
B38: 44529 | D38: Bill | G38: Production fee for Dielo's "Sierva Ponte Seria" | K38: =Table134711[[#This Row],[Valor de la Factura del Cliente]]*-0.2 -> 0 | L38: =+Table134711[[#This Row],[Valor de la Factura del Cliente]]*-0.05 -> 0 | N38: 800 | P38: =+Table134711[[#This Row],[Pagado por MVPX]]+Table134711[[#This Row],[Avance]]+P37 -> 7564.73
B39: 44529 | D39: Bill | G39: Producer Fe Van 4 Faltan 20 | K39: =Table134711[[#This Row],[Valor de la Factura del Cliente]]*-0.2 -> 0 | L39: =+Table134711[[#This Row],[Valor de la Factura del Cliente]]*-0.05 -> 0 | N39: 700 | P39: =+Table134711[[#This Row],[Pagado por MVPX]]+Table134711[[#This Row],[Avance]]+P38 -> 8264.73
B40: 44529 | D40: Bill | G40: Producer fee for MIXTURES | K40: =Table134711[[#This Row],[Valor de la Factura del Cliente]]*-0.2 -> 0 | L40: =+Table134711[[#This Row],[Valor de la Factura del Cliente]]*-0.05 -> 0 | N40: 3250 | P40: =+Table134711[[#This Row],[Pagado por MVPX]]+Table134711[[#This Row],[Avance]]+P39 -> 11514.73
B41: 44529 | D41: Bill | G41: Production fee "Madrugada" | K41: =Table134711[[#This Row],[Valor de la Factura del Cliente]]*-0.2 -> 0 | L41: =+Table134711[[#This Row],[Valor de la Factura del Cliente]]*-0.05 -> 0 | N41: 375 | P41: =+Table134711[[#This Row],[Pagado por MVPX]]+Table134711[[#This Row],[Avance]]+P40 -> 11889.73
B42: 44529 | D42: Bill | G42: Production fee for Dielo's "Gatita" | K42: =Table134711[[#This Row],[Valor de la Factura del Cliente]]*-0.2 -> 0 | L42: =+Table134711[[#This Row],[Valor de la Factura del Cliente]]*-0.05 -> 0 | N42: 750 | P42: =+Table134711[[#This Row],[Pagado por MVPX]]+Table134711[[#This Row],[Avance]]+P41 -> 12639.73
B43: 44529 | D43: Bill | G43: Production fee for Dielo's "No te me Canses" | K43: =Table134711[[#This Row],[Valor de la Factura del Cliente]]*-0.2 -> 0 | L43: =+Table134711[[#This Row],[Valor de la Factura del Cliente]]*-0.05 -> 0 | N43: 750 | P43: =+Table134711[[#This Row],[Pagado por MVPX]]+Table134711[[#This Row],[Avance]]+P42 -> 13389.73
B44: 44620 | D44: Bill | G44: Video edition color and directio creative | K44: =Table134711[[#This Row],[Valor de la Factura del Cliente]]*-0.2 -> 0 | L44: =+Table134711[[#This Row],[Valor de la Factura del Cliente]]*-0.05 -> 0 | N44: 1000 | P44: =+Table134711[[#This Row],[Pagado por MVPX]]+Table134711[[#This Row],[Avance]]+P43 -> 14389.73
B45: 44642 | C45: 55 | D45: Invoice | F45: WARNER MUSIC SPAIN SL | G45: Produccion Musical Paula Candejas, Danny Ocean "Cosquillas Diferentes". | H45: 3227.17 | K45: =Table134711[[#This Row],[Valor de la Factura del Cliente]]*-0.2 -> -645.434 | L45: =+Table134711[[#This Row],[Valor de la Factura del Cliente]]*-0.05 -> -161.3585 | N45: 2400.12 | P45: =+Table134711[[#This Row],[Pagado por MVPX]]+Table134711[[#This Row],[Avance]]+P44 -> 16789.85
B46: 44583 | C46: 28 | D46: Invoice | F46: Bellella Records LLC | G46: Production services for Danny Ocean | H46: 19500 | K46: =Table134711[[#This Row],[Valor de la Factura del Cliente]]*-0.2 -> -3900 | L46: =+Table134711[[#This Row],[Valor de la Factura del Cliente]]*-0.05 -> -975 | N46: 14625 | P46: =+Table134711[[#This Row],[Pagado por MVPX]]+Table134711[[#This Row],[Avance]]+P45 -> 31414.85
B47: 44837 | C47: 59 | D47: Invoice | F47: Remezcla LLC | G47: Collaboration the Vitamin Project # 2656 | H47: 2500 | K47: =Table134711[[#This Row],[Valor de la Factura del Cliente]]*-0.2 -> -500 | L47: =+Table134711[[#This Row],[Valor de la Factura del Cliente]]*-0.05 -> -125 | N47: 1875 | P47: =+Table134711[[#This Row],[Pagado por MVPX]]+Table134711[[#This Row],[Avance]]+P46 -> 33289.85
B48: 44340 | E48: PAYPAL | G48: Used to pay two invoices of Danny Ocean that are still due and whta's left is used to pay Dielo's debt (1,905) | K48: =Table134711[[#This Row],[Valor de la Factura del Cliente]]*-0.2 -> 0 | L48: =+Table134711[[#This Row],[Valor de la Factura del Cliente]]*-0.05 -> 0 | O48: -6000 | P48: =+Table134711[[#This Row],[Pagado por MVPX]]+Table134711[[#This Row],[Avance]]+P47 -> 27289.85
B49: 44503 | E49: PAYPAL | G49: Avance de pago de Warner u otro proyecto | K49: =Table134711[[#This Row],[Valor de la Factura del Cliente]]*-0.2 -> 0 | L49: =+Table134711[[#This Row],[Valor de la Factura del Cliente]]*-0.05 -> 0 | O49: -1500 | P49: =+Table134711[[#This Row],[Pagado por MVPX]]+Table134711[[#This Row],[Avance]]+P48 -> 25789.85
E50: PAYPAL | K50: =Table134711[[#This Row],[Valor de la Factura del Cliente]]*-0.2 -> 0 | L50: =+Table134711[[#This Row],[Valor de la Factura del Cliente]]*-0.05 -> 0 | O50: -8125 | P50: =+Table134711[[#This Row],[Pagado por MVPX]]+Table134711[[#This Row],[Avance]]+P49 -> 17664.85
B51: 44631 | E51: PAYPAL | G51: Video edition color and directio creative | K51: =Table134711[[#This Row],[Valor de la Factura del Cliente]]*-0.2 -> 0 | L51: =+Table134711[[#This Row],[Valor de la Factura del Cliente]]*-0.05 -> 0 | O51: -1000 | P51: =+Table134711[[#This Row],[Pagado por MVPX]]+Table134711[[#This Row],[Avance]]+P50 -> 16664.85
B52: 44690 | E52: PAYPAL | G52: Advance Invoice Danny Ocean | K52: =Table134711[[#This Row],[Valor de la Factura del Cliente]]*-0.2 -> 0 | L52: =+Table134711[[#This Row],[Valor de la Factura del Cliente]]*-0.05 -> 0 | O52: -3500 | P52: =+Table134711[[#This Row],[Pagado por MVPX]]+Table134711[[#This Row],[Avance]]+P51 -> 13164.85
B53: 44802 | E53: PAYPAL | G53: To record the progress to deduct with future invoice | K53: =Table134711[[#This Row],[Valor de la Factura del Cliente]]*-0.2 -> 0 | L53: =+Table134711[[#This Row],[Valor de la Factura del Cliente]]*-0.05 -> 0 | O53: -2000 | P53: =+Table134711[[#This Row],[Pagado por MVPX]]+Table134711[[#This Row],[Avance]]+P52 -> 11164.85
B54: 44813 | E54: PAYPAL | G54: To record the progress to deduct with future invoice | K54: =Table134711[[#This Row],[Valor de la Factura del Cliente]]*-0.2 -> 0 | L54: =+Table134711[[#This Row],[Valor de la Factura del Cliente]]*-0.05 -> 0 | O54: -500 | P54: =+Table134711[[#This Row],[Pagado por MVPX]]+Table134711[[#This Row],[Avance]]+P53 -> 10664.85
B55: 44837 | E55: PAYPAL | G55: Advance vfro | K55: =Table134711[[#This Row],[Valor de la Factura del Cliente]]*-0.2 -> 0 | L55: =+Table134711[[#This Row],[Valor de la Factura del Cliente]]*-0.05 -> 0 | O55: -2000 | P55: =+Table134711[[#This Row],[Pagado por MVPX]]+Table134711[[#This Row],[Avance]]+P54 -> 8664.85
B56: 44869 | E56: PAYPAL | G56: Advance for payment of Visa Aroldo Contrera | K56: =Table134711[[#This Row],[Valor de la Factura del Cliente]]*-0.2 -> 0 | L56: =+Table134711[[#This Row],[Valor de la Factura del Cliente]]*-0.05 -> 0 | O56: -5000 | P56: =+Table134711[[#This Row],[Pagado por MVPX]]+Table134711[[#This Row],[Avance]]+P55 -> 3664.85
B57: 44871 | E57: PAYPAL | G57: Advance for payment of Visa Aroldo Contrera | K57: =Table134711[[#This Row],[Valor de la Factura del Cliente]]*-0.2 -> 0 | L57: =+Table134711[[#This Row],[Valor de la Factura del Cliente]]*-0.05 -> 0 | O57: -2525 | P57: =+Table134711[[#This Row],[Pagado por MVPX]]+Table134711[[#This Row],[Avance]]+P56 -> 1139.85
B58: 44897 | E58: PAYPAL | G58: Advance for payment of Visa Aroldo Contrera | K58: =Table134711[[#This Row],[Valor de la Factura del Cliente]]*-0.2 -> 0 | L58: =+Table134711[[#This Row],[Valor de la Factura del Cliente]]*-0.05 -> 0 | O58: -3000 | P58: =+Table134711[[#This Row],[Pagado por MVPX]]+Table134711[[#This Row],[Avance]]+P57 -> -1860.15
B59: 44931 | E59: PAYPAL | G59: Advance for payment of Visa Aroldo Contrera | K59: =Table134711[[#This Row],[Valor de la Factura del Cliente]]*-0.2 -> 0 | L59: =+Table134711[[#This Row],[Valor de la Factura del Cliente]]*-0.05 -> 0 | O59: -2500 | P59: =+Table134711[[#This Row],[Pagado por MVPX]]+Table134711[[#This Row],[Avance]]+P58 -> -4360.15
B60: 44964 | E60: PAYPAL | G60: Pago Por los Servicios de RCA | K60: =Table134711[[#This Row],[Valor de la Factura del Cliente]]*-0.2 -> 0 | L60: =+Table134711[[#This Row],[Valor de la Factura del Cliente]]*-0.05 -> 0 | O60: -2000 | P60: =+Table134711[[#This Row],[Pagado por MVPX]]+Table134711[[#This Row],[Avance]]+P59 -> -6360.15
B61: 44990 | E61: PAYPAL | G61: Pago Por los Servicios de RCA | K61: =Table134711[[#This Row],[Valor de la Factura del Cliente]]*-0.2 -> 0 | L61: =+Table134711[[#This Row],[Valor de la Factura del Cliente]]*-0.05 -> 0 | O61: -1000 | P61: =+Table134711[[#This Row],[Pagado por MVPX]]+Table134711[[#This Row],[Avance]]+P60 -> -7360.15
B62: 45032 | E62: PAYPAL | G62: Pago Por los Servicios de RCA | K62: =Table134711[[#This Row],[Valor de la Factura del Cliente]]*-0.2 -> 0 | L62: =+Table134711[[#This Row],[Valor de la Factura del Cliente]]*-0.05 -> 0 | O62: -500 | P62: =+Table134711[[#This Row],[Pagado por MVPX]]+Table134711[[#This Row],[Avance]]+P61 -> -7860.15
... B65: 45077 | E65: PAYPAL | G65: Pago Por los Servicios de RCA | K65: =Table134711[[#This Row],[Valor de la Factura del Cliente]]*-0.2 -> 0 | L65: =+Table134711[[#This Row],[Valor de la Factura del Cliente]]*-0.05 -> 0 | O65: -1525 | P65: =+Table134711[[#This Row],[Pagado por MVPX]]+Table134711[[#This Row],[Avance]]+P64 -> -10910.15
B66: 45073 | C66: 7 | D66: Invoice | G66: Servicios Realizado ARC correspondiente April y Mach | K66: =Table134711[[#This Row],[Valor de la Factura del Cliente]]*-0.2 -> 0 | L66: =+Table134711[[#This Row],[Valor de la Factura del Cliente]]*-0.05 -> 0 | N66: 6000 | P66: =+Table134711[[#This Row],[Pagado por MVPX]]+Table134711[[#This Row],[Avance]]+P65 -> -4910.15
B67: 44966 | C67: 66 | D67: Invoice | G67: Servicios de Produccion de Vfro "Vivo Pensando" THE Change x Loui | H67: 5000 | K67: =Table134711[[#This Row],[Valor de la Factura del Cliente]]*-0.2 -> -1000 | L67: =+Table134711[[#This Row],[Valor de la Factura del Cliente]]*-0.05 -> -250 | N67: 3750 | P67: =+Table134711[[#This Row],[Pagado por MVPX]]+Table134711[[#This Row],[Avance]]+P66 -> -1160.15
B68: 45077 | C68: 82 | D68: Invoice | G68: Servicios de Produccion de Vfro y Okeiflou en el Tema "Paciente Por Ti" | H68: 5000 | K68: =Table134711[[#This Row],[Valor de la Factura del Cliente]]*-0.2 -> -1000 | L68: =+Table134711[[#This Row],[Valor de la Factura del Cliente]]*-0.05 -> -250 | N68: 3750 | P68: =+Table134711[[#This Row],[Pagado por MVPX]]+Table134711[[#This Row],[Avance]]+P67 -> 2589.85
B69: 45093 | E69: PAYPAL | G69: Pago Por los Servicios de RCA | K69: =Table134711[[#This Row],[Valor de la Factura del Cliente]]*-0.2 -> 0 | L69: =+Table134711[[#This Row],[Valor de la Factura del Cliente]]*-0.05 -> 0 | O69: -1000 | P69: =+Table134711[[#This Row],[Pagado por MVPX]]+Table134711[[#This Row],[Avance]]+P68 -> 1589.85
B70: 45116 | E70: PAYPAL | G70: Pago Por los Servicios de RCA | K70: =Table134711[[#This Row],[Valor de la Factura del Cliente]]*-0.2 -> 0 | L70: =+Table134711[[#This Row],[Valor de la Factura del Cliente]]*-0.05 -> 0 | O70: -500 | P70: =+Table134711[[#This Row],[Pagado por MVPX]]+Table134711[[#This Row],[Avance]]+P69 -> 1089.85
B71: 45118 | E71: PAYPAL | G71: Pago Por los Servicios de RCA | K71: =Table134711[[#This Row],[Valor de la Factura del Cliente]]*-0.2 -> 0 | L71: =+Table134711[[#This Row],[Valor de la Factura del Cliente]]*-0.05 -> 0 | O71: -600 | P71: =+Table134711[[#This Row],[Pagado por MVPX]]+Table134711[[#This Row],[Avance]]+P70 -> 489.85
B72: 45183 | E72: PAYPAL | G72: Pago Por los Servicios de RCA | K72: =Table134711[[#This Row],[Valor de la Factura del Cliente]]*-0.2 -> 0 | L72: =+Table134711[[#This Row],[Valor de la Factura del Cliente]]*-0.05 -> 0 | O72: -700 | P72: =+Table134711[[#This Row],[Pagado por MVPX]]+Table134711[[#This Row],[Avance]]+P71 -> -210.15
B73: 45184 | E73: PAYPAL | G73: Pago Por los Servicios de RCA | H73: 550.74 | K73: =Table134711[[#This Row],[Valor de la Factura del Cliente]]*-0.2 -> -110.148 | L73: =+Table134711[[#This Row],[Valor de la Factura del Cliente]]*-0.05 -> -27.537 | P73: =+Table134711[[#This Row],[Pagado por MVPX]]+Table134711[[#This Row],[Avance]]+P72 -> -210.15
G74: TOTAL | H74: =SUBTOTAL(109,Table134711[Valor de la Factura del Cliente]) -> 47277.91 | I74: =SUBTOTAL(109,Table134711[Cargos Bancarios]) -> -75 | K74: =SUBTOTAL(109,Table134711[20% Comisión]) -> -9455.582 | L74: =SUBTOTAL(109,Table134711[5% Legal]) -> -2363.8955 | M74: =SUBTOTAL(109,Table134711[Retención de Impuestos]) -> 0 | N74: =SUBTOTAL(109,Table134711[Pagado por MVPX]) -> 57575.12 | O74: =SUBTOTAL(109,Table134711[Avance]) -> -57785.27 | P74: =+P73 -> -210.15

Sheet ECBY
B2: Artista: | E2: ECBY
B3: Nombre legal: | E3: Erick CampoVerde
B4: Fecha de inicio: | E4: =MIN(Table134712[Fecha]) -> 43731
B5: Fecha fin: | E5: =MAX(Table134712[Fecha]) -> 45467
B7: ESTADO DE CUENTA
B8: Fecha | C8: Número | D8: Tipo | E8: Método de pago | F8: Nombre | G8: Concepto | H8: Valor de la Factura del Cliente | I8: Cargos Bancarios | J8: 50% Fee | K8: 20% Comisión | L8: 5% Legal | M8: Retención de Impuestos | N8: Pagado por MVPX | O8: Avance | P8: Balance
B9: 44046 | F9: Real Hasta La Muerte LLC | G9: Cost of providing production services 75% minus $ 15 wire transfer fee (Que se Joda) | H9: 2500 | I9: -15 | K9: =Table134712[[#This Row],[Valor de la Factura del Cliente]]*-0.2 -> -500 | L9: =+Table134712[[#This Row],[Valor de la Factura del Cliente]]*-0.05 -> -125 | N9: 1860 | P9: =+Table134712[[#This Row],[Pagado por MVPX]]-Table134712[[#This Row],[Avance]] -> 1860
B10: 44043 | F10: La Leyenda LLC | G10: Production Services for Yandel song "Ilegal" | H10: 3000 | K10: =Table134712[[#This Row],[Valor de la Factura del Cliente]]*-0.2 -> -600 | L10: =+Table134712[[#This Row],[Valor de la Factura del Cliente]]*-0.05 -> -150 | N10: 2500 | P10: =+Table134712[[#This Row],[Pagado por MVPX]]+P9-Table134712[[#This Row],[Avance]] -> 4360
B11: 44206 | F11: Rompe Records Music:Ecby (Erick R. Campoverde) | G11: Production services for Jay Maly "Mienteme" | H11: 3000 | I11: -15 | K11: =Table134712[[#This Row],[Valor de la Factura del Cliente]]*-0.2 -> -600 | L11: =+Table134712[[#This Row],[Valor de la Factura del Cliente]]*-0.05 -> -150 | N11: 2235 | P11: =+Table134712[[#This Row],[Pagado por MVPX]]+P10-Table134712[[#This Row],[Avance]] -> 6595
B12: 44831 | F12: Erick Campoverde/ECBY | G12: Production Services for "Leyenda Viva" | H12: 3000 | K12: =Table134712[[#This Row],[Valor de la Factura del Cliente]]*-0.2 -> -600 | L12: =+Table134712[[#This Row],[Valor de la Factura del Cliente]]*-0.05 -> -150 | N12: 2250 | P12: =+Table134712[[#This Row],[Pagado por MVPX]]+P11-Table134712[[#This Row],[Avance]] -> 8845
B13: 43731 | F13: Erick Campoverde/ECBY | G13: Payment hotel the Courtyard Sto Dgo | K13: =Table134712[[#This Row],[Valor de la Factura del Cliente]]*-0.2 -> 0 | L13: =+Table134712[[#This Row],[Valor de la Factura del Cliente]]*-0.05 -> 0 | O13: 66 | P13: =+Table134712[[#This Row],[Pagado por MVPX]]+P12-Table134712[[#This Row],[Avance]] -> 8779
B14: 44196 | F14: ST Music LLC | G14: Desde el Q3 2020 Hasta Q4 2023 | H14: 1702.61 | K14: =Table134712[[#This Row],[Valor de la Factura del Cliente]]*-0.2 -> -340.522 | L14: =+Table134712[[#This Row],[Valor de la Factura del Cliente]]*-0.05 -> -85.1305 | N14: 1276.9575 | P14: =+Table134712[[#This Row],[Pagado por MVPX]]+P13-Table134712[[#This Row],[Avance]] -> 10055.958
B15: 44056 | G15: Ordenador comprado para ECBY como anticipo | K15: =Table134712[[#This Row],[Valor de la Factura del Cliente]]*-0.2 -> 0 | L15: =+Table134712[[#This Row],[Valor de la Factura del Cliente]]*-0.05 -> 0 | O15: 2487.16 | P15: =+Table134712[[#This Row],[Pagado por MVPX]]+P14-Table134712[[#This Row],[Avance]] -> 7568.7975
B16: 44063 | F16: Avid Technology | G16: Protools para ECBY | K16: =Table134712[[#This Row],[Valor de la Factura del Cliente]]*-0.2 -> 0 | L16: =+Table134712[[#This Row],[Valor de la Factura del Cliente]]*-0.05 -> 0 | O16: 28 | P16: =+Table134712[[#This Row],[Pagado por MVPX]]+P15-Table134712[[#This Row],[Avance]] -> 7540.7975
B17: 44124 | F17: Avid Technology | G17: Protools para ECBY | K17: =Table134712[[#This Row],[Valor de la Factura del Cliente]]*-0.2 -> 0 | L17: =+Table134712[[#This Row],[Valor de la Factura del Cliente]]*-0.05 -> 0 | O17: 28 | P17: =+Table134712[[#This Row],[Pagado por MVPX]]+P16-Table134712[[#This Row],[Avance]] -> 7512.7975
B18: 44062 | F18: Julian Jose Coronel Diaz | G18: ECBY avanza para MAC | K18: =Table134712[[#This Row],[Valor de la Factura del Cliente]]*-0.2 -> 0 | L18: =+Table134712[[#This Row],[Valor de la Factura del Cliente]]*-0.05 -> 0 | O18: 98.19 | P18: =+Table134712[[#This Row],[Pagado por MVPX]]+P17-Table134712[[#This Row],[Avance]] -> 7414.6075
B19: 44064 | F19: Carlos Arturo Lascano Ruiz/ Kano | G19: Tasa de envío de dinero a Kano por los servicios de producción de "Ilegal" (Recuperable ECBY) | K19: =Table134712[[#This Row],[Valor de la Factura del Cliente]]*-0.2 -> 0 | L19: =+Table134712[[#This Row],[Valor de la Factura del Cliente]]*-0.05 -> 0 | O19: 48.79 | P19: =+Table134712[[#This Row],[Pagado por MVPX]]+P18-Table134712[[#This Row],[Avance]] -> 7365.8175
B20: 44064 | F20: Carlos Arturo Lascano Ruiz/ Kano | G20: Servicios de producción para "Crush" cubiertos por MVPX en nombre de ECBY (Pago efectuado como anticipo para ECBY) | K20: =Table134712[[#This Row],[Valor de la Factura del Cliente]]*-0.2 -> 0 | L20: =+Table134712[[#This Row],[Valor de la Factura del Cliente]]*-0.05 -> 0 | O20: 500 | P20: =+Table134712[[#This Row],[Pagado por MVPX]]+P19-Table134712[[#This Row],[Avance]] -> 6865.8175
B21: 44047 | F21: Western Union PR | G21: Pago a través de Western Union para el alquiler y la comida + 8 en honorarios (Propietario hizo el pago) | K21: =Table134712[[#This Row],[Valor de la Factura del Cliente]]*-0.2 -> 0 | L21: =+Table134712[[#This Row],[Valor de la Factura del Cliente]]*-0.05 -> 0 | O21: 308 | P21: =+Table134712[[#This Row],[Pagado por MVPX]]+P20-Table134712[[#This Row],[Avance]] -> 6557.8175
B22: 44037 | G22: Anticipo pagado a través de un préstamo a corto plazo realizado con Gesabeth (160 $ de gastos de transferencia) | K22: =Table134712[[#This Row],[Valor de la Factura del Cliente]]*-0.2 -> 0 | L22: =+Table134712[[#This Row],[Valor de la Factura del Cliente]]*-0.05 -> 0 | O22: 2443 | P22: =+Table134712[[#This Row],[Pagado por MVPX]]+P21-Table134712[[#This Row],[Avance]] -> 4114.8175
B23: 44093 | G23: Envio WU para gastos regulares del mes | K23: =Table134712[[#This Row],[Valor de la Factura del Cliente]]*-0.2 -> 0 | L23: =+Table134712[[#This Row],[Valor de la Factura del Cliente]]*-0.05 -> 0 | O23: 161 | P23: =+Table134712[[#This Row],[Pagado por MVPX]]+P22-Table134712[[#This Row],[Avance]] -> 3953.8175
B24: 44094 | G24: Envio WU para gastos regulares del mes | K24: =Table134712[[#This Row],[Valor de la Factura del Cliente]]*-0.2 -> 0 | L24: =+Table134712[[#This Row],[Valor de la Factura del Cliente]]*-0.05 -> 0 | O24: 161 | P24: =+Table134712[[#This Row],[Pagado por MVPX]]+P23-Table134712[[#This Row],[Avance]] -> 3792.8175
B25: 44112 | G25: Envio WU para gastos regulares | K25: =Table134712[[#This Row],[Valor de la Factura del Cliente]]*-0.2 -> 0 | L25: =+Table134712[[#This Row],[Valor de la Factura del Cliente]]*-0.05 -> 0 | O25: 311 | P25: =+Table134712[[#This Row],[Pagado por MVPX]]+P24-Table134712[[#This Row],[Avance]] -> 3481.8175
B26: 44123 | G26: Envio WU para gastos regulares | K26: =Table134712[[#This Row],[Valor de la Factura del Cliente]]*-0.2 -> 0 | L26: =+Table134712[[#This Row],[Valor de la Factura del Cliente]]*-0.05 -> 0 | O26: 311 | P26: =+Table134712[[#This Row],[Pagado por MVPX]]+P25-Table134712[[#This Row],[Avance]] -> 3170.8175
B27: 44131 | G27: Envio WU para gastos regulares | K27: =Table134712[[#This Row],[Valor de la Factura del Cliente]]*-0.2 -> 0 | L27: =+Table134712[[#This Row],[Valor de la Factura del Cliente]]*-0.05 -> 0 | O27: 500 | P27: =+Table134712[[#This Row],[Pagado por MVPX]]+P26-Table134712[[#This Row],[Avance]] -> 2670.8175
B28: 44172 | G28: Envio WU para gastos regulares | K28: =Table134712[[#This Row],[Valor de la Factura del Cliente]]*-0.2 -> 0 | L28: =+Table134712[[#This Row],[Valor de la Factura del Cliente]]*-0.05 -> 0 | O28: 721 | P28: =+Table134712[[#This Row],[Pagado por MVPX]]+P27-Table134712[[#This Row],[Avance]] -> 1949.8175
B29: 44207 | G29: Envio WU para gastos regulares | K29: =Table134712[[#This Row],[Valor de la Factura del Cliente]]*-0.2 -> 0 | L29: =+Table134712[[#This Row],[Valor de la Factura del Cliente]]*-0.05 -> 0 | O29: 796 | P29: =+Table134712[[#This Row],[Pagado por MVPX]]+P28-Table134712[[#This Row],[Avance]] -> 1153.8175
B30: 44228 | G30: Envio WU para gastos regulares | K30: =Table134712[[#This Row],[Valor de la Factura del Cliente]]*-0.2 -> 0 | L30: =+Table134712[[#This Row],[Valor de la Factura del Cliente]]*-0.05 -> 0 | O30: 478 | P30: =+Table134712[[#This Row],[Pagado por MVPX]]+P29-Table134712[[#This Row],[Avance]] -> 675.8175
B31: 44228 | G31: Envio WU para gastos regulares | K31: =Table134712[[#This Row],[Valor de la Factura del Cliente]]*-0.2 -> 0 | L31: =+Table134712[[#This Row],[Valor de la Factura del Cliente]]*-0.05 -> 0 | O31: 1404 | P31: =+Table134712[[#This Row],[Pagado por MVPX]]+P30-Table134712[[#This Row],[Avance]] -> -728.1825
B32: 44252 | G32: Envio WU para gastos regulares | K32: =Table134712[[#This Row],[Valor de la Factura del Cliente]]*-0.2 -> 0 | L32: =+Table134712[[#This Row],[Valor de la Factura del Cliente]]*-0.05 -> 0 | O32: 165 | P32: =+Table134712[[#This Row],[Pagado por MVPX]]+P31-Table134712[[#This Row],[Avance]] -> -893.1825
B33: 44264 | G33: Envio WU para gastos regulares | K33: =Table134712[[#This Row],[Valor de la Factura del Cliente]]*-0.2 -> 0 | L33: =+Table134712[[#This Row],[Valor de la Factura del Cliente]]*-0.05 -> 0 | O33: 205 | P33: =+Table134712[[#This Row],[Pagado por MVPX]]+P32-Table134712[[#This Row],[Avance]] -> -1098.1825
... B57: 44959 | G57: Planet Fitnes | K57: =Table134712[[#This Row],[Valor de la Factura del Cliente]]*-0.2 -> 0 | L57: =+Table134712[[#This Row],[Valor de la Factura del Cliente]]*-0.05 -> 0 | O57: 5.58 | P57: =+Table134712[[#This Row],[Pagado por MVPX]]+P56-Table134712[[#This Row],[Avance]] -> -4715.1925
B58: 44991 | G58: Servicios en Tanda, La Escena, Como si fuera uno mas | H58: 3600 | K58: =Table134712[[#This Row],[Valor de la Factura del Cliente]]*-0.2 -> -720 | L58: =+Table134712[[#This Row],[Valor de la Factura del Cliente]]*-0.05 -> -180 | N58: 2700 | P58: =+Table134712[[#This Row],[Pagado por MVPX]]+P57-Table134712[[#This Row],[Avance]] -> -2015.1925
B59: 45061 | G59: Planet Fitnes | K59: =Table134712[[#This Row],[Valor de la Factura del Cliente]]*-0.2 -> 0 | L59: =+Table134712[[#This Row],[Valor de la Factura del Cliente]]*-0.05 -> 0 | O59: 27.87 | P59: =+Table134712[[#This Row],[Pagado por MVPX]]+P58-Table134712[[#This Row],[Avance]] -> -2043.0625
B60: 45062 | G60: Planet Fitnes | K60: =Table134712[[#This Row],[Valor de la Factura del Cliente]]*-0.2 -> 0 | L60: =+Table134712[[#This Row],[Valor de la Factura del Cliente]]*-0.05 -> 0 | O60: 27.87 | P60: =+Table134712[[#This Row],[Pagado por MVPX]]+P59-Table134712[[#This Row],[Avance]] -> -2070.9325
B61: 45021 | G61: Airplane Ticket Arajet -Guayaquil RD | K61: =Table134712[[#This Row],[Valor de la Factura del Cliente]]*-0.2 -> 0 | L61: =+Table134712[[#This Row],[Valor de la Factura del Cliente]]*-0.05 -> 0 | O61: 308.74 | P61: =+Table134712[[#This Row],[Pagado por MVPX]]+P60-Table134712[[#This Row],[Avance]] -> -2379.6725
B62: 45027 | G62: Adelanto solicitado | K62: =Table134712[[#This Row],[Valor de la Factura del Cliente]]*-0.2 -> 0 | L62: =+Table134712[[#This Row],[Valor de la Factura del Cliente]]*-0.05 -> 0 | O62: 150 | P62: =+Table134712[[#This Row],[Pagado por MVPX]]+P61-Table134712[[#This Row],[Avance]] -> -2529.6725
B63: 45065 | G63: Payment of air ticket from Santo Domingo to Puerto Rico | K63: =Table134712[[#This Row],[Valor de la Factura del Cliente]]*-0.2 -> 0 | L63: =+Table134712[[#This Row],[Valor de la Factura del Cliente]]*-0.05 -> 0 | O63: 112.7 | P63: =+Table134712[[#This Row],[Pagado por MVPX]]+P62-Table134712[[#This Row],[Avance]] -> -2642.3725
B64: 45054 | G64: Gastos de Produccion y Grabación | K64: =Table134712[[#This Row],[Valor de la Factura del Cliente]]*-0.2 -> 0 | L64: =+Table134712[[#This Row],[Valor de la Factura del Cliente]]*-0.05 -> 0 | O64: 260.99 | P64: =+Table134712[[#This Row],[Pagado por MVPX]]+P63-Table134712[[#This Row],[Avance]] -> -2903.3625
B65: 45071 | G65: Advance to producers | K65: =Table134712[[#This Row],[Valor de la Factura del Cliente]]*-0.2 -> 0 | L65: =+Table134712[[#This Row],[Valor de la Factura del Cliente]]*-0.05 -> 0 | O65: 200 | P65: =+Table134712[[#This Row],[Pagado por MVPX]]+P64-Table134712[[#This Row],[Avance]] -> -3103.3625
B66: 45092 | G66: Planet Fitnes | K66: =Table134712[[#This Row],[Valor de la Factura del Cliente]]*-0.2 -> 0 | L66: =+Table134712[[#This Row],[Valor de la Factura del Cliente]]*-0.05 -> 0 | O66: 27.87 | P66: =+Table134712[[#This Row],[Pagado por MVPX]]+P65-Table134712[[#This Row],[Avance]] -> -3131.2325
B67: 45122 | G67: Planet Fitnes | K67: =Table134712[[#This Row],[Valor de la Factura del Cliente]]*-0.2 -> 0 | L67: =+Table134712[[#This Row],[Valor de la Factura del Cliente]]*-0.05 -> 0 | O67: 27.87 | P67: =+Table134712[[#This Row],[Pagado por MVPX]]+P66-Table134712[[#This Row],[Avance]] -> -3159.1025
B68: 45128 | G68: Avance | K68: =Table134712[[#This Row],[Valor de la Factura del Cliente]]*-0.2 -> 0 | L68: =+Table134712[[#This Row],[Valor de la Factura del Cliente]]*-0.05 -> 0 | O68: 1000 | P68: =+Table134712[[#This Row],[Pagado por MVPX]]+P67-Table134712[[#This Row],[Avance]] -> -4159.1025
B69: 45139 | G69: Avance | K69: =Table134712[[#This Row],[Valor de la Factura del Cliente]]*-0.2 -> 0 | L69: =+Table134712[[#This Row],[Valor de la Factura del Cliente]]*-0.05 -> 0 | O69: 300 | P69: =+Table134712[[#This Row],[Pagado por MVPX]]+P68-Table134712[[#This Row],[Avance]] -> -4459.1025
B70: 45172 | G70: Adelanto | K70: =Table134712[[#This Row],[Valor de la Factura del Cliente]]*-0.2 -> 0 | L70: =+Table134712[[#This Row],[Valor de la Factura del Cliente]]*-0.05 -> 0 | O70: 450 | P70: =+Table134712[[#This Row],[Pagado por MVPX]]+P69-Table134712[[#This Row],[Avance]] -> -4909.1025
B71: 45082 | G71: Beat Gracias al Cielo del Amor y Yo Jay Wheeler | H71: 1000 | K71: =Table134712[[#This Row],[Valor de la Factura del Cliente]]*-0.2 -> -200 | L71: =+Table134712[[#This Row],[Valor de la Factura del Cliente]]*-0.05 -> -50 | N71: 750 | P71: =+Table134712[[#This Row],[Pagado por MVPX]]+P70-Table134712[[#This Row],[Avance]] -> -4159.1025
B72: 45211 | G72: Avance | K72: =Table134712[[#This Row],[Valor de la Factura del Cliente]]*-0.2 -> 0 | L72: =+Table134712[[#This Row],[Valor de la Factura del Cliente]]*-0.05 -> 0 | O72: 600 | P72: =+Table134712[[#This Row],[Pagado por MVPX]]+P71-Table134712[[#This Row],[Avance]] -> -4759.1025
B73: 45222 | G73: Avance Gladys Celis | K73: =Table134712[[#This Row],[Valor de la Factura del Cliente]]*-0.2 -> 0 | L73: =+Table134712[[#This Row],[Valor de la Factura del Cliente]]*-0.05 -> 0 | O73: 350 | P73: =+Table134712[[#This Row],[Pagado por MVPX]]+P72-Table134712[[#This Row],[Avance]] -> -5109.1025
B74: 45450 | G74: Avance Video Renn | K74: =Table134712[[#This Row],[Valor de la Factura del Cliente]]*-0.2 -> 0 | L74: =+Table134712[[#This Row],[Valor de la Factura del Cliente]]*-0.05 -> 0 | O74: 500 | P74: =+Table134712[[#This Row],[Pagado por MVPX]]+P73-Table134712[[#This Row],[Avance]] -> -5609.1025
B75: 45453 | G75: Avance Video Renn | K75: =Table134712[[#This Row],[Valor de la Factura del Cliente]]*-0.2 -> 0 | L75: =+Table134712[[#This Row],[Valor de la Factura del Cliente]]*-0.05 -> 0 | O75: 430.99 | P75: =+Table134712[[#This Row],[Pagado por MVPX]]+P74-Table134712[[#This Row],[Avance]] -> -6040.0925
B76: 45463 | G76: Factura Luiggi 21 | H76: 1940.2 | I76: -25 | K76: =Table134712[[#This Row],[Valor de la Factura del Cliente]]*-0.2 -> -388.04 | L76: =+Table134712[[#This Row],[Valor de la Factura del Cliente]]*-0.05 -> -97.01 | N76: 1430.15 | P76: =+Table134712[[#This Row],[Pagado por MVPX]]+P75-Table134712[[#This Row],[Avance]] -> -4609.9425
B77: 45467 | G77: Adelanto | K77: =Table134712[[#This Row],[Valor de la Factura del Cliente]]*-0.2 -> 0 | L77: =+Table134712[[#This Row],[Valor de la Factura del Cliente]]*-0.05 -> 0 | O77: 200 | P77: =+Table134712[[#This Row],[Pagado por MVPX]]+P76-Table134712[[#This Row],[Avance]] -> -4809.9425
G78: TOTAL | H78: =SUBTOTAL(109,Table134712[Valor de la Factura del Cliente]) -> 19742.81 | I78: =SUBTOTAL(109,Table134712[Cargos Bancarios]) -> -55 | K78: =SUBTOTAL(109,Table134712[20% Comisión]) -> -3948.562 | L78: =SUBTOTAL(109,Table134712[5% Legal]) -> -987.1405 | M78: =SUBTOTAL(109,Table134712[Retención de Impuestos]) -> 0 | N78: =SUBTOTAL(109,Table134712[Pagado por MVPX]) -> 15002.108 | O78: =SUBTOTAL(109,Table134712[Avance]) -> 19812.05 | P78: =+#REF! -> #REF!

Sheet Saint LL
B2: Artista: | E2: Saint LL
B3: Nombre legal:
B4: Fecha de inicio: | E4: =MIN(Table134713[Fecha]) -> 45694
B5: Fecha fin: | E5: =MAX(Table134713[Fecha]) -> 45864
B7: ESTADO DE CUENTA
B8: Fecha | C8: Número | D8: Tipo | E8: Método de pago | F8: Nombre | G8: Concepto | H8: Valor de la Factura del Cliente | I8: Cargos Bancarios | J8: 50% Fee | K8: 20% Comisión | L8: 5% Legal | M8: Retención de Impuestos | N8: Pagado por MVPX | O8: Avance | P8: Balance
B9: 45694 | F9: Lucas Romero | G9: Producción de composición de los temas "CULEO" & "No Puedo Decifrar" | H9: 0 | I9: 0 | K9: 0 | L9: 0 | M9: 0 | N9: 200 | O9: 0 | P9: =-Table134713[[#This Row],[Pagado por MVPX]] -> -200
B10: 45738 | F10: Lucas Birgy | G10: Gastos de Videos Musicales | H10: 0 | I10: 0 | K10: 0 | L10: 0 | M10: 0 | N10: 418.4 | O10: 0 | P10: =+P9-Table134713[[#This Row],[Pagado por MVPX]] -> -618.4
B11: 45719 | F11: Hotel.com | G11: Gastos Víaticos | H11: 0 | I11: 0 | K11: 0 | L11: 0 | M11: 0 | N11: 17.36 | O11: 0 | P11: =+P10-Table134713[[#This Row],[Pagado por MVPX]] -> -635.76
B12: 45711 | F12: Airbnb | G12: Gastos Víaticos | H12: 0 | I12: 0 | K12: 0 | L12: 0 | M12: 0 | N12: 317.45 | O12: 0 | P12: =+P11-Table134713[[#This Row],[Pagado por MVPX]] -> -953.21
B13: 45721 | F13: Hertz | G13: Gastos Víaticos en Argentina | H13: 0 | I13: 0 | K13: 0 | L13: 0 | M13: 0 | N13: 356.29 | O13: 0 | P13: =+P12-Table134713[[#This Row],[Pagado por MVPX]] -> -1309.5
B14: 45721 | F14: McDonalds | G14: Gastos Víaticos en Argentina | H14: 0 | I14: 0 | K14: 0 | L14: 0 | M14: 0 | N14: 53.09 | O14: 0 | P14: =+P13-Table134713[[#This Row],[Pagado por MVPX]] -> -1362.59
B15: 45722 | F15: Uber*Trip | G15: Gastos Víaticos en Argentina | H15: 0 | I15: 0 | K15: 0 | L15: 0 | M15: 0 | N15: 30.12 | O15: 0 | P15: =+P14-Table134713[[#This Row],[Pagado por MVPX]] -> -1392.71
B16: 45722 | F16: Mercado Pago | G16: Gastos Víaticos en Argentina | H16: 0 | I16: 0 | K16: 0 | L16: 0 | M16: 0 | N16: 48.64 | O16: 0 | P16: =+P15-Table134713[[#This Row],[Pagado por MVPX]] -> -1441.35
B17: 45723 | F17: Pomifa Pigue | G17: Gastos Víaticos en Argentina | H17: 0 | I17: 0 | K17: 0 | L17: 0 | M17: 0 | N17: 139.04 | O17: 0 | P17: =+P16-Table134713[[#This Row],[Pagado por MVPX]] -> -1580.39
B18: 45724 | F18: LaMoraArroyo | G18: Gastos Víaticos en Argentina | H18: 0 | I18: 0 | K18: 0 | L18: 0 | M18: 0 | N18: 62.35 | O18: 0 | P18: =+P17-Table134713[[#This Row],[Pagado por MVPX]] -> -1642.74
B19: 45724 | F19: LaMoraArroyo | G19: Gastos Víaticos en Argentina | H19: 0 | I19: 0 | K19: 0 | L19: 0 | M19: 0 | N19: 6.11 | O19: 0 | P19: =+P18-Table134713[[#This Row],[Pagado por MVPX]] -> -1648.85
B20: 45726 | F20: Granja Pigue | G20: Gastos Víaticos en Argentina | H20: 0 | I20: 0 | K20: 0 | L20: 0 | M20: 0 | N20: 19.04 | O20: 0 | P20: =+P19-Table134713[[#This Row],[Pagado por MVPX]] -> -1667.89
B21: 45726 | F21: LaMoraArroyo | G21: Gastos Víaticos en Argentina | H21: 0 | I21: 0 | K21: 0 | L21: 0 | M21: 0 | N21: 33.01 | O21: 0 | P21: =+P20-Table134713[[#This Row],[Pagado por MVPX]] -> -1700.9
... B35: 45864 | F35: Lucas Birgy | G35: Gastos de Videos Musicales | H35: 0 | I35: 0 | K35: 0 | L35: 0 | M35: 0 | N35: 200 | O35: 0 | P35: =+P34-Table134713[[#This Row],[Pagado por MVPX]] -> -2988.83
G36: TOTAL | H36: =SUBTOTAL(109,Table134713[Valor de la Factura del Cliente]) -> 0 | I36: =SUBTOTAL(109,Table134713[Cargos Bancarios]) -> 0 | K36: =SUBTOTAL(109,Table134713[20% Comisión]) -> 0 | L36: =SUBTOTAL(109,Table134713[5% Legal]) -> 0 | M36: =SUBTOTAL(109,Table134713[Retención de Impuestos]) -> 0 | N36: =SUBTOTAL(109,Table134713[Pagado por MVPX]) -> 2988.83 | O36: =SUBTOTAL(109,Table134713[Avance]) -> 0 | P36: =+P35 -> -2988.83

Sheet Cesar Da Gold
B2: Artista: | E2: Cesar Da Gold
B3: Nombre legal: | E3: =+E2 -> Cesar Da Gold
B4: Fecha de inicio: | E4: =MIN(Table13471516[Fecha]) -> 44907
B5: Fecha fin: | E5: =MAX(Table13471516[Fecha]) -> 45380
B7: ESTADO DE CUENTA
B8: Fecha | C8: Número | D8: Tipo | E8: Método de pago | F8: Nombre | G8: Concepto | H8: Valor de la Factura del Cliente | I8: Cargos Bancarios | J8: 50% Fee | K8: 20% Comisión | L8: 5% Legal | M8: Retención de Impuestos | N8: Pagado por MVPX | O8: Avance | P8: Balance
B9: 44918 | F9: Cesar Da Gold | G9: Avance Cesar Pulgarin | K9: 0 | L9: 0 | O9: -2500 | P9: =+Table13471516[[#This Row],[Valor de la Factura del Cliente]]+Table13471516[[#This Row],[Avance]] -> -2500
B10: 44907 | F10: Cesar Da Gold | G10: Avance Cesar Pulgarin | K10: 0 | L10: 0 | O10: -1000 | P10: =+Table13471516[[#This Row],[Valor de la Factura del Cliente]]+Table13471516[[#This Row],[Avance]]+P9 -> -3500
B11: 45004 | F11: Cesar Da Gold | G11: Avance Cesar Pulgarin | K11: 0 | L11: 0 | O11: -525 | P11: =+Table13471516[[#This Row],[Valor de la Factura del Cliente]]+Table13471516[[#This Row],[Avance]]+P10 -> -4025
B12: 44994 | F12: Cesar Da Gold | G12: Saldo de Danny ocean | K12: 0 | L12: 0 | O12: -2325 | P12: =+Table13471516[[#This Row],[Valor de la Factura del Cliente]]+Table13471516[[#This Row],[Avance]]+P11 -> -6350
B13: 45015 | F13: Cesar Da Gold | G13: Avance Cesar Pulgarin | K13: 0 | L13: 0 | O13: -500 | P13: =+Table13471516[[#This Row],[Valor de la Factura del Cliente]]+Table13471516[[#This Row],[Avance]]+P12 -> -6850
B14: 45029 | F14: Cesar Da Gold | G14: Avance Cesar Pulgarin | K14: 0 | L14: 0 | O14: -500 | P14: =+Table13471516[[#This Row],[Valor de la Factura del Cliente]]+Table13471516[[#This Row],[Avance]]+P13 -> -7350
B15: 45077 | F15: Cesar Da Gold | G15: Avance Cesar Pulgarin | K15: 0 | L15: 0 | O15: -700 | P15: =+Table13471516[[#This Row],[Valor de la Factura del Cliente]]+Table13471516[[#This Row],[Avance]]+P14 -> -8050
B16: 45047 | F16: Cesar Da Gold | G16: Avance Cesar Pulgarin | K16: 0 | L16: 0 | O16: -200 | P16: =+Table13471516[[#This Row],[Valor de la Factura del Cliente]]+Table13471516[[#This Row],[Avance]]+P15 -> -8250
B17: 45103 | F17: Cesar Da Gold | G17: Avance Cesar Pulgarin | K17: 0 | L17: 0 | O17: -520 | P17: =+Table13471516[[#This Row],[Valor de la Factura del Cliente]]+Table13471516[[#This Row],[Avance]]+P16 -> -8770
B18: 45134 | F18: Cesar Da Gold | G18: Avance Cesar Pulgarin | K18: 0 | L18: 0 | O18: -400 | P18: =+Table13471516[[#This Row],[Valor de la Factura del Cliente]]+Table13471516[[#This Row],[Avance]]+P17 -> -9170
B19: 45139 | F19: Cesar Da Gold | G19: Avance Cesar Pulgarin | K19: 0 | L19: 0 | O19: -300 | P19: =+Table13471516[[#This Row],[Valor de la Factura del Cliente]]+Table13471516[[#This Row],[Avance]]+P18 -> -9470
B20: 45163 | F20: Cesar Da Gold | G20: Avance Cesar Pulgarin | K20: 0 | L20: 0 | O20: -300 | P20: =+Table13471516[[#This Row],[Valor de la Factura del Cliente]]+Table13471516[[#This Row],[Avance]]+P19 -> -9770
B21: 45180 | F21: Cesar Da Gold | G21: Avance Cesar Pulgarin | K21: 0 | L21: 0 | O21: -300 | P21: =+Table13471516[[#This Row],[Valor de la Factura del Cliente]]+Table13471516[[#This Row],[Avance]]+P20 -> -10070
B22: 45191 | F22: Rimas Music | G22: Invoice Polvora 6000, 1000 a marval y 1875 a chochi + 1875 a nikko | H22: 5000 | K22: 1000 | L22: 250 | N22: -1875 | O22: -1875 | P22: -10945
B23: 45201 | F23: Cesar Da Gold | G23: Abono Invoice No te Enamores | K23: 0 | L23: 0 | O23: -1500 | P23: -12445
B24: 45232 | F24: Cesar Da Gold | G24: Abono Invoice No te Enamores | K24: 0 | L24: 0 | O24: -500 | P24: -12945
B25: 45264 | F25: Cesar Da Gold | G25: Abono Invoice No te Enamores | K25: 0 | L25: 0 | O25: -500 | P25: -13445
B26: 45272 | F26: Cesar Da Gold | G26: Abono Invoice No te Enamores | K26: 0 | L26: 0 | O26: -300 | P26: -13745
